Workbook
Name Direccion: 'Blok Presupuesto'!$F$8:$G$8
Name Listado: 'Blok Presupuesto'!$B$15:$H$32
Name Cliente: 'Blok Presupuesto'!$F$6:$G$6
Name Cliente: Presupuesto!$F$6:$G$6
Name Listado: Presupuesto!$B$15:$H$32
Name Direccion: Presupuesto!$F$8:$G$8
Name Fecha: 'Blok Presupuesto'!$F$4:$G$4
Name Fecha: Presupuesto!$F$4:$G$4

Sheet Nota
A1: =Presupuesto!A15 | B1: =IFERROR(VLOOKUP(Carga!B8,Precios!D:F,8,0), "") | C1: / | D1: =CONCATENATE(" ",C1," ",A1," ",B1) -> /
A2: =Presupuesto!A16 | B2: =IFERROR(VLOOKUP(Carga!B9,Precios!D:F,8,0), "") | C2: / | D2: =CONCATENATE(" / ",A2," ",B2) -> /
A3: =Presupuesto!A17 | B3: =IFERROR(VLOOKUP(Carga!B10,Precios!D:F,8,0), "") | C3: / | D3: =CONCATENATE(" / ",A3," ",B3) -> /
A4: =Presupuesto!A18 | B4: =IFERROR(VLOOKUP(Carga!B11,Precios!D:F,8,0), "") | C4: / | D4: =CONCATENATE(" / ",A4," ",B4) -> /
A5: =Presupuesto!A19 | B5: =IFERROR(VLOOKUP(Carga!B12,Precios!D:F,8,0), "") | C5: / | D5: =CONCATENATE(" / ",A5," ",B5) -> /
A6: =Presupuesto!A20 | B6: =IFERROR(VLOOKUP(Carga!B13,Precios!D:F,8,0), "") | C6: / | D6: =CONCATENATE(" / ",A6," ",B6) -> /
A7: =Presupuesto!A21 | B7: =IFERROR(VLOOKUP(Carga!B14,Precios!D:F,8,0), "") | C7: / | D7: =CONCATENATE(" / ",A7," ",B7) -> /
A8: =Presupuesto!A22 | B8: =IFERROR(VLOOKUP(Carga!B15,Precios!D:F,8,0), "") | C8: / | D8: =CONCATENATE(" / ",A8," ",B8) -> /
A9: =Presupuesto!A23 | B9: =IFERROR(VLOOKUP(Carga!B16,Precios!D:F,8,0), "") | C9: / | D9: =CONCATENATE(" / ",A9," ",B9) -> /
A10: =Presupuesto!A24 | B10: =IFERROR(VLOOKUP(Carga!B17,Precios!D:F,8,0), "") | C10: / | D10: =CONCATENATE(" / ",A10," ",B10) -> /
A11: =Presupuesto!A25 | B11: =IFERROR(VLOOKUP(Carga!B18,Precios!D:F,8,0), "") | C11: / | D11: =CONCATENATE(" / ",A11," ",B11) -> /
A12: =Presupuesto!A26 | B12: =IFERROR(VLOOKUP(Carga!B19,Precios!D:F,8,0), "") | C12: / | D12: =CONCATENATE(" / ",A12," ",B12) -> /
A13: =Presupuesto!A27 | B13: =IFERROR(VLOOKUP(Carga!B20,Precios!D:F,8,0), "") | C13: / | D13: =CONCATENATE(" / ",A13," ",B13) -> /
... A23: =Presupuesto!A37 | B23: =IFERROR(VLOOKUP(Carga!B30,Precios!D:F,8,0), "") | C23: / | D23: =CONCATENATE(" / ",A23," ",B23) -> /
E24: =CONCATENATE(D1:D23) -> / / / / / / / / / / / / / / / / / / / / / / /

Sheet Hoja8
A1: Concepto | B1: Cantidad | C1: Detalle ingresado | D1: precio unitario | E1: desc | F1: Total
A2: 46072 | B2: Villagrono Alfredus | C2: 3513559347 | D2: Enrique banchs 3281 los alamos
A3: Instalación a altura h<4mts con perfil C P/ BPC 100 a 300 | B3: 1 | C3: 43400 | D3: 43400 | F3: TOTAL
A4: Instalación a altura h<4mts con perfil C P/ BPC 100 a 300 | B4: 1 | C4: 43400 | D4: 43400 | F4: 292800
A5: Instalación a altura h<4mts con perfil C P/ BPC 100 a 300 | B5: 1 | C5: 43400 | D5: 43400 | F5: 292800
A6: Instalación a altura h<4mts con perfil C P/ BPC 100 a 300 | B6: 1 | C6: 43400 | D6: 43400 | F6: 292800
A7: Instalación a altura h<4mts con perfil C P/ BPC 100 a 300 | B7: 1 | C7: 43400 | D7: 43400 | F7: -180000
A8: Instalación a altura h<4mts con perfil C P/ BPC 100 a 300 | B8: 1 | C8: 43400 | D8: 2.387e+16 | F8: -180000
A9: Certificacion de vivienda o local comercial (hasta 20bocas) no incluye adecuacion de la instalacion | B9: -2 | D9: 180000 | E9: 0 | F9: -360000
A10: Certificacion de vivienda o local comercial (hasta 20bocas) no incluye adecuacion de la instalacion | B10: -2 | D10: 180000 | E10: 0 | F10: -360000
A11: Certificacion de vivienda o local comercial (hasta 20bocas) no incluye adecuacion de la instalacion | B11: -2 | D11: 180000 | E11: 0 | F11: -360000
A12: Certificacion de vivienda o local comercial (hasta 20bocas) no incluye adecuacion de la instalacion | B12: -2 | D12: 180000 | E12: 0 | F12: -360000
A13: Certificacion de vivienda o local comercial (hasta 20bocas) no incluye adecuacion de la instalacion | B13: -2 | D13: 180000 | E13: 0 | F13: -360000
A14: Certificacion de vivienda o local comercial (hasta 20bocas) no incluye adecuacion de la instalacion | B14: -2 | D14: 180000 | E14: 0 | F14: -360000
A15: Certificacion de vivienda o local comercial (hasta 20bocas) no incluye adecuacion de la instalacion | B15: -2 | D15: 180000 | E15: 0 | F15: -360000
A16: Certificacion de vivienda o local comercial (hasta 20bocas) no incluye adecuacion de la instalacion | B16: -2 | D16: 180000 | E16: 0 | F16: -360000
A17: Certificacion de vivienda o local comercial (hasta 20bocas) no incluye adecuacion de la instalacion | B17: -2 | D17: 180000 | E17: 0 | F17: -360000
A18: Certificacion de vivienda o local comercial (hasta 20bocas) no incluye adecuacion de la instalacion | B18: -2 | D18: 180000 | E18: 0 | F18: -360000
A19: Certificacion de vivienda o local comercial (hasta 20bocas) no incluye adecuacion de la instalacion | B19: -2 | D19: 180000 | E19: 0 | F19: -360000
A20: Certificacion de vivienda o local comercial (hasta 20bocas) no incluye adecuacion de la instalacion | B20: -2 | D20: 180000 | E20: 0 | F20: -360000
... A36: Certificacion de vivienda o local comercial (hasta 20bocas) no incluye adecuacion de la instalacion | B36: -2 | D36: 180000 | E36: 0 | F36: -360000
A37: Certificacion de vivienda o local comercial (hasta 20bocas) no incluye adecuacion de la instalacion | B37: -2 | C37: Jkota | D37: 180000 | E37: 0 | F37: -360000

Sheet Clientes
A1: =IFERROR(__xludf.DUMMYFUNCTION("IMPORTRANGE(""https://docs.google.com/spreadsheets/d/1aPynYCYBaEafPC4rqTulMOzPg_guy_NLzZHOzvFJwyw/edit?usp=drivesdk"", ""Respuestas de formulario 1!A1:H150"")"),"Marca temporal") -> Marca temporal | B1: =IFERROR(__xludf.DUMMYFUNCTION("""COMPUTED_VALUE"""),"Apellido y Nombre") -> Apellido y Nombre | C1: =IFERROR(__xludf.DUMMYFUNCTION("""COMPUTED_VALUE"""),"Teléfono") -> Teléfono | D1: =IFERROR(__xludf.DUMMYFUNCTION("""COMPUTED_VALUE"""),"Dirección") -> Dirección | E1: =IFERROR(__xludf.DUMMYFUNCTION("""COMPUTED_VALUE"""),"Observaciones ") -> Observaciones
A2: =IFERROR(__xludf.DUMMYFUNCTION("""COMPUTED_VALUE"""),46065.8989693287) -> 46065.899 | B2: =IFERROR(__xludf.DUMMYFUNCTION("""COMPUTED_VALUE"""),"Villagrono Alfredus") -> Villagrono Alfredus | C2: =IFERROR(__xludf.DUMMYFUNCTION("""COMPUTED_VALUE"""),3.513559347E9) -> 3513559347 | D2: =IFERROR(__xludf.DUMMYFUNCTION("""COMPUTED_VALUE"""),"Enrique banchs 3281 los alamos") -> Enrique banchs 3281 los alamos | E2: =IFERROR(__xludf.DUMMYFUNCTION("""COMPUTED_VALUE"""),"Alfredus Alfredus") -> Alfredus Alfredus
A3: =IFERROR(__xludf.DUMMYFUNCTION("""COMPUTED_VALUE"""),46065.90200585648) -> 46065.902 | B3: =IFERROR(__xludf.DUMMYFUNCTION("""COMPUTED_VALUE"""),"Federico Matisaleno") -> Federico Matisaleno | C3: =IFERROR(__xludf.DUMMYFUNCTION("""COMPUTED_VALUE"""),3.518469723E9) -> 3518469723 | D3: =IFERROR(__xludf.DUMMYFUNCTION("""COMPUTED_VALUE"""),"Domingo Zipoli 542 Cordoba ") -> Domingo Zipoli 542 Cordoba
A4: =IFERROR(__xludf.DUMMYFUNCTION("""COMPUTED_VALUE"""),46065.914829490735) -> 46065.915 | B4: =IFERROR(__xludf.DUMMYFUNCTION("""COMPUTED_VALUE"""),"Lucianote Pabarotiitii") -> Lucianote Pabarotiitii | C4: =IFERROR(__xludf.DUMMYFUNCTION("""COMPUTED_VALUE"""),3.513559347E9) -> 3513559347 | D4: =IFERROR(__xludf.DUMMYFUNCTION("""COMPUTED_VALUE"""),"Domingo Funesialo 54612 Barro Campañaioni") -> Domingo Funesialo 54612 Barro Campañaioni
A5: =IFERROR(__xludf.DUMMYFUNCTION("""COMPUTED_VALUE"""),46065.91937481481) -> 46065.919 | B5: =IFERROR(__xludf.DUMMYFUNCTION("""COMPUTED_VALUE"""),"Gorgoto") -> Gorgoto | C5: =IFERROR(__xludf.DUMMYFUNCTION("""COMPUTED_VALUE"""),3.513559347E9) -> 3513559347 | D5: =IFERROR(__xludf.DUMMYFUNCTION("""COMPUTED_VALUE"""),"Jsjsjjd bsjsj 51518 vdbjdj") -> Jsjsjjd bsjsj 51518 vdbjdj
A6: =IFERROR(__xludf.DUMMYFUNCTION("""COMPUTED_VALUE"""),46067.909977083335) -> 46067.91 | B6: =IFERROR(__xludf.DUMMYFUNCTION("""COMPUTED_VALUE"""),"Lolito Supertino") -> Lolito Supertino | C6: =IFERROR(__xludf.DUMMYFUNCTION("""COMPUTED_VALUE"""),3.513559347E9) -> 3513559347 | D6: =IFERROR(__xludf.DUMMYFUNCTION("""COMPUTED_VALUE"""),"Bulevares de san juan 3456 Barrio Lopes de vega") -> Bulevares de san juan 3456 Barrio Lopes de vega
A7: =IFERROR(__xludf.DUMMYFUNCTION("""COMPUTED_VALUE"""),46068.722087222224) -> 46068.722 | B7: =IFERROR(__xludf.DUMMYFUNCTION("""COMPUTED_VALUE"""),"Federico Orellano") -> Federico Orellano | C7: =IFERROR(__xludf.DUMMYFUNCTION("""COMPUTED_VALUE"""),3.513559347E9) -> 3513559347 | D7: =IFERROR(__xludf.DUMMYFUNCTION("""COMPUTED_VALUE"""),"Prueba 1234 Bro Prueba 1 cp 4321") -> Prueba 1234 Bro Prueba 1 cp 4321 | E7: =IFERROR(__xludf.DUMMYFUNCTION("""COMPUTED_VALUE"""),"Ywwjye") -> Ywwjye
A8: =IFERROR(__xludf.DUMMYFUNCTION("""COMPUTED_VALUE"""),46068.72213230324) -> 46068.722 | B8: =IFERROR(__xludf.DUMMYFUNCTION("""COMPUTED_VALUE"""),"Federico Orellano") -> Federico Orellano | C8: =IFERROR(__xludf.DUMMYFUNCTION("""COMPUTED_VALUE"""),3.513559347E9) -> 3513559347 | D8: =IFERROR(__xludf.DUMMYFUNCTION("""COMPUTED_VALUE"""),"Prueba 1234 Bro Prueba 1 cp 4321") -> Prueba 1234 Bro Prueba 1 cp 4321 | E8: =IFERROR(__xludf.DUMMYFUNCTION("""COMPUTED_VALUE"""),"eiie") -> eiie
A9: =IFERROR(__xludf.DUMMYFUNCTION("""COMPUTED_VALUE"""),46068.722922430556) -> 46068.723 | B9: =IFERROR(__xludf.DUMMYFUNCTION("""COMPUTED_VALUE"""),"Juanito") -> Juanito | C9: =IFERROR(__xludf.DUMMYFUNCTION("""COMPUTED_VALUE"""),12345.0) -> 12345 | D9: =IFERROR(__xludf.DUMMYFUNCTION("""COMPUTED_VALUE"""),"0987654321") -> 0987654321 | E9: =IFERROR(__xludf.DUMMYFUNCTION("""COMPUTED_VALUE"""),"jjjt") -> jjjt
A10: =IFERROR(__xludf.DUMMYFUNCTION("""COMPUTED_VALUE"""),46068.726037500004) -> 46068.726 | B10: =IFERROR(__xludf.DUMMYFUNCTION("""COMPUTED_VALUE"""),"Nieva Prueba") -> Nieva Prueba | C10: =IFERROR(__xludf.DUMMYFUNCTION("""COMPUTED_VALUE"""),3.513559347E9) -> 3513559347 | D10: =IFERROR(__xludf.DUMMYFUNCTION("""COMPUTED_VALUE"""),"Dirección de prueba 1") -> Dirección de prueba 1
A11: =IFERROR(__xludf.DUMMYFUNCTION("""COMPUTED_VALUE"""),46068.73903166667) -> 46068.739 | B11: =IFERROR(__xludf.DUMMYFUNCTION("""COMPUTED_VALUE"""),"Pepito monje") -> Pepito monje | C11: =IFERROR(__xludf.DUMMYFUNCTION("""COMPUTED_VALUE"""),3.513559347E9) -> 3513559347 | D11: =IFERROR(__xludf.DUMMYFUNCTION("""COMPUTED_VALUE"""),"Guntanamera 1020") -> Guntanamera 1020 | E11: =IFERROR(__xludf.DUMMYFUNCTION("""COMPUTED_VALUE"""),"rujrr") -> rujrr
A12: =IFERROR(__xludf.DUMMYFUNCTION("""COMPUTED_VALUE"""),46069.04093928241) -> 46069.041 | B12: =IFERROR(__xludf.DUMMYFUNCTION("""COMPUTED_VALUE"""),"Villagra Sergio") -> Villagra Sergio | C12: =IFERROR(__xludf.DUMMYFUNCTION("""COMPUTED_VALUE"""),3.513559347E9) -> 3513559347 | D12: =IFERROR(__xludf.DUMMYFUNCTION("""COMPUTED_VALUE"""),"Domingo Zipoli 4567 Barrio Alberdi CP 5002") -> Domingo Zipoli 4567 Barrio Alberdi CP 5002 | E12: =IFERROR(__xludf.DUMMYFUNCTION("""COMPUTED_VALUE"""),"eiie") -> eiie
A13: =IFERROR(__xludf.DUMMYFUNCTION("""COMPUTED_VALUE"""),46069.072799166664) -> 46069.073 | B13: =IFERROR(__xludf.DUMMYFUNCTION("""COMPUTED_VALUE"""),"Preuga corte de luz") -> Preuga corte de luz | C13: =IFERROR(__xludf.DUMMYFUNCTION("""COMPUTED_VALUE"""),3.513559347E9) -> 3513559347 | D13: =IFERROR(__xludf.DUMMYFUNCTION("""COMPUTED_VALUE"""),"Gregorio correa 1837 cp Kdkdk barrio") -> Gregorio correa 1837 cp Kdkdk barrio | E13: =IFERROR(__xludf.DUMMYFUNCTION("""COMPUTED_VALUE"""),"rjjrjr") -> rjjrjr
A14: =IFERROR(__xludf.DUMMYFUNCTION("""COMPUTED_VALUE"""),46069.79447824074) -> 46069.794 | B14: =IFERROR(__xludf.DUMMYFUNCTION("""COMPUTED_VALUE"""),"Orueba123456") -> Orueba123456 | C14: =IFERROR(__xludf.DUMMYFUNCTION("""COMPUTED_VALUE"""),3.513559347E9) -> 3513559347 | D14: =IFERROR(__xludf.DUMMYFUNCTION("""COMPUTED_VALUE"""),"Enrique banchs 3281 los alamos") -> Enrique banchs 3281 los alamos | E14: =IFERROR(__xludf.DUMMYFUNCTION("""COMPUTED_VALUE"""),"iriri") -> iriri
A15: =IFERROR(__xludf.DUMMYFUNCTION("""COMPUTED_VALUE"""),46069.79786993055) -> 46069.798 | B15: =IFERROR(__xludf.DUMMYFUNCTION("""COMPUTED_VALUE"""),"Prueba numero 2") -> Prueba numero 2 | C15: =IFERROR(__xludf.DUMMYFUNCTION("""COMPUTED_VALUE"""),3.513559347E9) -> 3513559347 | D15: =IFERROR(__xludf.DUMMYFUNCTION("""COMPUTED_VALUE"""),"https://maps.app.goo.gl/xuNo6YtDjecjWtoJ7") -> https://maps.app.goo.gl/xuNo6YtDjecjWtoJ7 | E15: =IFERROR(__xludf.DUMMYFUNCTION("""COMPUTED_VALUE"""),"ggg") -> ggg
A16: =IFERROR(__xludf.DUMMYFUNCTION("""COMPUTED_VALUE"""),46070.066752638886) -> 46070.067 | B16: =IFERROR(__xludf.DUMMYFUNCTION("""COMPUTED_VALUE"""),"Nuevo Nuevito peresoso") -> Nuevo Nuevito peresoso | C16: =IFERROR(__xludf.DUMMYFUNCTION("""COMPUTED_VALUE"""),3.513559346E9) -> 3513559346 | D16: =IFERROR(__xludf.DUMMYFUNCTION("""COMPUTED_VALUE"""),"Domingo Zipoli 2368 alberdi cordoba") -> Domingo Zipoli 2368 alberdi cordoba
A17: =IFERROR(__xludf.DUMMYFUNCTION("""COMPUTED_VALUE"""),46070.47383278935) -> 46070.474 | B17: =IFERROR(__xludf.DUMMYFUNCTION("""COMPUTED_VALUE"""),"Ultima carga") -> Ultima carga | C17: =IFERROR(__xludf.DUMMYFUNCTION("""COMPUTED_VALUE"""),3.513559347E9) -> 3513559347 | D17: =IFERROR(__xludf.DUMMYFUNCTION("""COMPUTED_VALUE"""),"Ultima carga de prueba") -> Ultima carga de prueba
A18: =IFERROR(__xludf.DUMMYFUNCTION("""COMPUTED_VALUE"""),46070.68906409723) -> 46070.689 | B18: =IFERROR(__xludf.DUMMYFUNCTION("""COMPUTED_VALUE"""),"Gorgito") -> Gorgito | C18: =IFERROR(__xludf.DUMMYFUNCTION("""COMPUTED_VALUE"""),3.513589347E9) -> 3513589347 | D18: =IFERROR(__xludf.DUMMYFUNCTION("""COMPUTED_VALUE"""),"Nieva dirección ") -> Nieva dirección
A19: =IFERROR(__xludf.DUMMYFUNCTION("""COMPUTED_VALUE"""),46070.694844212965) -> 46070.695 | B19: =IFERROR(__xludf.DUMMYFUNCTION("""COMPUTED_VALUE"""),"Gonzalote") -> Gonzalote | C19: =IFERROR(__xludf.DUMMYFUNCTION("""COMPUTED_VALUE"""),3.513559347E9) -> 3513559347 | D19: =IFERROR(__xludf.DUMMYFUNCTION("""COMPUTED_VALUE"""),"Domingo zipoli 345 https://maps.app.goo.gl/vXvuksTmu9fyES1f7 ") -> Domingo zipoli 345 https://maps.app.goo.gl/vXvuksTmu9fyES1f7
A20: =IFERROR(__xludf.DUMMYFUNCTION("""COMPUTED_VALUE"""),46070.73501456018) -> 46070.735 | B20: =IFERROR(__xludf.DUMMYFUNCTION("""COMPUTED_VALUE"""),"Anita Machado") -> Anita Machado | C20: =IFERROR(__xludf.DUMMYFUNCTION("""COMPUTED_VALUE"""),3.513090975E9) -> 3513090975 | D20: =IFERROR(__xludf.DUMMYFUNCTION("""COMPUTED_VALUE"""),"Ruta 20 Ruta 20 deliverys, Fructuoso Rivera 1063, Fructuoso Rivera 1000, X5000 Córdoba") -> Ruta 20 Ruta 20 deliverys, Fructuoso Rivera 1063, Fructuoso Rivera 1000, X5000 Córdoba | E20: =IFERROR(__xludf.DUMMYFUNCTION("""COMPUTED_VALUE"""),"eia") -> eia
A21: =IFERROR(__xludf.DUMMYFUNCTION("""COMPUTED_VALUE"""),46070.990546932866) -> 46070.991 | B21: =IFERROR(__xludf.DUMMYFUNCTION("""COMPUTED_VALUE"""),"Prueba masemyerchef") -> Prueba masemyerchef | C21: =IFERROR(__xludf.DUMMYFUNCTION("""COMPUTED_VALUE"""),3.513559345E9) -> 3513559345 | D21: =IFERROR(__xludf.DUMMYFUNCTION("""COMPUTED_VALUE"""),"San Fernando 3245, Los Álamos, Córdoba, Provincia de Córdoba") -> San Fernando 3245, Los Álamos, Córdoba, Provincia de Córdoba
A22: =IFERROR(__xludf.DUMMYFUNCTION("""COMPUTED_VALUE"""),46071.01636951389) -> 46071.016 | B22: =IFERROR(__xludf.DUMMYFUNCTION("""COMPUTED_VALUE"""),"Villagra Villagra") -> Villagra Villagra | C22: =IFERROR(__xludf.DUMMYFUNCTION("""COMPUTED_VALUE"""),3.513559347E9) -> 3513559347 | D22: =IFERROR(__xludf.DUMMYFUNCTION("""COMPUTED_VALUE"""),"Av. Leandro N. Alem 3900, Córdoba, Provincia de Córdoba") -> Av. Leandro N. Alem 3900, Córdoba, Provincia de Córdoba | E22: =IFERROR(__xludf.DUMMYFUNCTION("""COMPUTED_VALUE"""),"Pruebillacitass") -> Pruebillacitass
A23: =IFERROR(__xludf.DUMMYFUNCTION("""COMPUTED_VALUE"""),46072.167987719906) -> 46072.168 | B23: =IFERROR(__xludf.DUMMYFUNCTION("""COMPUTED_VALUE"""),"Billa") -> Billa | C23: =IFERROR(__xludf.DUMMYFUNCTION("""COMPUTED_VALUE"""),3.513559347E9) -> 3513559347 | D23: =IFERROR(__xludf.DUMMYFUNCTION("""COMPUTED_VALUE"""),"Hshajs") -> Hshajs
A24: =IFERROR(__xludf.DUMMYFUNCTION("""COMPUTED_VALUE"""),46072.17262324074) -> 46072.173 | B24: =IFERROR(__xludf.DUMMYFUNCTION("""COMPUTED_VALUE"""),"Kkkkkkkkkkk") -> Kkkkkkkkkkk | C24: =IFERROR(__xludf.DUMMYFUNCTION("""COMPUTED_VALUE"""),3.513559347E9) -> 3513559347 | D24: =IFERROR(__xludf.DUMMYFUNCTION("""COMPUTED_VALUE"""),"Kkkkkkkk") -> Kkkkkkkk
A25: =IFERROR(__xludf.DUMMYFUNCTION("""COMPUTED_VALUE"""),46072.178416863426) -> 46072.178 | B25: =IFERROR(__xludf.DUMMYFUNCTION("""COMPUTED_VALUE"""),"Dies numeros") -> Dies numeros | C25: =IFERROR(__xludf.DUMMYFUNCTION("""COMPUTED_VALUE"""),1.213615555E9) -> 1213615555 | D25: =IFERROR(__xludf.DUMMYFUNCTION("""COMPUTED_VALUE"""),"Gshsh") -> Gshsh
A26: =IFERROR(__xludf.DUMMYFUNCTION("""COMPUTED_VALUE"""),46072.17998886574) -> 46072.18 | B26: =IFERROR(__xludf.DUMMYFUNCTION("""COMPUTED_VALUE"""),"Otraprueba") -> Otraprueba | C26: =IFERROR(__xludf.DUMMYFUNCTION("""COMPUTED_VALUE"""),1.23456789E9) -> 1234567890 | D26: =IFERROR(__xludf.DUMMYFUNCTION("""COMPUTED_VALUE"""),"Otra prueba") -> Otra prueba | E26: =IFERROR(__xludf.DUMMYFUNCTION("""COMPUTED_VALUE"""),"gg") -> gg
A27: =IFERROR(__xludf.DUMMYFUNCTION("""COMPUTED_VALUE"""),46072.195380798614) -> 46072.195 | B27: =IFERROR(__xludf.DUMMYFUNCTION("""COMPUTED_VALUE"""),"Ghhhhh") -> Ghhhhh | C27: =IFERROR(__xludf.DUMMYFUNCTION("""COMPUTED_VALUE"""),5.213655566E9) -> 5213655566 | D27: =IFERROR(__xludf.DUMMYFUNCTION("""COMPUTED_VALUE"""),"Ghh") -> Ghh
A28: =IFERROR(__xludf.DUMMYFUNCTION("""COMPUTED_VALUE"""),46072.19978998843) -> 46072.2 | B28: =IFERROR(__xludf.DUMMYFUNCTION("""COMPUTED_VALUE"""),"Otra pruebexicixixixllla mas ") -> Otra pruebexicixixixllla mas | C28: =IFERROR(__xludf.DUMMYFUNCTION("""COMPUTED_VALUE"""),3.512364676E9) -> 3512364676 | D28: =IFERROR(__xludf.DUMMYFUNCTION("""COMPUTED_VALUE"""),"Ysysy") -> Ysysy
A29: =IFERROR(__xludf.DUMMYFUNCTION("""COMPUTED_VALUE"""),46072.70643569445) -> 46072.706 | B29: =IFERROR(__xludf.DUMMYFUNCTION("""COMPUTED_VALUE"""),"Villagra Sergio Adrian") -> Villagra Sergio Adrian | C29: =IFERROR(__xludf.DUMMYFUNCTION("""COMPUTED_VALUE"""),3.513559347E9) -> 3513559347 | D29: =IFERROR(__xludf.DUMMYFUNCTION("""COMPUTED_VALUE"""),"Enrique Banchs 3281, X5012 Córdoba") -> Enrique Banchs 3281, X5012 Córdoba | E29: =IFERROR(__xludf.DUMMYFUNCTION("""COMPUTED_VALUE"""),"El maximo 😎😎😎😎") -> El maximo 😎😎😎😎
A30: =IFERROR(__xludf.DUMMYFUNCTION("""COMPUTED_VALUE"""),46073.738713425926) -> 46073.739 | B30: =IFERROR(__xludf.DUMMYFUNCTION("""COMPUTED_VALUE"""),"Sergio Villagra MTX") -> Sergio Villagra MTX | C30: =IFERROR(__xludf.DUMMYFUNCTION("""COMPUTED_VALUE"""),3.513559347E9) -> 3513559347 | D30: =IFERROR(__xludf.DUMMYFUNCTION("""COMPUTED_VALUE"""),"Octavio Pinto 3457, Córdoba, Provincia de Córdoba") -> Octavio Pinto 3457, Córdoba, Provincia de Córdoba | E30: =IFERROR(__xludf.DUMMYFUNCTION("""COMPUTED_VALUE"""),"Aqui se deben de colocar todas las observaciones.") -> Aqui se deben de colocar todas las observaciones.
A31: =IFERROR(__xludf.DUMMYFUNCTION("""COMPUTED_VALUE"""),46074.17716305556) -> 46074.177 | B31: =IFERROR(__xludf.DUMMYFUNCTION("""COMPUTED_VALUE"""),"Jeronimo ") -> Jeronimo | C31: =IFERROR(__xludf.DUMMYFUNCTION("""COMPUTED_VALUE"""),3.513559347E9) -> 3513559347 | D31: =IFERROR(__xludf.DUMMYFUNCTION("""COMPUTED_VALUE"""),"Jerónimo Luis de Cabrera 345, X5000GVG X5000GVG, Córdoba") -> Jerónimo Luis de Cabrera 345, X5000GVG X5000GVG, Córdoba | E31: =IFERROR(__xludf.DUMMYFUNCTION("""COMPUTED_VALUE"""),"Modificaciones de datos ") -> Modificaciones de datos
A32: =IFERROR(__xludf.DUMMYFUNCTION("""COMPUTED_VALUE"""),46074.38879064815) -> 46074.389 | B32: =IFERROR(__xludf.DUMMYFUNCTION("""COMPUTED_VALUE"""),"Pepito Mpnje") -> Pepito Mpnje | C32: =IFERROR(__xludf.DUMMYFUNCTION("""COMPUTED_VALUE"""),3.513559347E9) -> 3513559347 | D32: =IFERROR(__xludf.DUMMYFUNCTION("""COMPUTED_VALUE"""),"La Rioja 368, X5022FRH Córdoba") -> La Rioja 368, X5022FRH Córdoba | E32: =IFERROR(__xludf.DUMMYFUNCTION("""COMPUTED_VALUE"""),"Cliente conflictivo, avisado por otros electricistas ") -> Cliente conflictivo, avisado por otros electricistas
A33: =IFERROR(__xludf.DUMMYFUNCTION("""COMPUTED_VALUE"""),46082.04411354166) -> 46082.044 | B33: =IFERROR(__xludf.DUMMYFUNCTION("""COMPUTED_VALUE"""),"Leonel Suarez") -> Leonel Suarez | C33: =IFERROR(__xludf.DUMMYFUNCTION("""COMPUTED_VALUE"""),3.516595494E9) -> 3516595494 | D33: =IFERROR(__xludf.DUMMYFUNCTION("""COMPUTED_VALUE"""),"Enrique Banchs 3281, X5012 Córdoba") -> Enrique Banchs 3281, X5012 Córdoba | E33: =IFERROR(__xludf.DUMMYFUNCTION("""COMPUTED_VALUE"""),"Cargamos cambios") -> Cargamos cambios
A34: =IFERROR(__xludf.DUMMYFUNCTION("""COMPUTED_VALUE"""),46087.56516125) -> 46087.565 | B34: =IFERROR(__xludf.DUMMYFUNCTION("""COMPUTED_VALUE"""),"Facundo Suarez Materiales Eléctricos") -> Facundo Suarez Materiales Eléctricos | C34: =IFERROR(__xludf.DUMMYFUNCTION("""COMPUTED_VALUE"""),3.517693218E9) -> 3517693218 | D34: =IFERROR(__xludf.DUMMYFUNCTION("""COMPUTED_VALUE"""),"Lino Eneas Spilimbergo 5000, X5001 Córdoba") -> Lino Eneas Spilimbergo 5000, X5001 Córdoba | E34: =IFERROR(__xludf.DUMMYFUNCTION("""COMPUTED_VALUE"""),"www.sgselectricidad@gmail.com SGS Materiales Eléctricos e Iluminación") -> www.sgselectricidad@gmail.com SGS Materiales Eléctricos e Iluminación
A35: =IFERROR(__xludf.DUMMYFUNCTION("""COMPUTED_VALUE"""),46089.7175712037) -> 46089.718 | B35: =IFERROR(__xludf.DUMMYFUNCTION("""COMPUTED_VALUE"""),"Lara Suárez ") -> Lara Suárez | C35: =IFERROR(__xludf.DUMMYFUNCTION("""COMPUTED_VALUE"""),3.513568653E9) -> 3513568653 | D35: =IFERROR(__xludf.DUMMYFUNCTION("""COMPUTED_VALUE"""),"San Francisco 1231, X5012CSE Córdoba") -> San Francisco 1231, X5012CSE Córdoba | E35: =IFERROR(__xludf.DUMMYFUNCTION("""COMPUTED_VALUE"""),"Chussasera !!! 😆") -> Chussasera !!! 😆
A36: =IFERROR(__xludf.DUMMYFUNCTION("""COMPUTED_VALUE"""),46089.88928736111) -> 46089.889 | B36: =IFERROR(__xludf.DUMMYFUNCTION("""COMPUTED_VALUE"""),"Sergio Villagra Prueba ") -> Sergio Villagra Prueba | C36: =IFERROR(__xludf.DUMMYFUNCTION("""COMPUTED_VALUE"""),3.513559347E9) -> 3513559347 | D36: =IFERROR(__xludf.DUMMYFUNCTION("""COMPUTED_VALUE"""),"Enrique Banchs 3281, X5012 Córdoba") -> Enrique Banchs 3281, X5012 Córdoba | E36: =IFERROR(__xludf.DUMMYFUNCTION("""COMPUTED_VALUE"""),"Edicion nueva") -> Edicion nueva
A37: =IFERROR(__xludf.DUMMYFUNCTION("""COMPUTED_VALUE"""),46122.10008899306) -> 46122.1 | B37: =IFERROR(__xludf.DUMMYFUNCTION("""COMPUTED_VALUE"""),"Villagra Sergio ") -> Villagra Sergio | C37: =IFERROR(__xludf.DUMMYFUNCTION("""COMPUTED_VALUE"""),3.513559347E9) -> 3513559347 | D37: =IFERROR(__xludf.DUMMYFUNCTION("""COMPUTED_VALUE"""),"Enrique Banchs 3281, X5012 Córdoba") -> Enrique Banchs 3281, X5012 Córdoba
A38: =IFERROR(__xludf.DUMMYFUNCTION("""COMPUTED_VALUE"""),46122.379640150466) -> 46122.38 | B38: =IFERROR(__xludf.DUMMYFUNCTION("""COMPUTED_VALUE"""),"VILLAGRATAA") -> VILLAGRATAA | C38: =IFERROR(__xludf.DUMMYFUNCTION("""COMPUTED_VALUE"""),3.513559347E9) -> 3513559347 | D38: =IFERROR(__xludf.DUMMYFUNCTION("""COMPUTED_VALUE"""),"Domingo Zípoli 267, X5000 Córdoba") -> Domingo Zípoli 267, X5000 Córdoba | E38: =IFERROR(__xludf.DUMMYFUNCTION("""COMPUTED_VALUE"""),"CLIENTE: VILLAGRATAA TELÉFONO: 3513559347 DIRECCIÓN: Domingo Zípoli 267, X5000 Córdoba NOTAS: ") -> CLIENTE: VILLAGRATAA TELÉFONO: 3513559347 DIRECCIÓN: Domingo Zípoli 267, X5000 Córdoba NOTAS:
A39: =IFERROR(__xludf.DUMMYFUNCTION("""COMPUTED_VALUE"""),46122.74433998842) -> 46122.744 | B39: =IFERROR(__xludf.DUMMYFUNCTION("""COMPUTED_VALUE"""),"Hshsh") -> Hshsh | C39: =IFERROR(__xludf.DUMMYFUNCTION("""COMPUTED_VALUE"""),1.23456789E9) -> 1234567890 | D39: =IFERROR(__xludf.DUMMYFUNCTION("""COMPUTED_VALUE"""),"Octavio Pinto 3247, X5000 Córdoba") -> Octavio Pinto 3247, X5000 Córdoba | E39: =IFERROR(__xludf.DUMMYFUNCTION("""COMPUTED_VALUE"""),"Teléfono agregado") -> Teléfono agregado
A40: =IFERROR(__xludf.DUMMYFUNCTION("""COMPUTED_VALUE"""),46122.744394629626) -> 46122.744 | B40: =IFERROR(__xludf.DUMMYFUNCTION("""COMPUTED_VALUE"""),"Hshsh") -> Hshsh | C40: =IFERROR(__xludf.DUMMYFUNCTION("""COMPUTED_VALUE"""),"0123456789") -> 0123456789 | D40: =IFERROR(__xludf.DUMMYFUNCTION("""COMPUTED_VALUE"""),"Octavio Pinto 3247, X5000 Córdoba") -> Octavio Pinto 3247, X5000 Córdoba
A41: =IFERROR(__xludf.DUMMYFUNCTION("""COMPUTED_VALUE"""),46154.91371010417) -> 46154.914 | B41: =IFERROR(__xludf.DUMMYFUNCTION("""COMPUTED_VALUE"""),"AAAAAAAAAAAAAA") -> AAAAAAAAAAAAAA | C41: =IFERROR(__xludf.DUMMYFUNCTION("""COMPUTED_VALUE"""),1.23456789E9) -> 1234567890 | D41: =IFERROR(__xludf.DUMMYFUNCTION("""COMPUTED_VALUE"""),"Enrique Banchs 3281, X5012 Córdoba") -> Enrique Banchs 3281, X5012 Córdoba
A42: =IFERROR(__xludf.DUMMYFUNCTION("""COMPUTED_VALUE"""),46174.44387469908) -> 46174.444 | B42: =IFERROR(__xludf.DUMMYFUNCTION("""COMPUTED_VALUE"""),"Ivan") -> Ivan | C42: =IFERROR(__xludf.DUMMYFUNCTION("""COMPUTED_VALUE"""),2.966615418E9) -> 2966615418 | D42: =IFERROR(__xludf.DUMMYFUNCTION("""COMPUTED_VALUE"""),"S/N") -> S/N
A43: =IFERROR(__xludf.DUMMYFUNCTION("""COMPUTED_VALUE"""),46174.95804618056) -> 46174.958 | B43: =IFERROR(__xludf.DUMMYFUNCTION("""COMPUTED_VALUE"""),"EPAC") -> EPAC | C43: =IFERROR(__xludf.DUMMYFUNCTION("""COMPUTED_VALUE"""),3.51815126E9) -> 3518151260 | D43: =IFERROR(__xludf.DUMMYFUNCTION("""COMPUTED_VALUE"""),"Diag. Ica 1538, X5012 Córdoba") -> Diag. Ica 1538, X5012 Córdoba
A44: =IFERROR(__xludf.DUMMYFUNCTION("""COMPUTED_VALUE"""),46181.3176121412) -> 46181.318 | B44: =IFERROR(__xludf.DUMMYFUNCTION("""COMPUTED_VALUE"""),"Luciana Garro") -> Luciana Garro | C44: =IFERROR(__xludf.DUMMYFUNCTION("""COMPUTED_VALUE"""),3.515609308E9) -> 3515609308 | D44: =IFERROR(__xludf.DUMMYFUNCTION("""COMPUTED_VALUE"""),"Justo Páez Molina 289, X5003FYF Córdoba") -> Justo Páez Molina 289, X5003FYF Córdoba
A45: =IFERROR(__xludf.DUMMYFUNCTION("""COMPUTED_VALUE"""),46189.96543699074) -> 46189.965 | B45: =IFERROR(__xludf.DUMMYFUNCTION("""COMPUTED_VALUE"""),"Casella Florencia ") -> Casella Florencia | C45: =IFERROR(__xludf.DUMMYFUNCTION("""COMPUTED_VALUE"""),3.515433326E9) -> 3515433326 | D45: =IFERROR(__xludf.DUMMYFUNCTION("""COMPUTED_VALUE"""),"Gregorio Vélez 4520, X5009 Córdoba") -> Gregorio Vélez 4520, X5009 Córdoba
A46: =IFERROR(__xludf.DUMMYFUNCTION("""COMPUTED_VALUE"""),46190.4854272338) -> 46190.485 | B46: =IFERROR(__xludf.DUMMYFUNCTION("""COMPUTED_VALUE"""),"Florencia Casella Stiefel") -> Florencia Casella Stiefel | C46: =IFERROR(__xludf.DUMMYFUNCTION("""COMPUTED_VALUE"""),3.515433326E9) -> 3515433326 | D46: =IFERROR(__xludf.DUMMYFUNCTION("""COMPUTED_VALUE"""),"Gregorio Vélez 4520, X5009 Córdoba") -> Gregorio Vélez 4520, X5009 Córdoba

Sheet Carga
A2: Fecha | B2: 46067
A3: Nombre | B3: Pepito monje
A4: Dirección | B4: =VLOOKUP(B3,Clientes!B2:D200,3,0) -> Guntanamera 1020
A6: Tema | B6: Concepto | C6: descuento | F6: Cantidad | G6: Valor | I6: sub | K6: descuentos en % | M6: concatenado
C7: porcentaje | D7: % | E7: detalle
A8: DOCUMENTACIÓN, CERTIFICACIÓN Y SERVICIO DE MEDICIÓN | B8: Visita de inspeccion | F8: 1 | G8: =IFERROR(VLOOKUP(B8,Precios!D:E,2,0), "") | I8: =IF(G8*F8=0, "",G8*F8) | K8: =(SUM($I$8:$I$33)*C8)/-100 -> 0 | M8: =IF(I8+K8=0, "",I8+K8)
A9: DESCUENTO | B9: Visita de Inspección - Bonificación | F9: 1 | G9: =IFERROR(VLOOKUP(B9,Precios!D:E,2,0), "") | I9: =IF(G9*F9=0, "",G9*F9) | K9: =(SUM($I$8:$I$33)*C9)/-100 -> 0 | M9: =IF(I9+K9=0, "",I9+K9)
A10: CABLEADOS EN CAÑERÍAS | B10: Recableado (incluye sacar artef, llaves y colocar nueva instalación) por Boca | F10: 1 | G10: =IFERROR(VLOOKUP(B10,Precios!D:E,2,0), "") -> 56500 | I10: =IF(G10*F10=0, "",G10*F10) -> 56500 | K10: =(SUM($I$8:$I$33)*C10)/-100 -> 0 | M10: =IF(I10+K10=0, "",I10+K10) -> 56500
A11: DESCUENTO | B11: Otros Descuentos | C11: 45 | D11: % | G11: =IFERROR(VLOOKUP(B11,Precios!D:E,2,0), "") | I11: =IF(G11*F11=0, "",G11*F11) | K11: =(SUM($I$8:$I$33)*C11)/-100 -> -155475 | M11: =IF(I11+K11=0, "",I11+K11) -> -155475
G12: =IFERROR(VLOOKUP(B12,Precios!D:E,2,0), "") | I12: =IF(G12*F12=0, "",G12*F12) | K12: =(SUM($I$8:$I$33)*C12)/-100 -> 0 | M12: =IF(I12+K12=0, "",I12+K12)
G13: =IFERROR(VLOOKUP(B13,Precios!D:E,2,0), "") | I13: =IF(G13*F13=0, "",G13*F13) | K13: =(SUM($I$8:$I$33)*C13)/-100 -> 0 | M13: =IF(I13+K13=0, "",I13+K13)
G14: =IFERROR(VLOOKUP(B14,Precios!D:E,2,0), "") | I14: =IF(G14*F14=0, "",G14*F14) | K14: =(SUM($I$8:$I$33)*C14)/-100 -> 0 | M14: =IF(I14+K14=0, "",I14+K14)
G15: =IFERROR(VLOOKUP(B15,Precios!D:E,2,0), "") | I15: =IF(G15*F15=0, "",G15*F15) | K15: =(SUM($I$8:$I$33)*C15)/-100 -> 0 | M15: =IF(I15+K15=0, "",I15+K15)
G16: =IFERROR(VLOOKUP(B16,Precios!D:E,2,0), "") | I16: =IF(G16*F16=0, "",G16*F16) | K16: =(SUM($I$8:$I$33)*C16)/-100 -> 0 | M16: =IF(I16+K16=0, "",I16+K16)
G17: =IFERROR(VLOOKUP(B17,Precios!D:E,2,0), "") | I17: =IF(G17*F17=0, "",G17*F17) | K17: =(SUM($I$8:$I$33)*C17)/-100 -> 0 | M17: =IF(I17+K17=0, "",I17+K17)
G18: =IFERROR(VLOOKUP(B18,Precios!D:E,2,0), "") | I18: =IF(G18*F18=0, "",G18*F18) | K18: =(SUM($I$8:$I$33)*C18)/-100 -> 0 | M18: =IF(I18+K18=0, "",I18+K18)
G19: =IFERROR(VLOOKUP(B19,Precios!D:E,2,0), "") | I19: =IF(G19*F19=0, "",G19*F19) | K19: =(SUM($I$8:$I$33)*C19)/-100 -> 0 | M19: =IF(I19+K19=0, "",I19+K19)
G20: =IFERROR(VLOOKUP(B20,Precios!D:E,2,0), "") | I20: =IF(G20*F20=0, "",G20*F20) | K20: =(SUM($I$8:$I$33)*C20)/-100 -> 0 | M20: =IF(I20+K20=0, "",I20+K20)
G21: =IFERROR(VLOOKUP(B21,Precios!D:E,2,0), "") | I21: =IF(G21*F21=0, "",G21*F21) | K21: =(SUM($I$8:$I$33)*C21)/-100 -> 0 | M21: =IF(I21+K21=0, "",I21+K21)
G22: =IFERROR(VLOOKUP(B22,Precios!D:E,2,0), "") | I22: =IF(G22*F22=0, "",G22*F22) | K22: =(SUM($I$8:$I$33)*C22)/-100 -> 0 | M22: =IF(I22+K22=0, "",I22+K22)
G23: =IFERROR(VLOOKUP(B23,Precios!D:E,2,0), "") | I23: =IF(G23*F23=0, "",G23*F23) | K23: =(SUM($I$8:$I$33)*C23)/-100 -> 0 | M23: =IF(I23+K23=0, "",I23+K23)
... G28: =IFERROR(VLOOKUP(B28,Precios!D:E,2,0), "") | I28: =IF(G28*F28=0, "",G28*F28) | K28: =(SUM($I$8:$I$33)*C28)/-100 -> 0 | M28: =IF(I28+K28=0, "",I28+K28)
A29: ACOMETIDAS Y TABLEROS | B29: Acometida Trifásica aérea, hasta 10kw con sistema doble aislación | G29: =IFERROR(VLOOKUP(B29,Precios!D:E,2,0), "") -> 222000 | I29: =IF(G29*F29=0, "",G29*F29) | K29: =(SUM($I$8:$I$33)*C29)/-100 -> 0 | M29: =IF(I29+K29=0, "",I29+K29)
A30: ACOMETIDAS Y TABLEROS | B30: Acometida Trifásica de 11 a 35kw | F30: 1 | G30: =IFERROR(VLOOKUP(B30,Precios!D:E,2,0), "") -> 289000 | I30: =IF(G30*F30=0, "",G30*F30) -> 289000 | K30: =(SUM($I$8:$I$33)*C30)/-100 -> 0 | M30: =IF(I30+K30=0, "",I30+K30) -> 289000
G31: =IFERROR(VLOOKUP(B31,Precios!D:E,2,0), "") | I31: =IF(G31*F31=0, "",G31*F31) | M31: =IF(I31+K31=0, "",I31+K31)
G32: =IFERROR(VLOOKUP(B32,Precios!D:E,2,0), "") | I32: =IF(G32*F32=0, "",G32*F32) | M32: =IF(I32+K32=0, "",I32+K32)
G33: =IFERROR(VLOOKUP(B33,Precios!D:E,2,0), "") | I33: =IF(G33*F33=0, "",G33*F33) | M33: =IF(I33+K33=0, "",I33+K33)
K34: subtotal (sin desc) | M34: =SUMIF(M8:M30,">0") -> 345500
K35: total descuento | M35: =SUMIF(M8:M30,"<0") -> -155475
K37: Total Neto | M37: =SUM(M34,M35) -> 190025
I39: -
A41: =IFERROR(__xludf.DUMMYFUNCTION("IMPORTRANGE(""https://docs.google.com/spreadsheets/d/1aPynYCYBaEafPC4rqTulMOzPg_guy_NLzZHOzvFJwyw/edit?usp=drivesdk"", ""Respuestas de formulario 1!C5"")"),3.513559347E9) -> 3513559347

Sheet Copia_de_Carga
A2: Fecha | B2: 46067
A3: Nombre | B3: Pepito monje
A4: Dirección | B4: =VLOOKUP(B3,Clientes!B2:D200,3,0) -> Guntanamera 1020
A6: Tema | B6: Concepto | C6: descuento | F6: Cantidad | G6: Valor | I6: sub | K6: descuentos en % | M6: concatenado
C7: porcentaje | D7: % | E7: detalle
B8: =Hoja8!A2 -> 46072 | F8: =Hoja8!B2 -> Villagrono Alfredus | G8: =IFERROR(VLOOKUP(B8,Precios!D:E,2,0), "") | I8: =IF(G8*F8=0, "",G8*F8) -> #VALUE! | K8: =(SUM($I$8:$I$33)*C8)/-100 -> #VALUE! | M8: =IF(I8+K8=0, "",I8+K8) -> #VALUE!
B9: =Hoja8!A3 -> Instalación a altura h<4mts con perfil C P/ BPC 100 a 300 | F9: =Hoja8!B3 -> 1 | G9: =IFERROR(VLOOKUP(B9,Precios!D:E,2,0), "") -> 51700 | I9: =IF(G9*F9=0, "",G9*F9) -> 51700 | K9: =(SUM($I$8:$I$33)*C9)/-100 -> #VALUE! | M9: =IF(I9+K9=0, "",I9+K9) -> #VALUE!
B10: =Hoja8!A4 -> Instalación a altura h<4mts con perfil C P/ BPC 100 a 300 | F10: =Hoja8!B4 -> 1 | G10: =IFERROR(VLOOKUP(B10,Precios!D:E,2,0), "") -> 51700 | I10: =IF(G10*F10=0, "",G10*F10) -> 51700 | K10: =(SUM($I$8:$I$33)*C10)/-100 -> #VALUE! | M10: =IF(I10+K10=0, "",I10+K10) -> #VALUE!
B11: =Hoja8!A5 -> Instalación a altura h<4mts con perfil C P/ BPC 100 a 300 | D11: % | F11: =Hoja8!B5 -> 1 | G11: =IFERROR(VLOOKUP(B11,Precios!D:E,2,0), "") -> 51700 | I11: =IF(G11*F11=0, "",G11*F11) -> 51700 | K11: =(SUM($I$8:$I$33)*C11)/-100 -> #VALUE! | M11: =IF(I11+K11=0, "",I11+K11) -> #VALUE!
B12: =Hoja8!A6 -> Instalación a altura h<4mts con perfil C P/ BPC 100 a 300 | F12: =Hoja8!B6 -> 1 | G12: =IFERROR(VLOOKUP(B12,Precios!D:E,2,0), "") -> 51700 | I12: =IF(G12*F12=0, "",G12*F12) -> 51700 | K12: =(SUM($I$8:$I$33)*C12)/-100 -> #VALUE! | M12: =IF(I12+K12=0, "",I12+K12) -> #VALUE!
B13: =Hoja8!A7 -> Instalación a altura h<4mts con perfil C P/ BPC 100 a 300 | F13: =Hoja8!B7 -> 1 | G13: =IFERROR(VLOOKUP(B13,Precios!D:E,2,0), "") -> 51700 | I13: =IF(G13*F13=0, "",G13*F13) -> 51700 | K13: =(SUM($I$8:$I$33)*C13)/-100 -> #VALUE! | M13: =IF(I13+K13=0, "",I13+K13) -> #VALUE!
B14: =Hoja8!A8 -> Instalación a altura h<4mts con perfil C P/ BPC 100 a 300 | F14: =Hoja8!B8 -> 1 | G14: =IFERROR(VLOOKUP(B14,Precios!D:E,2,0), "") -> 51700 | I14: =IF(G14*F14=0, "",G14*F14) -> 51700 | K14: =(SUM($I$8:$I$33)*C14)/-100 -> #VALUE! | M14: =IF(I14+K14=0, "",I14+K14) -> #VALUE!
B15: =Hoja8!A9 -> Certificacion de vivienda o local comercial (hasta 20bocas) no incluye adecuacion de la instalacion | F15: =Hoja8!B9 -> -2 | G15: =IFERROR(VLOOKUP(B15,Precios!D:E,2,0), "") | I15: =IF(G15*F15=0, "",G15*F15) | K15: =(SUM($I$8:$I$33)*C15)/-100 -> #VALUE! | M15: =IF(I15+K15=0, "",I15+K15) -> #VALUE!
B16: =Hoja8!A10 -> Certificacion de vivienda o local comercial (hasta 20bocas) no incluye adecuacion de la instalacion | F16: =Hoja8!B10 -> -2 | G16: =IFERROR(VLOOKUP(B16,Precios!D:E,2,0), "") | I16: =IF(G16*F16=0, "",G16*F16) | K16: =(SUM($I$8:$I$33)*C16)/-100 -> #VALUE! | M16: =IF(I16+K16=0, "",I16+K16) -> #VALUE!
B17: =Hoja8!A11 -> Certificacion de vivienda o local comercial (hasta 20bocas) no incluye adecuacion de la instalacion | F17: =Hoja8!B11 -> -2 | G17: =IFERROR(VLOOKUP(B17,Precios!D:E,2,0), "") | I17: =IF(G17*F17=0, "",G17*F17) | K17: =(SUM($I$8:$I$33)*C17)/-100 -> #VALUE! | M17: =IF(I17+K17=0, "",I17+K17) -> #VALUE!
B18: =Hoja8!A12 -> Certificacion de vivienda o local comercial (hasta 20bocas) no incluye adecuacion de la instalacion | F18: =Hoja8!B12 -> -2 | G18: =IFERROR(VLOOKUP(B18,Precios!D:E,2,0), "") | I18: =IF(G18*F18=0, "",G18*F18) | K18: =(SUM($I$8:$I$33)*C18)/-100 -> #VALUE! | M18: =IF(I18+K18=0, "",I18+K18) -> #VALUE!
B19: =Hoja8!A13 -> Certificacion de vivienda o local comercial (hasta 20bocas) no incluye adecuacion de la instalacion | F19: =Hoja8!B13 -> -2 | G19: =IFERROR(VLOOKUP(B19,Precios!D:E,2,0), "") | I19: =IF(G19*F19=0, "",G19*F19) | K19: =(SUM($I$8:$I$33)*C19)/-100 -> #VALUE! | M19: =IF(I19+K19=0, "",I19+K19) -> #VALUE!
B20: =Hoja8!A14 -> Certificacion de vivienda o local comercial (hasta 20bocas) no incluye adecuacion de la instalacion | F20: =Hoja8!B14 -> -2 | G20: =IFERROR(VLOOKUP(B20,Precios!D:E,2,0), "") | I20: =IF(G20*F20=0, "",G20*F20) | K20: =(SUM($I$8:$I$33)*C20)/-100 -> #VALUE! | M20: =IF(I20+K20=0, "",I20+K20) -> #VALUE!
B21: =Hoja8!A15 -> Certificacion de vivienda o local comercial (hasta 20bocas) no incluye adecuacion de la instalacion | F21: =Hoja8!B15 -> -2 | G21: =IFERROR(VLOOKUP(B21,Precios!D:E,2,0), "") | I21: =IF(G21*F21=0, "",G21*F21) | K21: =(SUM($I$8:$I$33)*C21)/-100 -> #VALUE! | M21: =IF(I21+K21=0, "",I21+K21) -> #VALUE!
B22: =Hoja8!A16 -> Certificacion de vivienda o local comercial (hasta 20bocas) no incluye adecuacion de la instalacion | F22: =Hoja8!B16 -> -2 | G22: =IFERROR(VLOOKUP(B22,Precios!D:E,2,0), "") | I22: =IF(G22*F22=0, "",G22*F22) | K22: =(SUM($I$8:$I$33)*C22)/-100 -> #VALUE! | M22: =IF(I22+K22=0, "",I22+K22) -> #VALUE!
B23: =Hoja8!A17 -> Certificacion de vivienda o local comercial (hasta 20bocas) no incluye adecuacion de la instalacion | F23: =Hoja8!B17 -> -2 | G23: =IFERROR(VLOOKUP(B23,Precios!D:E,2,0), "") | I23: =IF(G23*F23=0, "",G23*F23) | K23: =(SUM($I$8:$I$33)*C23)/-100 -> #VALUE! | M23: =IF(I23+K23=0, "",I23+K23) -> #VALUE!
... B26: =Hoja8!A20 -> Certificacion de vivienda o local comercial (hasta 20bocas) no incluye adecuacion de la instalacion | F26: =Hoja8!B20 -> -2 | G26: =IFERROR(VLOOKUP(B26,Precios!D:E,2,0), "") | I26: =IF(G26*F26=0, "",G26*F26) | K26: =(SUM($I$8:$I$33)*C26)/-100 -> #VALUE! | M26: =IF(I26+K26=0, "",I26+K26) -> #VALUE!
B27: =Hoja8!A21 -> Certificacion de vivienda o local comercial (hasta 20bocas) no incluye adecuacion de la instalacion | F27: =Hoja8!B21 -> -2 | G27: =Hoja8!C21 | I27: =IF(G27*F27=0, "",G27*F27) | K27: =(SUM($I$8:$I$33)*C27)/-100 -> #VALUE! | M27: =IF(I27+K27=0, "",I27+K27) -> #VALUE!
B28: =Hoja8!A22 -> Certificacion de vivienda o local comercial (hasta 20bocas) no incluye adecuacion de la instalacion | F28: =Hoja8!B22 -> -2 | G28: =Hoja8!C22 | I28: =IF(G28*F28=0, "",G28*F28) | K28: =(SUM($I$8:$I$33)*C28)/-100 -> #VALUE! | M28: =IF(I28+K28=0, "",I28+K28) -> #VALUE!
A29: ACOMETIDAS Y TABLEROS | B29: =Hoja8!A23 -> Certificacion de vivienda o local comercial (hasta 20bocas) no incluye adecuacion de la instalacion | F29: =Hoja8!B23 -> -2 | G29: =Hoja8!C23 | I29: =IF(G29*F29=0, "",G29*F29) | K29: =(SUM($I$8:$I$33)*C29)/-100 -> #VALUE! | M29: =IF(I29+K29=0, "",I29+K29) -> #VALUE!
A30: ACOMETIDAS Y TABLEROS | B30: =Hoja8!A24 -> Certificacion de vivienda o local comercial (hasta 20bocas) no incluye adecuacion de la instalacion | F30: =Hoja8!B24 -> -2 | G30: =Hoja8!C24 | I30: =IF(G30*F30=0, "",G30*F30) | K30: =(SUM($I$8:$I$33)*C30)/-100 -> #VALUE! | M30: =IF(I30+K30=0, "",I30+K30) -> #VALUE!
G31: =IFERROR(VLOOKUP(B31,Precios!D:E,2,0), "") | I31: =IF(G31*F31=0, "",G31*F31) | M31: =IF(I31+K31=0, "",I31+K31)
G32: =IFERROR(VLOOKUP(B32,Precios!D:E,2,0), "") | I32: =IF(G32*F32=0, "",G32*F32) | M32: =IF(I32+K32=0, "",I32+K32)
G33: =IFERROR(VLOOKUP(B33,Precios!D:E,2,0), "") | I33: =IF(G33*F33=0, "",G33*F33) | M33: =IF(I33+K33=0, "",I33+K33)
K34: subtotal (sin desc) | M34: =SUMIF(M8:M30,">0") -> 0
K35: total descuento | M35: =SUMIF(M8:M30,"<0") -> 0
K37: Total Neto | M37: =SUM(M34,M35) -> 0
I39: -
A41: =IFERROR(__xludf.DUMMYFUNCTION("IMPORTRANGE(""https://docs.google.com/spreadsheets/d/1aPynYCYBaEafPC4rqTulMOzPg_guy_NLzZHOzvFJwyw/edit?usp=drivesdk"", ""Respuestas de formulario 1!C5"")"),3.513559347E9) -> 3513559347

Sheet F1
A1: =IFERROR(__xludf.DUMMYFUNCTION("FILTER(Precios!$D:$D,Carga!A8=Precios!$C:$C)"),"#N/A") -> #N/A | B1: =IFERROR(__xludf.DUMMYFUNCTION("FILTER(Precios!$D:$D,Carga!A9=Precios!$C:$C)"),"#N/A") -> #N/A | C1: =IFERROR(__xludf.DUMMYFUNCTION("FILTER(Precios!$D:$D,Carga!A10=Precios!$C:$C)"),"#N/A") -> #N/A | D1: =IFERROR(__xludf.DUMMYFUNCTION("FILTER(Precios!$D:$D,Carga!A11=Precios!$C:$C)"),"#N/A") -> #N/A | E1: =IFERROR(__xludf.DUMMYFUNCTION("FILTER(Precios!$D:$D,Carga!A12=Precios!$C:$C)"),"") | F1: =IFERROR(__xludf.DUMMYFUNCTION("FILTER(Precios!$D:$D,Carga!A13=Precios!$C:$C)"),"") | G1: =IFERROR(__xludf.DUMMYFUNCTION("FILTER(Precios!$D:$D,Carga!A14=Precios!$C:$C)"),"") | H1: =IFERROR(__xludf.DUMMYFUNCTION("FILTER(Precios!$D:$D,Carga!A15=Precios!$C:$C)"),"") | I1: =IFERROR(__xludf.DUMMYFUNCTION("FILTER(Precios!$D:$D,Carga!A16=Precios!$C:$C)"),"") | J1: =IFERROR(__xludf.DUMMYFUNCTION("FILTER(Precios!$D:$D,Carga!A17=Precios!$C:$C)"),"") | K1: =IFERROR(__xludf.DUMMYFUNCTION("FILTER(Precios!$D:$D,Carga!A18=Precios!$C:$C)"),"") | L1: =IFERROR(__xludf.DUMMYFUNCTION("FILTER(Precios!$D:$D,Carga!A19=Precios!$C:$C)"),"") | M1: =IFERROR(__xludf.DUMMYFUNCTION("FILTER(Precios!$D:$D,Carga!A20=Precios!$C:$C)"),"") | N1: =IFERROR(__xludf.DUMMYFUNCTION("FILTER(Precios!$D:$D,Carga!A21=Precios!$C:$C)"),"") | O1: =IFERROR(__xludf.DUMMYFUNCTION("FILTER(Precios!$D:$D,Carga!A22=Precios!$C:$C)"),"") | P1: =IFERROR(__xludf.DUMMYFUNCTION("FILTER(Precios!$D:$D,Carga!A23=Precios!$C:$C)"),"") | Q1: =IFERROR(__xludf.DUMMYFUNCTION("FILTER(Precios!$D:$D,Carga!A24=Precios!$C:$C)"),"") | R1: =IFERROR(__xludf.DUMMYFUNCTION("FILTER(Precios!$D:$D,Carga!A25=Precios!$C:$C)"),"") | S1: =IFERROR(__xludf.DUMMYFUNCTION("FILTER(Precios!$D:$D,Carga!A26=Precios!$C:$C)"),"") | T1: =IFERROR(__xludf.DUMMYFUNCTION("FILTER(Precios!$D:$D,Carga!A27=Precios!$C:$C)"),"") | U1: =IFERROR(__xludf.DUMMYFUNCTION("FILTER(Precios!$D:$D,Carga!A28=Precios!$C:$C)"),"") | V1: =IFERROR(__xludf.DUMMYFUNCTION("FILTER(Precios!$D:$D,Carga!A29=Precios!$C:$C)"),"Acometida Monofásica aérea, con sistema doble aislación") -> Acometida Monofásica aérea, con sistema doble aislación | W1: =IFERROR(__xludf.DUMMYFUNCTION("FILTER(Precios!$D:$D,Carga!A30=Precios!$C:$C)"),"Acometida Monofásica aérea, con sistema doble aislación") -> Acometida Monofásica aérea, con sistema doble aislación
V2: =IFERROR(__xludf.DUMMYFUNCTION("""COMPUTED_VALUE"""),"Acometida Trifásica aérea, hasta 10kw con sistema doble aislación") -> Acometida Trifásica aérea, hasta 10kw con sistema doble aislación | W2: =IFERROR(__xludf.DUMMYFUNCTION("""COMPUTED_VALUE"""),"Acometida Trifásica aérea, hasta 10kw con sistema doble aislación") -> Acometida Trifásica aérea, hasta 10kw con sistema doble aislación
V3: =IFERROR(__xludf.DUMMYFUNCTION("""COMPUTED_VALUE"""),"Acometida subterránea, hasta 10kw con sistema doble aislación") -> Acometida subterránea, hasta 10kw con sistema doble aislación | W3: =IFERROR(__xludf.DUMMYFUNCTION("""COMPUTED_VALUE"""),"Acometida subterránea, hasta 10kw con sistema doble aislación") -> Acometida subterránea, hasta 10kw con sistema doble aislación
V4: =IFERROR(__xludf.DUMMYFUNCTION("""COMPUTED_VALUE"""),"Acometida Trifásica de 11 a 35kw") -> Acometida Trifásica de 11 a 35kw | W4: =IFERROR(__xludf.DUMMYFUNCTION("""COMPUTED_VALUE"""),"Acometida Trifásica de 11 a 35kw") -> Acometida Trifásica de 11 a 35kw
V5: =IFERROR(__xludf.DUMMYFUNCTION("""COMPUTED_VALUE"""),"Acometida Trifásica de 36 a 50kw") -> Acometida Trifásica de 36 a 50kw | W5: =IFERROR(__xludf.DUMMYFUNCTION("""COMPUTED_VALUE"""),"Acometida Trifásica de 36 a 50kw") -> Acometida Trifásica de 36 a 50kw
V6: =IFERROR(__xludf.DUMMYFUNCTION("""COMPUTED_VALUE"""),"Acometida Trifásica mas de 50kw") -> Acometida Trifásica mas de 50kw | W6: =IFERROR(__xludf.DUMMYFUNCTION("""COMPUTED_VALUE"""),"Acometida Trifásica mas de 50kw") -> Acometida Trifásica mas de 50kw
V7: =IFERROR(__xludf.DUMMYFUNCTION("""COMPUTED_VALUE"""),"Fijación tablero de superficie (hasta 54 bocas)") -> Fijación tablero de superficie (hasta 54 bocas) | W7: =IFERROR(__xludf.DUMMYFUNCTION("""COMPUTED_VALUE"""),"Fijación tablero de superficie (hasta 54 bocas)") -> Fijación tablero de superficie (hasta 54 bocas)
V8: =IFERROR(__xludf.DUMMYFUNCTION("""COMPUTED_VALUE"""),"Fijación tablero de superficie") -> Fijación tablero de superficie | W8: =IFERROR(__xludf.DUMMYFUNCTION("""COMPUTED_VALUE"""),"Fijación tablero de superficie") -> Fijación tablero de superficie
V9: =IFERROR(__xludf.DUMMYFUNCTION("""COMPUTED_VALUE"""),"Empotrado de gabinete en mampostería (de 1 a 24 bocas)") -> Empotrado de gabinete en mampostería (de 1 a 24 bocas) | W9: =IFERROR(__xludf.DUMMYFUNCTION("""COMPUTED_VALUE"""),"Empotrado de gabinete en mampostería (de 1 a 24 bocas)") -> Empotrado de gabinete en mampostería (de 1 a 24 bocas)
V10: =IFERROR(__xludf.DUMMYFUNCTION("""COMPUTED_VALUE"""),"Empotrado / Fijación de gabinete en mampostería") -> Empotrado / Fijación de gabinete en mampostería | W10: =IFERROR(__xludf.DUMMYFUNCTION("""COMPUTED_VALUE"""),"Empotrado / Fijación de gabinete en mampostería") -> Empotrado / Fijación de gabinete en mampostería
V11: =IFERROR(__xludf.DUMMYFUNCTION("""COMPUTED_VALUE"""),"Empotrado de gabinete en mampostería (de 25 a 54 bocas)") -> Empotrado de gabinete en mampostería (de 25 a 54 bocas) | W11: =IFERROR(__xludf.DUMMYFUNCTION("""COMPUTED_VALUE"""),"Empotrado de gabinete en mampostería (de 25 a 54 bocas)") -> Empotrado de gabinete en mampostería (de 25 a 54 bocas)
V12: =IFERROR(__xludf.DUMMYFUNCTION("""COMPUTED_VALUE"""),"Armado de tablero de obra") -> Armado de tablero de obra | W12: =IFERROR(__xludf.DUMMYFUNCTION("""COMPUTED_VALUE"""),"Armado de tablero de obra") -> Armado de tablero de obra
V13: =IFERROR(__xludf.DUMMYFUNCTION("""COMPUTED_VALUE"""),"Zanjeo x metro ( 25 x 80cm) mas tendido de cable subterraneo hasta 4x10mm y relleno con protecciones mecánicas para longitudes de cable menor a 10 metros") -> Zanjeo x metro ( 25 x 80cm) mas tendido de cable subterraneo hasta 4x10mm y relleno con protecciones mecánicas para longitudes de cable menor a 10 metros | W13: =IFERROR(__xludf.DUMMYFUNCTION("""COMPUTED_VALUE"""),"Zanjeo x metro ( 25 x 80cm) mas tendido de cable subterraneo hasta 4x10mm y relleno con protecciones mecánicas para longitudes de cable menor a 10 metros") -> Zanjeo x metro ( 25 x 80cm) mas tendido de cable subterraneo hasta 4x10mm y relleno con protecciones mecánicas para longitudes de cable menor a 10 metros
V14: =IFERROR(__xludf.DUMMYFUNCTION("""COMPUTED_VALUE"""),"Zanjeo x metro ( 25 x 80cm) mas tendido de cable subterraneo hasta 4x10mm y relleno con protecciones mecánicas para longitudes de cable mayor a 10 metros") -> Zanjeo x metro ( 25 x 80cm) mas tendido de cable subterraneo hasta 4x10mm y relleno con protecciones mecánicas para longitudes de cable mayor a 10 metros | W14: =IFERROR(__xludf.DUMMYFUNCTION("""COMPUTED_VALUE"""),"Zanjeo x metro ( 25 x 80cm) mas tendido de cable subterraneo hasta 4x10mm y relleno con protecciones mecánicas para longitudes de cable mayor a 10 metros") -> Zanjeo x metro ( 25 x 80cm) mas tendido de cable subterraneo hasta 4x10mm y relleno con protecciones mecánicas para longitudes de cable mayor a 10 metros
V15: =IFERROR(__xludf.DUMMYFUNCTION("""COMPUTED_VALUE"""),"Puesta a tierra: jabalina+caja de inspección") -> Puesta a tierra: jabalina+caja de inspección | W15: =IFERROR(__xludf.DUMMYFUNCTION("""COMPUTED_VALUE"""),"Puesta a tierra: jabalina+caja de inspección") -> Puesta a tierra: jabalina+caja de inspección
E427: =IFERROR(__xludf.DUMMYFUNCTION("""COMPUTED_VALUE"""),"DOCUMENTACIÓN, CERTIFICACIÓN Y SERVICIO DE MEDICIÓN") -> DOCUMENTACIÓN, CERTIFICACIÓN Y SERVICIO DE MEDICIÓN | F427: =IFERROR(__xludf.DUMMYFUNCTION("""COMPUTED_VALUE"""),"DOCUMENTACIÓN, CERTIFICACIÓN Y SERVICIO DE MEDICIÓN") -> DOCUMENTACIÓN, CERTIFICACIÓN Y SERVICIO DE MEDICIÓN | G427: =IFERROR(__xludf.DUMMYFUNCTION("""COMPUTED_VALUE"""),"DOCUMENTACIÓN, CERTIFICACIÓN Y SERVICIO DE MEDICIÓN") -> DOCUMENTACIÓN, CERTIFICACIÓN Y SERVICIO DE MEDICIÓN | H427: =IFERROR(__xludf.DUMMYFUNCTION("""COMPUTED_VALUE"""),"DOCUMENTACIÓN, CERTIFICACIÓN Y SERVICIO DE MEDICIÓN") -> DOCUMENTACIÓN, CERTIFICACIÓN Y SERVICIO DE MEDICIÓN | I427: =IFERROR(__xludf.DUMMYFUNCTION("""COMPUTED_VALUE"""),"DOCUMENTACIÓN, CERTIFICACIÓN Y SERVICIO DE MEDICIÓN") -> DOCUMENTACIÓN, CERTIFICACIÓN Y SERVICIO DE MEDICIÓN | J427: =IFERROR(__xludf.DUMMYFUNCTION("""COMPUTED_VALUE"""),"DOCUMENTACIÓN, CERTIFICACIÓN Y SERVICIO DE MEDICIÓN") -> DOCUMENTACIÓN, CERTIFICACIÓN Y SERVICIO DE MEDICIÓN | K427: =IFERROR(__xludf.DUMMYFUNCTION("""COMPUTED_VALUE"""),"DOCUMENTACIÓN, CERTIFICACIÓN Y SERVICIO DE MEDICIÓN") -> DOCUMENTACIÓN, CERTIFICACIÓN Y SERVICIO DE MEDICIÓN | L427: =IFERROR(__xludf.DUMMYFUNCTION("""COMPUTED_VALUE"""),"DOCUMENTACIÓN, CERTIFICACIÓN Y SERVICIO DE MEDICIÓN") -> DOCUMENTACIÓN, CERTIFICACIÓN Y SERVICIO DE MEDICIÓN | ... U427: =IFERROR(__xludf.DUMMYFUNCTION("""COMPUTED_VALUE"""),"DOCUMENTACIÓN, CERTIFICACIÓN Y SERVICIO DE MEDICIÓN") -> DOCUMENTACIÓN, CERTIFICACIÓN Y SERVICIO DE MEDICIÓN
E428: =IFERROR(__xludf.DUMMYFUNCTION("""COMPUTED_VALUE"""),"ACOMETIDAS Y TABLEROS") -> ACOMETIDAS Y TABLEROS | F428: =IFERROR(__xludf.DUMMYFUNCTION("""COMPUTED_VALUE"""),"ACOMETIDAS Y TABLEROS") -> ACOMETIDAS Y TABLEROS | G428: =IFERROR(__xludf.DUMMYFUNCTION("""COMPUTED_VALUE"""),"ACOMETIDAS Y TABLEROS") -> ACOMETIDAS Y TABLEROS | H428: =IFERROR(__xludf.DUMMYFUNCTION("""COMPUTED_VALUE"""),"ACOMETIDAS Y TABLEROS") -> ACOMETIDAS Y TABLEROS | I428: =IFERROR(__xludf.DUMMYFUNCTION("""COMPUTED_VALUE"""),"ACOMETIDAS Y TABLEROS") -> ACOMETIDAS Y TABLEROS | J428: =IFERROR(__xludf.DUMMYFUNCTION("""COMPUTED_VALUE"""),"ACOMETIDAS Y TABLEROS") -> ACOMETIDAS Y TABLEROS | K428: =IFERROR(__xludf.DUMMYFUNCTION("""COMPUTED_VALUE"""),"ACOMETIDAS Y TABLEROS") -> ACOMETIDAS Y TABLEROS | L428: =IFERROR(__xludf.DUMMYFUNCTION("""COMPUTED_VALUE"""),"ACOMETIDAS Y TABLEROS") -> ACOMETIDAS Y TABLEROS | ... U428: =IFERROR(__xludf.DUMMYFUNCTION("""COMPUTED_VALUE"""),"ACOMETIDAS Y TABLEROS") -> ACOMETIDAS Y TABLEROS
E429: =IFERROR(__xludf.DUMMYFUNCTION("""COMPUTED_VALUE"""),"CANALIZACIÓN EMBUTIDA") -> CANALIZACIÓN EMBUTIDA | F429: =IFERROR(__xludf.DUMMYFUNCTION("""COMPUTED_VALUE"""),"CANALIZACIÓN EMBUTIDA") -> CANALIZACIÓN EMBUTIDA | G429: =IFERROR(__xludf.DUMMYFUNCTION("""COMPUTED_VALUE"""),"CANALIZACIÓN EMBUTIDA") -> CANALIZACIÓN EMBUTIDA | H429: =IFERROR(__xludf.DUMMYFUNCTION("""COMPUTED_VALUE"""),"CANALIZACIÓN EMBUTIDA") -> CANALIZACIÓN EMBUTIDA | I429: =IFERROR(__xludf.DUMMYFUNCTION("""COMPUTED_VALUE"""),"CANALIZACIÓN EMBUTIDA") -> CANALIZACIÓN EMBUTIDA | J429: =IFERROR(__xludf.DUMMYFUNCTION("""COMPUTED_VALUE"""),"CANALIZACIÓN EMBUTIDA") -> CANALIZACIÓN EMBUTIDA | K429: =IFERROR(__xludf.DUMMYFUNCTION("""COMPUTED_VALUE"""),"CANALIZACIÓN EMBUTIDA") -> CANALIZACIÓN EMBUTIDA | L429: =IFERROR(__xludf.DUMMYFUNCTION("""COMPUTED_VALUE"""),"CANALIZACIÓN EMBUTIDA") -> CANALIZACIÓN EMBUTIDA | ... U429: =IFERROR(__xludf.DUMMYFUNCTION("""COMPUTED_VALUE"""),"CANALIZACIÓN EMBUTIDA") -> CANALIZACIÓN EMBUTIDA
E430: =IFERROR(__xludf.DUMMYFUNCTION("""COMPUTED_VALUE"""),"CANALIZACIÓN EMBUTIDA EN DURLOCK") -> CANALIZACIÓN EMBUTIDA EN DURLOCK | F430: =IFERROR(__xludf.DUMMYFUNCTION("""COMPUTED_VALUE"""),"CANALIZACIÓN EMBUTIDA EN DURLOCK") -> CANALIZACIÓN EMBUTIDA EN DURLOCK | G430: =IFERROR(__xludf.DUMMYFUNCTION("""COMPUTED_VALUE"""),"CANALIZACIÓN EMBUTIDA EN DURLOCK") -> CANALIZACIÓN EMBUTIDA EN DURLOCK | H430: =IFERROR(__xludf.DUMMYFUNCTION("""COMPUTED_VALUE"""),"CANALIZACIÓN EMBUTIDA EN DURLOCK") -> CANALIZACIÓN EMBUTIDA EN DURLOCK | I430: =IFERROR(__xludf.DUMMYFUNCTION("""COMPUTED_VALUE"""),"CANALIZACIÓN EMBUTIDA EN DURLOCK") -> CANALIZACIÓN EMBUTIDA EN DURLOCK | J430: =IFERROR(__xludf.DUMMYFUNCTION("""COMPUTED_VALUE"""),"CANALIZACIÓN EMBUTIDA EN DURLOCK") -> CANALIZACIÓN EMBUTIDA EN DURLOCK | K430: =IFERROR(__xludf.DUMMYFUNCTION("""COMPUTED_VALUE"""),"CANALIZACIÓN EMBUTIDA EN DURLOCK") -> CANALIZACIÓN EMBUTIDA EN DURLOCK | L430: =IFERROR(__xludf.DUMMYFUNCTION("""COMPUTED_VALUE"""),"CANALIZACIÓN EMBUTIDA EN DURLOCK") -> CANALIZACIÓN EMBUTIDA EN DURLOCK | ... U430: =IFERROR(__xludf.DUMMYFUNCTION("""COMPUTED_VALUE"""),"CANALIZACIÓN EMBUTIDA EN DURLOCK") -> CANALIZACIÓN EMBUTIDA EN DURLOCK
E431: =IFERROR(__xludf.DUMMYFUNCTION("""COMPUTED_VALUE"""),"CANALIZACIÓN EXTERIOR ") -> CANALIZACIÓN EXTERIOR | F431: =IFERROR(__xludf.DUMMYFUNCTION("""COMPUTED_VALUE"""),"CANALIZACIÓN EXTERIOR ") -> CANALIZACIÓN EXTERIOR | G431: =IFERROR(__xludf.DUMMYFUNCTION("""COMPUTED_VALUE"""),"CANALIZACIÓN EXTERIOR ") -> CANALIZACIÓN EXTERIOR | H431: =IFERROR(__xludf.DUMMYFUNCTION("""COMPUTED_VALUE"""),"CANALIZACIÓN EXTERIOR ") -> CANALIZACIÓN EXTERIOR | I431: =IFERROR(__xludf.DUMMYFUNCTION("""COMPUTED_VALUE"""),"CANALIZACIÓN EXTERIOR ") -> CANALIZACIÓN EXTERIOR | J431: =IFERROR(__xludf.DUMMYFUNCTION("""COMPUTED_VALUE"""),"CANALIZACIÓN EXTERIOR ") -> CANALIZACIÓN EXTERIOR | K431: =IFERROR(__xludf.DUMMYFUNCTION("""COMPUTED_VALUE"""),"CANALIZACIÓN EXTERIOR ") -> CANALIZACIÓN EXTERIOR | L431: =IFERROR(__xludf.DUMMYFUNCTION("""COMPUTED_VALUE"""),"CANALIZACIÓN EXTERIOR ") -> CANALIZACIÓN EXTERIOR | ... U431: =IFERROR(__xludf.DUMMYFUNCTION("""COMPUTED_VALUE"""),"CANALIZACIÓN EXTERIOR ") -> CANALIZACIÓN EXTERIOR
E432: =IFERROR(__xludf.DUMMYFUNCTION("""COMPUTED_VALUE"""),"CANALIZACIÓN DE CABLE CANAL") -> CANALIZACIÓN DE CABLE CANAL | F432: =IFERROR(__xludf.DUMMYFUNCTION("""COMPUTED_VALUE"""),"CANALIZACIÓN DE CABLE CANAL") -> CANALIZACIÓN DE CABLE CANAL | G432: =IFERROR(__xludf.DUMMYFUNCTION("""COMPUTED_VALUE"""),"CANALIZACIÓN DE CABLE CANAL") -> CANALIZACIÓN DE CABLE CANAL | H432: =IFERROR(__xludf.DUMMYFUNCTION("""COMPUTED_VALUE"""),"CANALIZACIÓN DE CABLE CANAL") -> CANALIZACIÓN DE CABLE CANAL | I432: =IFERROR(__xludf.DUMMYFUNCTION("""COMPUTED_VALUE"""),"CANALIZACIÓN DE CABLE CANAL") -> CANALIZACIÓN DE CABLE CANAL | J432: =IFERROR(__xludf.DUMMYFUNCTION("""COMPUTED_VALUE"""),"CANALIZACIÓN DE CABLE CANAL") -> CANALIZACIÓN DE CABLE CANAL | K432: =IFERROR(__xludf.DUMMYFUNCTION("""COMPUTED_VALUE"""),"CANALIZACIÓN DE CABLE CANAL") -> CANALIZACIÓN DE CABLE CANAL | L432: =IFERROR(__xludf.DUMMYFUNCTION("""COMPUTED_VALUE"""),"CANALIZACIÓN DE CABLE CANAL") -> CANALIZACIÓN DE CABLE CANAL | ... U432: =IFERROR(__xludf.DUMMYFUNCTION("""COMPUTED_VALUE"""),"CANALIZACIÓN DE CABLE CANAL") -> CANALIZACIÓN DE CABLE CANAL
E433: =IFERROR(__xludf.DUMMYFUNCTION("""COMPUTED_VALUE"""),"CANALIZACIÓN Y CABLEADO CON PISO DUCTOS / POLIDUCTOS ") -> CANALIZACIÓN Y CABLEADO CON PISO DUCTOS / POLIDUCTOS | F433: =IFERROR(__xludf.DUMMYFUNCTION("""COMPUTED_VALUE"""),"CANALIZACIÓN Y CABLEADO CON PISO DUCTOS / POLIDUCTOS ") -> CANALIZACIÓN Y CABLEADO CON PISO DUCTOS / POLIDUCTOS | G433: =IFERROR(__xludf.DUMMYFUNCTION("""COMPUTED_VALUE"""),"CANALIZACIÓN Y CABLEADO CON PISO DUCTOS / POLIDUCTOS ") -> CANALIZACIÓN Y CABLEADO CON PISO DUCTOS / POLIDUCTOS | H433: =IFERROR(__xludf.DUMMYFUNCTION("""COMPUTED_VALUE"""),"CANALIZACIÓN Y CABLEADO CON PISO DUCTOS / POLIDUCTOS ") -> CANALIZACIÓN Y CABLEADO CON PISO DUCTOS / POLIDUCTOS | I433: =IFERROR(__xludf.DUMMYFUNCTION("""COMPUTED_VALUE"""),"CANALIZACIÓN Y CABLEADO CON PISO DUCTOS / POLIDUCTOS ") -> CANALIZACIÓN Y CABLEADO CON PISO DUCTOS / POLIDUCTOS | J433: =IFERROR(__xludf.DUMMYFUNCTION("""COMPUTED_VALUE"""),"CANALIZACIÓN Y CABLEADO CON PISO DUCTOS / POLIDUCTOS ") -> CANALIZACIÓN Y CABLEADO CON PISO DUCTOS / POLIDUCTOS | K433: =IFERROR(__xludf.DUMMYFUNCTION("""COMPUTED_VALUE"""),"CANALIZACIÓN Y CABLEADO CON PISO DUCTOS / POLIDUCTOS ") -> CANALIZACIÓN Y CABLEADO CON PISO DUCTOS / POLIDUCTOS | L433: =IFERROR(__xludf.DUMMYFUNCTION("""COMPUTED_VALUE"""),"CANALIZACIÓN Y CABLEADO CON PISO DUCTOS / POLIDUCTOS ") -> CANALIZACIÓN Y CABLEADO CON PISO DUCTOS / POLIDUCTOS | ... U433: =IFERROR(__xludf.DUMMYFUNCTION("""COMPUTED_VALUE"""),"CANALIZACIÓN Y CABLEADO CON PISO DUCTOS / POLIDUCTOS ") -> CANALIZACIÓN Y CABLEADO CON PISO DUCTOS / POLIDUCTOS
E434: =IFERROR(__xludf.DUMMYFUNCTION("""COMPUTED_VALUE"""),"CANALIZACIÓN CON BANDEJAS PORTA CABLES Y PERFIL C") -> CANALIZACIÓN CON BANDEJAS PORTA CABLES Y PERFIL C | F434: =IFERROR(__xludf.DUMMYFUNCTION("""COMPUTED_VALUE"""),"CANALIZACIÓN CON BANDEJAS PORTA CABLES Y PERFIL C") -> CANALIZACIÓN CON BANDEJAS PORTA CABLES Y PERFIL C | G434: =IFERROR(__xludf.DUMMYFUNCTION("""COMPUTED_VALUE"""),"CANALIZACIÓN CON BANDEJAS PORTA CABLES Y PERFIL C") -> CANALIZACIÓN CON BANDEJAS PORTA CABLES Y PERFIL C | H434: =IFERROR(__xludf.DUMMYFUNCTION("""COMPUTED_VALUE"""),"CANALIZACIÓN CON BANDEJAS PORTA CABLES Y PERFIL C") -> CANALIZACIÓN CON BANDEJAS PORTA CABLES Y PERFIL C | I434: =IFERROR(__xludf.DUMMYFUNCTION("""COMPUTED_VALUE"""),"CANALIZACIÓN CON BANDEJAS PORTA CABLES Y PERFIL C") -> CANALIZACIÓN CON BANDEJAS PORTA CABLES Y PERFIL C | J434: =IFERROR(__xludf.DUMMYFUNCTION("""COMPUTED_VALUE"""),"CANALIZACIÓN CON BANDEJAS PORTA CABLES Y PERFIL C") -> CANALIZACIÓN CON BANDEJAS PORTA CABLES Y PERFIL C | K434: =IFERROR(__xludf.DUMMYFUNCTION("""COMPUTED_VALUE"""),"CANALIZACIÓN CON BANDEJAS PORTA CABLES Y PERFIL C") -> CANALIZACIÓN CON BANDEJAS PORTA CABLES Y PERFIL C | L434: =IFERROR(__xludf.DUMMYFUNCTION("""COMPUTED_VALUE"""),"CANALIZACIÓN CON BANDEJAS PORTA CABLES Y PERFIL C") -> CANALIZACIÓN CON BANDEJAS PORTA CABLES Y PERFIL C | ... U434: =IFERROR(__xludf.DUMMYFUNCTION("""COMPUTED_VALUE"""),"CANALIZACIÓN CON BANDEJAS PORTA CABLES Y PERFIL C") -> CANALIZACIÓN CON BANDEJAS PORTA CABLES Y PERFIL C
E435: =IFERROR(__xludf.DUMMYFUNCTION("""COMPUTED_VALUE"""),"CABLEADOS EN CAÑERÍAS ") -> CABLEADOS EN CAÑERÍAS | F435: =IFERROR(__xludf.DUMMYFUNCTION("""COMPUTED_VALUE"""),"CABLEADOS EN CAÑERÍAS ") -> CABLEADOS EN CAÑERÍAS | G435: =IFERROR(__xludf.DUMMYFUNCTION("""COMPUTED_VALUE"""),"CABLEADOS EN CAÑERÍAS ") -> CABLEADOS EN CAÑERÍAS | H435: =IFERROR(__xludf.DUMMYFUNCTION("""COMPUTED_VALUE"""),"CABLEADOS EN CAÑERÍAS ") -> CABLEADOS EN CAÑERÍAS | I435: =IFERROR(__xludf.DUMMYFUNCTION("""COMPUTED_VALUE"""),"CABLEADOS EN CAÑERÍAS ") -> CABLEADOS EN CAÑERÍAS | J435: =IFERROR(__xludf.DUMMYFUNCTION("""COMPUTED_VALUE"""),"CABLEADOS EN CAÑERÍAS ") -> CABLEADOS EN CAÑERÍAS | K435: =IFERROR(__xludf.DUMMYFUNCTION("""COMPUTED_VALUE"""),"CABLEADOS EN CAÑERÍAS ") -> CABLEADOS EN CAÑERÍAS | L435: =IFERROR(__xludf.DUMMYFUNCTION("""COMPUTED_VALUE"""),"CABLEADOS EN CAÑERÍAS ") -> CABLEADOS EN CAÑERÍAS | ... U435: =IFERROR(__xludf.DUMMYFUNCTION("""COMPUTED_VALUE"""),"CABLEADOS EN CAÑERÍAS ") -> CABLEADOS EN CAÑERÍAS
E436: =IFERROR(__xludf.DUMMYFUNCTION("""COMPUTED_VALUE"""),"CABLEADO EN BANDEJAS PORTA CABLES ") -> CABLEADO EN BANDEJAS PORTA CABLES | F436: =IFERROR(__xludf.DUMMYFUNCTION("""COMPUTED_VALUE"""),"CABLEADO EN BANDEJAS PORTA CABLES ") -> CABLEADO EN BANDEJAS PORTA CABLES | G436: =IFERROR(__xludf.DUMMYFUNCTION("""COMPUTED_VALUE"""),"CABLEADO EN BANDEJAS PORTA CABLES ") -> CABLEADO EN BANDEJAS PORTA CABLES | H436: =IFERROR(__xludf.DUMMYFUNCTION("""COMPUTED_VALUE"""),"CABLEADO EN BANDEJAS PORTA CABLES ") -> CABLEADO EN BANDEJAS PORTA CABLES | I436: =IFERROR(__xludf.DUMMYFUNCTION("""COMPUTED_VALUE"""),"CABLEADO EN BANDEJAS PORTA CABLES ") -> CABLEADO EN BANDEJAS PORTA CABLES | J436: =IFERROR(__xludf.DUMMYFUNCTION("""COMPUTED_VALUE"""),"CABLEADO EN BANDEJAS PORTA CABLES ") -> CABLEADO EN BANDEJAS PORTA CABLES | K436: =IFERROR(__xludf.DUMMYFUNCTION("""COMPUTED_VALUE"""),"CABLEADO EN BANDEJAS PORTA CABLES ") -> CABLEADO EN BANDEJAS PORTA CABLES | L436: =IFERROR(__xludf.DUMMYFUNCTION("""COMPUTED_VALUE"""),"CABLEADO EN BANDEJAS PORTA CABLES ") -> CABLEADO EN BANDEJAS PORTA CABLES | ... U436: =IFERROR(__xludf.DUMMYFUNCTION("""COMPUTED_VALUE"""),"CABLEADO EN BANDEJAS PORTA CABLES ") -> CABLEADO EN BANDEJAS PORTA CABLES
E437: =IFERROR(__xludf.DUMMYFUNCTION("""COMPUTED_VALUE"""),"COLOCACIÓN DE INTERRUPTORES, TOMAS, ETC.") -> COLOCACIÓN DE INTERRUPTORES, TOMAS, ETC. | F437: =IFERROR(__xludf.DUMMYFUNCTION("""COMPUTED_VALUE"""),"COLOCACIÓN DE INTERRUPTORES, TOMAS, ETC.") -> COLOCACIÓN DE INTERRUPTORES, TOMAS, ETC. | G437: =IFERROR(__xludf.DUMMYFUNCTION("""COMPUTED_VALUE"""),"COLOCACIÓN DE INTERRUPTORES, TOMAS, ETC.") -> COLOCACIÓN DE INTERRUPTORES, TOMAS, ETC. | H437: =IFERROR(__xludf.DUMMYFUNCTION("""COMPUTED_VALUE"""),"COLOCACIÓN DE INTERRUPTORES, TOMAS, ETC.") -> COLOCACIÓN DE INTERRUPTORES, TOMAS, ETC. | I437: =IFERROR(__xludf.DUMMYFUNCTION("""COMPUTED_VALUE"""),"COLOCACIÓN DE INTERRUPTORES, TOMAS, ETC.") -> COLOCACIÓN DE INTERRUPTORES, TOMAS, ETC. | J437: =IFERROR(__xludf.DUMMYFUNCTION("""COMPUTED_VALUE"""),"COLOCACIÓN DE INTERRUPTORES, TOMAS, ETC.") -> COLOCACIÓN DE INTERRUPTORES, TOMAS, ETC. | K437: =IFERROR(__xludf.DUMMYFUNCTION("""COMPUTED_VALUE"""),"COLOCACIÓN DE INTERRUPTORES, TOMAS, ETC.") -> COLOCACIÓN DE INTERRUPTORES, TOMAS, ETC. | L437: =IFERROR(__xludf.DUMMYFUNCTION("""COMPUTED_VALUE"""),"COLOCACIÓN DE INTERRUPTORES, TOMAS, ETC.") -> COLOCACIÓN DE INTERRUPTORES, TOMAS, ETC. | ... U437: =IFERROR(__xludf.DUMMYFUNCTION("""COMPUTED_VALUE"""),"COLOCACIÓN DE INTERRUPTORES, TOMAS, ETC.") -> COLOCACIÓN DE INTERRUPTORES, TOMAS, ETC.
E438: =IFERROR(__xludf.DUMMYFUNCTION("""COMPUTED_VALUE"""),"COLOCACIÓN DE ARTEFACTOS") -> COLOCACIÓN DE ARTEFACTOS | F438: =IFERROR(__xludf.DUMMYFUNCTION("""COMPUTED_VALUE"""),"COLOCACIÓN DE ARTEFACTOS") -> COLOCACIÓN DE ARTEFACTOS | G438: =IFERROR(__xludf.DUMMYFUNCTION("""COMPUTED_VALUE"""),"COLOCACIÓN DE ARTEFACTOS") -> COLOCACIÓN DE ARTEFACTOS | H438: =IFERROR(__xludf.DUMMYFUNCTION("""COMPUTED_VALUE"""),"COLOCACIÓN DE ARTEFACTOS") -> COLOCACIÓN DE ARTEFACTOS | I438: =IFERROR(__xludf.DUMMYFUNCTION("""COMPUTED_VALUE"""),"COLOCACIÓN DE ARTEFACTOS") -> COLOCACIÓN DE ARTEFACTOS | J438: =IFERROR(__xludf.DUMMYFUNCTION("""COMPUTED_VALUE"""),"COLOCACIÓN DE ARTEFACTOS") -> COLOCACIÓN DE ARTEFACTOS | K438: =IFERROR(__xludf.DUMMYFUNCTION("""COMPUTED_VALUE"""),"COLOCACIÓN DE ARTEFACTOS") -> COLOCACIÓN DE ARTEFACTOS | L438: =IFERROR(__xludf.DUMMYFUNCTION("""COMPUTED_VALUE"""),"COLOCACIÓN DE ARTEFACTOS") -> COLOCACIÓN DE ARTEFACTOS | ... U438: =IFERROR(__xludf.DUMMYFUNCTION("""COMPUTED_VALUE"""),"COLOCACIÓN DE ARTEFACTOS") -> COLOCACIÓN DE ARTEFACTOS
E439: =IFERROR(__xludf.DUMMYFUNCTION("""COMPUTED_VALUE"""),"COLOCACIÓN DE ELEMENTOS DE PROTECCIÓN Y COMANDO") -> COLOCACIÓN DE ELEMENTOS DE PROTECCIÓN Y COMANDO | F439: =IFERROR(__xludf.DUMMYFUNCTION("""COMPUTED_VALUE"""),"COLOCACIÓN DE ELEMENTOS DE PROTECCIÓN Y COMANDO") -> COLOCACIÓN DE ELEMENTOS DE PROTECCIÓN Y COMANDO | G439: =IFERROR(__xludf.DUMMYFUNCTION("""COMPUTED_VALUE"""),"COLOCACIÓN DE ELEMENTOS DE PROTECCIÓN Y COMANDO") -> COLOCACIÓN DE ELEMENTOS DE PROTECCIÓN Y COMANDO | H439: =IFERROR(__xludf.DUMMYFUNCTION("""COMPUTED_VALUE"""),"COLOCACIÓN DE ELEMENTOS DE PROTECCIÓN Y COMANDO") -> COLOCACIÓN DE ELEMENTOS DE PROTECCIÓN Y COMANDO | I439: =IFERROR(__xludf.DUMMYFUNCTION("""COMPUTED_VALUE"""),"COLOCACIÓN DE ELEMENTOS DE PROTECCIÓN Y COMANDO") -> COLOCACIÓN DE ELEMENTOS DE PROTECCIÓN Y COMANDO | J439: =IFERROR(__xludf.DUMMYFUNCTION("""COMPUTED_VALUE"""),"COLOCACIÓN DE ELEMENTOS DE PROTECCIÓN Y COMANDO") -> COLOCACIÓN DE ELEMENTOS DE PROTECCIÓN Y COMANDO | K439: =IFERROR(__xludf.DUMMYFUNCTION("""COMPUTED_VALUE"""),"COLOCACIÓN DE ELEMENTOS DE PROTECCIÓN Y COMANDO") -> COLOCACIÓN DE ELEMENTOS DE PROTECCIÓN Y COMANDO | L439: =IFERROR(__xludf.DUMMYFUNCTION("""COMPUTED_VALUE"""),"COLOCACIÓN DE ELEMENTOS DE PROTECCIÓN Y COMANDO") -> COLOCACIÓN DE ELEMENTOS DE PROTECCIÓN Y COMANDO | ... U439: =IFERROR(__xludf.DUMMYFUNCTION("""COMPUTED_VALUE"""),"COLOCACIÓN DE ELEMENTOS DE PROTECCIÓN Y COMANDO") -> COLOCACIÓN DE ELEMENTOS DE PROTECCIÓN Y COMANDO
E440: =IFERROR(__xludf.DUMMYFUNCTION("""COMPUTED_VALUE"""),"TABLERO DE COMANDO DE MOTORES") -> TABLERO DE COMANDO DE MOTORES | F440: =IFERROR(__xludf.DUMMYFUNCTION("""COMPUTED_VALUE"""),"TABLERO DE COMANDO DE MOTORES") -> TABLERO DE COMANDO DE MOTORES | G440: =IFERROR(__xludf.DUMMYFUNCTION("""COMPUTED_VALUE"""),"TABLERO DE COMANDO DE MOTORES") -> TABLERO DE COMANDO DE MOTORES | H440: =IFERROR(__xludf.DUMMYFUNCTION("""COMPUTED_VALUE"""),"TABLERO DE COMANDO DE MOTORES") -> TABLERO DE COMANDO DE MOTORES | I440: =IFERROR(__xludf.DUMMYFUNCTION("""COMPUTED_VALUE"""),"TABLERO DE COMANDO DE MOTORES") -> TABLERO DE COMANDO DE MOTORES | J440: =IFERROR(__xludf.DUMMYFUNCTION("""COMPUTED_VALUE"""),"TABLERO DE COMANDO DE MOTORES") -> TABLERO DE COMANDO DE MOTORES | K440: =IFERROR(__xludf.DUMMYFUNCTION("""COMPUTED_VALUE"""),"TABLERO DE COMANDO DE MOTORES") -> TABLERO DE COMANDO DE MOTORES | L440: =IFERROR(__xludf.DUMMYFUNCTION("""COMPUTED_VALUE"""),"TABLERO DE COMANDO DE MOTORES") -> TABLERO DE COMANDO DE MOTORES | ... U440: =IFERROR(__xludf.DUMMYFUNCTION("""COMPUTED_VALUE"""),"TABLERO DE COMANDO DE MOTORES") -> TABLERO DE COMANDO DE MOTORES
E441: =IFERROR(__xludf.DUMMYFUNCTION("""COMPUTED_VALUE"""),"EMERGENCIAS ") -> EMERGENCIAS | F441: =IFERROR(__xludf.DUMMYFUNCTION("""COMPUTED_VALUE"""),"EMERGENCIAS ") -> EMERGENCIAS | G441: =IFERROR(__xludf.DUMMYFUNCTION("""COMPUTED_VALUE"""),"EMERGENCIAS ") -> EMERGENCIAS | H441: =IFERROR(__xludf.DUMMYFUNCTION("""COMPUTED_VALUE"""),"EMERGENCIAS ") -> EMERGENCIAS | I441: =IFERROR(__xludf.DUMMYFUNCTION("""COMPUTED_VALUE"""),"EMERGENCIAS ") -> EMERGENCIAS | J441: =IFERROR(__xludf.DUMMYFUNCTION("""COMPUTED_VALUE"""),"EMERGENCIAS ") -> EMERGENCIAS | K441: =IFERROR(__xludf.DUMMYFUNCTION("""COMPUTED_VALUE"""),"EMERGENCIAS ") -> EMERGENCIAS | L441: =IFERROR(__xludf.DUMMYFUNCTION("""COMPUTED_VALUE"""),"EMERGENCIAS ") -> EMERGENCIAS | ... U441: =IFERROR(__xludf.DUMMYFUNCTION("""COMPUTED_VALUE"""),"EMERGENCIAS ") -> EMERGENCIAS
E442: =IFERROR(__xludf.DUMMYFUNCTION("""COMPUTED_VALUE"""),"MANTENIMIENTO DE TABLEROS ELÉCTRICOS E INSTALACIONES ELECTRICAS") -> MANTENIMIENTO DE TABLEROS ELÉCTRICOS E INSTALACIONES ELECTRICAS | F442: =IFERROR(__xludf.DUMMYFUNCTION("""COMPUTED_VALUE"""),"MANTENIMIENTO DE TABLEROS ELÉCTRICOS E INSTALACIONES ELECTRICAS") -> MANTENIMIENTO DE TABLEROS ELÉCTRICOS E INSTALACIONES ELECTRICAS | G442: =IFERROR(__xludf.DUMMYFUNCTION("""COMPUTED_VALUE"""),"MANTENIMIENTO DE TABLEROS ELÉCTRICOS E INSTALACIONES ELECTRICAS") -> MANTENIMIENTO DE TABLEROS ELÉCTRICOS E INSTALACIONES ELECTRICAS | H442: =IFERROR(__xludf.DUMMYFUNCTION("""COMPUTED_VALUE"""),"MANTENIMIENTO DE TABLEROS ELÉCTRICOS E INSTALACIONES ELECTRICAS") -> MANTENIMIENTO DE TABLEROS ELÉCTRICOS E INSTALACIONES ELECTRICAS | I442: =IFERROR(__xludf.DUMMYFUNCTION("""COMPUTED_VALUE"""),"MANTENIMIENTO DE TABLEROS ELÉCTRICOS E INSTALACIONES ELECTRICAS") -> MANTENIMIENTO DE TABLEROS ELÉCTRICOS E INSTALACIONES ELECTRICAS | J442: =IFERROR(__xludf.DUMMYFUNCTION("""COMPUTED_VALUE"""),"MANTENIMIENTO DE TABLEROS ELÉCTRICOS E INSTALACIONES ELECTRICAS") -> MANTENIMIENTO DE TABLEROS ELÉCTRICOS E INSTALACIONES ELECTRICAS | K442: =IFERROR(__xludf.DUMMYFUNCTION("""COMPUTED_VALUE"""),"MANTENIMIENTO DE TABLEROS ELÉCTRICOS E INSTALACIONES ELECTRICAS") -> MANTENIMIENTO DE TABLEROS ELÉCTRICOS E INSTALACIONES ELECTRICAS | L442: =IFERROR(__xludf.DUMMYFUNCTION("""COMPUTED_VALUE"""),"MANTENIMIENTO DE TABLEROS ELÉCTRICOS E INSTALACIONES ELECTRICAS") -> MANTENIMIENTO DE TABLEROS ELÉCTRICOS E INSTALACIONES ELECTRICAS | ... U442: =IFERROR(__xludf.DUMMYFUNCTION("""COMPUTED_VALUE"""),"MANTENIMIENTO DE TABLEROS ELÉCTRICOS E INSTALACIONES ELECTRICAS") -> MANTENIMIENTO DE TABLEROS ELÉCTRICOS E INSTALACIONES ELECTRICAS
E443: =IFERROR(__xludf.DUMMYFUNCTION("""COMPUTED_VALUE"""),"VARIOS BAJA TENSIÓN ") -> VARIOS BAJA TENSIÓN | F443: =IFERROR(__xludf.DUMMYFUNCTION("""COMPUTED_VALUE"""),"VARIOS BAJA TENSIÓN ") -> VARIOS BAJA TENSIÓN | G443: =IFERROR(__xludf.DUMMYFUNCTION("""COMPUTED_VALUE"""),"VARIOS BAJA TENSIÓN ") -> VARIOS BAJA TENSIÓN | H443: =IFERROR(__xludf.DUMMYFUNCTION("""COMPUTED_VALUE"""),"VARIOS BAJA TENSIÓN ") -> VARIOS BAJA TENSIÓN | I443: =IFERROR(__xludf.DUMMYFUNCTION("""COMPUTED_VALUE"""),"VARIOS BAJA TENSIÓN ") -> VARIOS BAJA TENSIÓN | J443: =IFERROR(__xludf.DUMMYFUNCTION("""COMPUTED_VALUE"""),"VARIOS BAJA TENSIÓN ") -> VARIOS BAJA TENSIÓN | K443: =IFERROR(__xludf.DUMMYFUNCTION("""COMPUTED_VALUE"""),"VARIOS BAJA TENSIÓN ") -> VARIOS BAJA TENSIÓN | L443: =IFERROR(__xludf.DUMMYFUNCTION("""COMPUTED_VALUE"""),"VARIOS BAJA TENSIÓN ") -> VARIOS BAJA TENSIÓN | ... U443: =IFERROR(__xludf.DUMMYFUNCTION("""COMPUTED_VALUE"""),"VARIOS BAJA TENSIÓN ") -> VARIOS BAJA TENSIÓN
E444: =IFERROR(__xludf.DUMMYFUNCTION("""COMPUTED_VALUE"""),"COLOCACIÓN DE PORTERO ELÉCTRICO UNIFAMILIAR") -> COLOCACIÓN DE PORTERO ELÉCTRICO UNIFAMILIAR | F444: =IFERROR(__xludf.DUMMYFUNCTION("""COMPUTED_VALUE"""),"COLOCACIÓN DE PORTERO ELÉCTRICO UNIFAMILIAR") -> COLOCACIÓN DE PORTERO ELÉCTRICO UNIFAMILIAR | G444: =IFERROR(__xludf.DUMMYFUNCTION("""COMPUTED_VALUE"""),"COLOCACIÓN DE PORTERO ELÉCTRICO UNIFAMILIAR") -> COLOCACIÓN DE PORTERO ELÉCTRICO UNIFAMILIAR | H444: =IFERROR(__xludf.DUMMYFUNCTION("""COMPUTED_VALUE"""),"COLOCACIÓN DE PORTERO ELÉCTRICO UNIFAMILIAR") -> COLOCACIÓN DE PORTERO ELÉCTRICO UNIFAMILIAR | I444: =IFERROR(__xludf.DUMMYFUNCTION("""COMPUTED_VALUE"""),"COLOCACIÓN DE PORTERO ELÉCTRICO UNIFAMILIAR") -> COLOCACIÓN DE PORTERO ELÉCTRICO UNIFAMILIAR | J444: =IFERROR(__xludf.DUMMYFUNCTION("""COMPUTED_VALUE"""),"COLOCACIÓN DE PORTERO ELÉCTRICO UNIFAMILIAR") -> COLOCACIÓN DE PORTERO ELÉCTRICO UNIFAMILIAR | K444: =IFERROR(__xludf.DUMMYFUNCTION("""COMPUTED_VALUE"""),"COLOCACIÓN DE PORTERO ELÉCTRICO UNIFAMILIAR") -> COLOCACIÓN DE PORTERO ELÉCTRICO UNIFAMILIAR | L444: =IFERROR(__xludf.DUMMYFUNCTION("""COMPUTED_VALUE"""),"COLOCACIÓN DE PORTERO ELÉCTRICO UNIFAMILIAR") -> COLOCACIÓN DE PORTERO ELÉCTRICO UNIFAMILIAR | ... U444: =IFERROR(__xludf.DUMMYFUNCTION("""COMPUTED_VALUE"""),"COLOCACIÓN DE PORTERO ELÉCTRICO UNIFAMILIAR") -> COLOCACIÓN DE PORTERO ELÉCTRICO UNIFAMILIAR
E445: =IFERROR(__xludf.DUMMYFUNCTION("""COMPUTED_VALUE"""),"COLOCACIÓN DE PORTERO ELÉCTRICO EN EDIFICIO (AUDIO SOLO) MULTIFAMILIAR") -> COLOCACIÓN DE PORTERO ELÉCTRICO EN EDIFICIO (AUDIO SOLO) MULTIFAMILIAR | F445: =IFERROR(__xludf.DUMMYFUNCTION("""COMPUTED_VALUE"""),"COLOCACIÓN DE PORTERO ELÉCTRICO EN EDIFICIO (AUDIO SOLO) MULTIFAMILIAR") -> COLOCACIÓN DE PORTERO ELÉCTRICO EN EDIFICIO (AUDIO SOLO) MULTIFAMILIAR | G445: =IFERROR(__xludf.DUMMYFUNCTION("""COMPUTED_VALUE"""),"COLOCACIÓN DE PORTERO ELÉCTRICO EN EDIFICIO (AUDIO SOLO) MULTIFAMILIAR") -> COLOCACIÓN DE PORTERO ELÉCTRICO EN EDIFICIO (AUDIO SOLO) MULTIFAMILIAR | H445: =IFERROR(__xludf.DUMMYFUNCTION("""COMPUTED_VALUE"""),"COLOCACIÓN DE PORTERO ELÉCTRICO EN EDIFICIO (AUDIO SOLO) MULTIFAMILIAR") -> COLOCACIÓN DE PORTERO ELÉCTRICO EN EDIFICIO (AUDIO SOLO) MULTIFAMILIAR | I445: =IFERROR(__xludf.DUMMYFUNCTION("""COMPUTED_VALUE"""),"COLOCACIÓN DE PORTERO ELÉCTRICO EN EDIFICIO (AUDIO SOLO) MULTIFAMILIAR") -> COLOCACIÓN DE PORTERO ELÉCTRICO EN EDIFICIO (AUDIO SOLO) MULTIFAMILIAR | J445: =IFERROR(__xludf.DUMMYFUNCTION("""COMPUTED_VALUE"""),"COLOCACIÓN DE PORTERO ELÉCTRICO EN EDIFICIO (AUDIO SOLO) MULTIFAMILIAR") -> COLOCACIÓN DE PORTERO ELÉCTRICO EN EDIFICIO (AUDIO SOLO) MULTIFAMILIAR | K445: =IFERROR(__xludf.DUMMYFUNCTION("""COMPUTED_VALUE"""),"COLOCACIÓN DE PORTERO ELÉCTRICO EN EDIFICIO (AUDIO SOLO) MULTIFAMILIAR") -> COLOCACIÓN DE PORTERO ELÉCTRICO EN EDIFICIO (AUDIO SOLO) MULTIFAMILIAR | L445: =IFERROR(__xludf.DUMMYFUNCTION("""COMPUTED_VALUE"""),"COLOCACIÓN DE PORTERO ELÉCTRICO EN EDIFICIO (AUDIO SOLO) MULTIFAMILIAR") -> COLOCACIÓN DE PORTERO ELÉCTRICO EN EDIFICIO (AUDIO SOLO) MULTIFAMILIAR | ... U445: =IFERROR(__xludf.DUMMYFUNCTION("""COMPUTED_VALUE"""),"COLOCACIÓN DE PORTERO ELÉCTRICO EN EDIFICIO (AUDIO SOLO) MULTIFAMILIAR") -> COLOCACIÓN DE PORTERO ELÉCTRICO EN EDIFICIO (AUDIO SOLO) MULTIFAMILIAR
E446: =IFERROR(__xludf.DUMMYFUNCTION("""COMPUTED_VALUE"""),"SISTEMAS DE SEGURIDAD") -> SISTEMAS DE SEGURIDAD | F446: =IFERROR(__xludf.DUMMYFUNCTION("""COMPUTED_VALUE"""),"SISTEMAS DE SEGURIDAD") -> SISTEMAS DE SEGURIDAD | G446: =IFERROR(__xludf.DUMMYFUNCTION("""COMPUTED_VALUE"""),"SISTEMAS DE SEGURIDAD") -> SISTEMAS DE SEGURIDAD | H446: =IFERROR(__xludf.DUMMYFUNCTION("""COMPUTED_VALUE"""),"SISTEMAS DE SEGURIDAD") -> SISTEMAS DE SEGURIDAD | I446: =IFERROR(__xludf.DUMMYFUNCTION("""COMPUTED_VALUE"""),"SISTEMAS DE SEGURIDAD") -> SISTEMAS DE SEGURIDAD | J446: =IFERROR(__xludf.DUMMYFUNCTION("""COMPUTED_VALUE"""),"SISTEMAS DE SEGURIDAD") -> SISTEMAS DE SEGURIDAD | K446: =IFERROR(__xludf.DUMMYFUNCTION("""COMPUTED_VALUE"""),"SISTEMAS DE SEGURIDAD") -> SISTEMAS DE SEGURIDAD | L446: =IFERROR(__xludf.DUMMYFUNCTION("""COMPUTED_VALUE"""),"SISTEMAS DE SEGURIDAD") -> SISTEMAS DE SEGURIDAD | ... U446: =IFERROR(__xludf.DUMMYFUNCTION("""COMPUTED_VALUE"""),"SISTEMAS DE SEGURIDAD") -> SISTEMAS DE SEGURIDAD
E447: =IFERROR(__xludf.DUMMYFUNCTION("""COMPUTED_VALUE"""),"VARIOS CORRIENTES DÉBILES ") -> VARIOS CORRIENTES DÉBILES | F447: =IFERROR(__xludf.DUMMYFUNCTION("""COMPUTED_VALUE"""),"VARIOS CORRIENTES DÉBILES ") -> VARIOS CORRIENTES DÉBILES | G447: =IFERROR(__xludf.DUMMYFUNCTION("""COMPUTED_VALUE"""),"VARIOS CORRIENTES DÉBILES ") -> VARIOS CORRIENTES DÉBILES | H447: =IFERROR(__xludf.DUMMYFUNCTION("""COMPUTED_VALUE"""),"VARIOS CORRIENTES DÉBILES ") -> VARIOS CORRIENTES DÉBILES | I447: =IFERROR(__xludf.DUMMYFUNCTION("""COMPUTED_VALUE"""),"VARIOS CORRIENTES DÉBILES ") -> VARIOS CORRIENTES DÉBILES | J447: =IFERROR(__xludf.DUMMYFUNCTION("""COMPUTED_VALUE"""),"VARIOS CORRIENTES DÉBILES ") -> VARIOS CORRIENTES DÉBILES | K447: =IFERROR(__xludf.DUMMYFUNCTION("""COMPUTED_VALUE"""),"VARIOS CORRIENTES DÉBILES ") -> VARIOS CORRIENTES DÉBILES | L447: =IFERROR(__xludf.DUMMYFUNCTION("""COMPUTED_VALUE"""),"VARIOS CORRIENTES DÉBILES ") -> VARIOS CORRIENTES DÉBILES | ... U447: =IFERROR(__xludf.DUMMYFUNCTION("""COMPUTED_VALUE"""),"VARIOS CORRIENTES DÉBILES ") -> VARIOS CORRIENTES DÉBILES
E448: =IFERROR(__xludf.DUMMYFUNCTION("""COMPUTED_VALUE"""),"COMPUESTO DE INSTALACONES EMBUTIDAS") -> COMPUESTO DE INSTALACONES EMBUTIDAS | F448: =IFERROR(__xludf.DUMMYFUNCTION("""COMPUTED_VALUE"""),"COMPUESTO DE INSTALACONES EMBUTIDAS") -> COMPUESTO DE INSTALACONES EMBUTIDAS | G448: =IFERROR(__xludf.DUMMYFUNCTION("""COMPUTED_VALUE"""),"COMPUESTO DE INSTALACONES EMBUTIDAS") -> COMPUESTO DE INSTALACONES EMBUTIDAS | H448: =IFERROR(__xludf.DUMMYFUNCTION("""COMPUTED_VALUE"""),"COMPUESTO DE INSTALACONES EMBUTIDAS") -> COMPUESTO DE INSTALACONES EMBUTIDAS | I448: =IFERROR(__xludf.DUMMYFUNCTION("""COMPUTED_VALUE"""),"COMPUESTO DE INSTALACONES EMBUTIDAS") -> COMPUESTO DE INSTALACONES EMBUTIDAS | J448: =IFERROR(__xludf.DUMMYFUNCTION("""COMPUTED_VALUE"""),"COMPUESTO DE INSTALACONES EMBUTIDAS") -> COMPUESTO DE INSTALACONES EMBUTIDAS | K448: =IFERROR(__xludf.DUMMYFUNCTION("""COMPUTED_VALUE"""),"COMPUESTO DE INSTALACONES EMBUTIDAS") -> COMPUESTO DE INSTALACONES EMBUTIDAS | L448: =IFERROR(__xludf.DUMMYFUNCTION("""COMPUTED_VALUE"""),"COMPUESTO DE INSTALACONES EMBUTIDAS") -> COMPUESTO DE INSTALACONES EMBUTIDAS | ... U448: =IFERROR(__xludf.DUMMYFUNCTION("""COMPUTED_VALUE"""),"COMPUESTO DE INSTALACONES EMBUTIDAS") -> COMPUESTO DE INSTALACONES EMBUTIDAS
E449: =IFERROR(__xludf.DUMMYFUNCTION("""COMPUTED_VALUE"""),"COMPUESTO DE CANALIZACIÓN EXTERIOR ") -> COMPUESTO DE CANALIZACIÓN EXTERIOR | F449: =IFERROR(__xludf.DUMMYFUNCTION("""COMPUTED_VALUE"""),"COMPUESTO DE CANALIZACIÓN EXTERIOR ") -> COMPUESTO DE CANALIZACIÓN EXTERIOR | G449: =IFERROR(__xludf.DUMMYFUNCTION("""COMPUTED_VALUE"""),"COMPUESTO DE CANALIZACIÓN EXTERIOR ") -> COMPUESTO DE CANALIZACIÓN EXTERIOR | H449: =IFERROR(__xludf.DUMMYFUNCTION("""COMPUTED_VALUE"""),"COMPUESTO DE CANALIZACIÓN EXTERIOR ") -> COMPUESTO DE CANALIZACIÓN EXTERIOR | I449: =IFERROR(__xludf.DUMMYFUNCTION("""COMPUTED_VALUE"""),"COMPUESTO DE CANALIZACIÓN EXTERIOR ") -> COMPUESTO DE CANALIZACIÓN EXTERIOR | J449: =IFERROR(__xludf.DUMMYFUNCTION("""COMPUTED_VALUE"""),"COMPUESTO DE CANALIZACIÓN EXTERIOR ") -> COMPUESTO DE CANALIZACIÓN EXTERIOR | K449: =IFERROR(__xludf.DUMMYFUNCTION("""COMPUTED_VALUE"""),"COMPUESTO DE CANALIZACIÓN EXTERIOR ") -> COMPUESTO DE CANALIZACIÓN EXTERIOR | L449: =IFERROR(__xludf.DUMMYFUNCTION("""COMPUTED_VALUE"""),"COMPUESTO DE CANALIZACIÓN EXTERIOR ") -> COMPUESTO DE CANALIZACIÓN EXTERIOR | ... U449: =IFERROR(__xludf.DUMMYFUNCTION("""COMPUTED_VALUE"""),"COMPUESTO DE CANALIZACIÓN EXTERIOR ") -> COMPUESTO DE CANALIZACIÓN EXTERIOR
E450: =IFERROR(__xludf.DUMMYFUNCTION("""COMPUTED_VALUE"""),"COMPUESTO DE INSTALACIONES CON CABLE CANAL") -> COMPUESTO DE INSTALACIONES CON CABLE CANAL | F450: =IFERROR(__xludf.DUMMYFUNCTION("""COMPUTED_VALUE"""),"COMPUESTO DE INSTALACIONES CON CABLE CANAL") -> COMPUESTO DE INSTALACIONES CON CABLE CANAL | G450: =IFERROR(__xludf.DUMMYFUNCTION("""COMPUTED_VALUE"""),"COMPUESTO DE INSTALACIONES CON CABLE CANAL") -> COMPUESTO DE INSTALACIONES CON CABLE CANAL | H450: =IFERROR(__xludf.DUMMYFUNCTION("""COMPUTED_VALUE"""),"COMPUESTO DE INSTALACIONES CON CABLE CANAL") -> COMPUESTO DE INSTALACIONES CON CABLE CANAL | I450: =IFERROR(__xludf.DUMMYFUNCTION("""COMPUTED_VALUE"""),"COMPUESTO DE INSTALACIONES CON CABLE CANAL") -> COMPUESTO DE INSTALACIONES CON CABLE CANAL | J450: =IFERROR(__xludf.DUMMYFUNCTION("""COMPUTED_VALUE"""),"COMPUESTO DE INSTALACIONES CON CABLE CANAL") -> COMPUESTO DE INSTALACIONES CON CABLE CANAL | K450: =IFERROR(__xludf.DUMMYFUNCTION("""COMPUTED_VALUE"""),"COMPUESTO DE INSTALACIONES CON CABLE CANAL") -> COMPUESTO DE INSTALACIONES CON CABLE CANAL | L450: =IFERROR(__xludf.DUMMYFUNCTION("""COMPUTED_VALUE"""),"COMPUESTO DE INSTALACIONES CON CABLE CANAL") -> COMPUESTO DE INSTALACIONES CON CABLE CANAL | ... U450: =IFERROR(__xludf.DUMMYFUNCTION("""COMPUTED_VALUE"""),"COMPUESTO DE INSTALACIONES CON CABLE CANAL") -> COMPUESTO DE INSTALACIONES CON CABLE CANAL
E451: =IFERROR(__xludf.DUMMYFUNCTION("""COMPUTED_VALUE"""),"COMPUESTO ACOMETIDA") -> COMPUESTO ACOMETIDA | F451: =IFERROR(__xludf.DUMMYFUNCTION("""COMPUTED_VALUE"""),"COMPUESTO ACOMETIDA") -> COMPUESTO ACOMETIDA | G451: =IFERROR(__xludf.DUMMYFUNCTION("""COMPUTED_VALUE"""),"COMPUESTO ACOMETIDA") -> COMPUESTO ACOMETIDA | H451: =IFERROR(__xludf.DUMMYFUNCTION("""COMPUTED_VALUE"""),"COMPUESTO ACOMETIDA") -> COMPUESTO ACOMETIDA | I451: =IFERROR(__xludf.DUMMYFUNCTION("""COMPUTED_VALUE"""),"COMPUESTO ACOMETIDA") -> COMPUESTO ACOMETIDA | J451: =IFERROR(__xludf.DUMMYFUNCTION("""COMPUTED_VALUE"""),"COMPUESTO ACOMETIDA") -> COMPUESTO ACOMETIDA | K451: =IFERROR(__xludf.DUMMYFUNCTION("""COMPUTED_VALUE"""),"COMPUESTO ACOMETIDA") -> COMPUESTO ACOMETIDA | L451: =IFERROR(__xludf.DUMMYFUNCTION("""COMPUTED_VALUE"""),"COMPUESTO ACOMETIDA") -> COMPUESTO ACOMETIDA | ... U451: =IFERROR(__xludf.DUMMYFUNCTION("""COMPUTED_VALUE"""),"COMPUESTO ACOMETIDA") -> COMPUESTO ACOMETIDA
E452: =IFERROR(__xludf.DUMMYFUNCTION("""COMPUTED_VALUE"""),"PERSONAL CONTRATADO") -> PERSONAL CONTRATADO | F452: =IFERROR(__xludf.DUMMYFUNCTION("""COMPUTED_VALUE"""),"PERSONAL CONTRATADO") -> PERSONAL CONTRATADO | G452: =IFERROR(__xludf.DUMMYFUNCTION("""COMPUTED_VALUE"""),"PERSONAL CONTRATADO") -> PERSONAL CONTRATADO | H452: =IFERROR(__xludf.DUMMYFUNCTION("""COMPUTED_VALUE"""),"PERSONAL CONTRATADO") -> PERSONAL CONTRATADO | I452: =IFERROR(__xludf.DUMMYFUNCTION("""COMPUTED_VALUE"""),"PERSONAL CONTRATADO") -> PERSONAL CONTRATADO | J452: =IFERROR(__xludf.DUMMYFUNCTION("""COMPUTED_VALUE"""),"PERSONAL CONTRATADO") -> PERSONAL CONTRATADO | K452: =IFERROR(__xludf.DUMMYFUNCTION("""COMPUTED_VALUE"""),"PERSONAL CONTRATADO") -> PERSONAL CONTRATADO | L452: =IFERROR(__xludf.DUMMYFUNCTION("""COMPUTED_VALUE"""),"PERSONAL CONTRATADO") -> PERSONAL CONTRATADO | ... U452: =IFERROR(__xludf.DUMMYFUNCTION("""COMPUTED_VALUE"""),"PERSONAL CONTRATADO") -> PERSONAL CONTRATADO
E453: =IFERROR(__xludf.DUMMYFUNCTION("""COMPUTED_VALUE"""),"Nueva Categoría ") -> Nueva Categoría | F453: =IFERROR(__xludf.DUMMYFUNCTION("""COMPUTED_VALUE"""),"Nueva Categoría ") -> Nueva Categoría | G453: =IFERROR(__xludf.DUMMYFUNCTION("""COMPUTED_VALUE"""),"Nueva Categoría ") -> Nueva Categoría | H453: =IFERROR(__xludf.DUMMYFUNCTION("""COMPUTED_VALUE"""),"Nueva Categoría ") -> Nueva Categoría | I453: =IFERROR(__xludf.DUMMYFUNCTION("""COMPUTED_VALUE"""),"Nueva Categoría ") -> Nueva Categoría | J453: =IFERROR(__xludf.DUMMYFUNCTION("""COMPUTED_VALUE"""),"Nueva Categoría ") -> Nueva Categoría | K453: =IFERROR(__xludf.DUMMYFUNCTION("""COMPUTED_VALUE"""),"Nueva Categoría ") -> Nueva Categoría | L453: =IFERROR(__xludf.DUMMYFUNCTION("""COMPUTED_VALUE"""),"Nueva Categoría ") -> Nueva Categoría | ... U453: =IFERROR(__xludf.DUMMYFUNCTION("""COMPUTED_VALUE"""),"Nueva Categoría ") -> Nueva Categoría
E454: =IFERROR(__xludf.DUMMYFUNCTION("""COMPUTED_VALUE"""),"PURIFICACION (EI)") -> PURIFICACION (EI) | F454: =IFERROR(__xludf.DUMMYFUNCTION("""COMPUTED_VALUE"""),"PURIFICACION (EI)") -> PURIFICACION (EI) | G454: =IFERROR(__xludf.DUMMYFUNCTION("""COMPUTED_VALUE"""),"PURIFICACION (EI)") -> PURIFICACION (EI) | H454: =IFERROR(__xludf.DUMMYFUNCTION("""COMPUTED_VALUE"""),"PURIFICACION (EI)") -> PURIFICACION (EI) | I454: =IFERROR(__xludf.DUMMYFUNCTION("""COMPUTED_VALUE"""),"PURIFICACION (EI)") -> PURIFICACION (EI) | J454: =IFERROR(__xludf.DUMMYFUNCTION("""COMPUTED_VALUE"""),"PURIFICACION (EI)") -> PURIFICACION (EI) | K454: =IFERROR(__xludf.DUMMYFUNCTION("""COMPUTED_VALUE"""),"PURIFICACION (EI)") -> PURIFICACION (EI) | L454: =IFERROR(__xludf.DUMMYFUNCTION("""COMPUTED_VALUE"""),"PURIFICACION (EI)") -> PURIFICACION (EI) | ... U454: =IFERROR(__xludf.DUMMYFUNCTION("""COMPUTED_VALUE"""),"PURIFICACION (EI)") -> PURIFICACION (EI)
E455: =IFERROR(__xludf.DUMMYFUNCTION("""COMPUTED_VALUE"""),"ELECTROINSTALADOR (Otros)") -> ELECTROINSTALADOR (Otros) | F455: =IFERROR(__xludf.DUMMYFUNCTION("""COMPUTED_VALUE"""),"ELECTROINSTALADOR (Otros)") -> ELECTROINSTALADOR (Otros) | G455: =IFERROR(__xludf.DUMMYFUNCTION("""COMPUTED_VALUE"""),"ELECTROINSTALADOR (Otros)") -> ELECTROINSTALADOR (Otros) | H455: =IFERROR(__xludf.DUMMYFUNCTION("""COMPUTED_VALUE"""),"ELECTROINSTALADOR (Otros)") -> ELECTROINSTALADOR (Otros) | I455: =IFERROR(__xludf.DUMMYFUNCTION("""COMPUTED_VALUE"""),"ELECTROINSTALADOR (Otros)") -> ELECTROINSTALADOR (Otros) | J455: =IFERROR(__xludf.DUMMYFUNCTION("""COMPUTED_VALUE"""),"ELECTROINSTALADOR (Otros)") -> ELECTROINSTALADOR (Otros) | K455: =IFERROR(__xludf.DUMMYFUNCTION("""COMPUTED_VALUE"""),"ELECTROINSTALADOR (Otros)") -> ELECTROINSTALADOR (Otros) | L455: =IFERROR(__xludf.DUMMYFUNCTION("""COMPUTED_VALUE"""),"ELECTROINSTALADOR (Otros)") -> ELECTROINSTALADOR (Otros) | ... U455: =IFERROR(__xludf.DUMMYFUNCTION("""COMPUTED_VALUE"""),"ELECTROINSTALADOR (Otros)") -> ELECTROINSTALADOR (Otros)
E457: =IFERROR(__xludf.DUMMYFUNCTION("""COMPUTED_VALUE"""),"Obra completa - Refacción - Ampliación (*) (AAIERIC)") -> Obra completa - Refacción - Ampliación (*) (AAIERIC) | F457: =IFERROR(__xludf.DUMMYFUNCTION("""COMPUTED_VALUE"""),"Obra completa - Refacción - Ampliación (*) (AAIERIC)") -> Obra completa - Refacción - Ampliación (*) (AAIERIC) | G457: =IFERROR(__xludf.DUMMYFUNCTION("""COMPUTED_VALUE"""),"Obra completa - Refacción - Ampliación (*) (AAIERIC)") -> Obra completa - Refacción - Ampliación (*) (AAIERIC) | H457: =IFERROR(__xludf.DUMMYFUNCTION("""COMPUTED_VALUE"""),"Obra completa - Refacción - Ampliación (*) (AAIERIC)") -> Obra completa - Refacción - Ampliación (*) (AAIERIC) | I457: =IFERROR(__xludf.DUMMYFUNCTION("""COMPUTED_VALUE"""),"Obra completa - Refacción - Ampliación (*) (AAIERIC)") -> Obra completa - Refacción - Ampliación (*) (AAIERIC) | J457: =IFERROR(__xludf.DUMMYFUNCTION("""COMPUTED_VALUE"""),"Obra completa - Refacción - Ampliación (*) (AAIERIC)") -> Obra completa - Refacción - Ampliación (*) (AAIERIC) | K457: =IFERROR(__xludf.DUMMYFUNCTION("""COMPUTED_VALUE"""),"Obra completa - Refacción - Ampliación (*) (AAIERIC)") -> Obra completa - Refacción - Ampliación (*) (AAIERIC) | L457: =IFERROR(__xludf.DUMMYFUNCTION("""COMPUTED_VALUE"""),"Obra completa - Refacción - Ampliación (*) (AAIERIC)") -> Obra completa - Refacción - Ampliación (*) (AAIERIC) | ... U457: =IFERROR(__xludf.DUMMYFUNCTION("""COMPUTED_VALUE"""),"Obra completa - Refacción - Ampliación (*) (AAIERIC)") -> Obra completa - Refacción - Ampliación (*) (AAIERIC)
E458: =IFERROR(__xludf.DUMMYFUNCTION("""COMPUTED_VALUE"""),"Canalización de cañería en losa") -> Canalización de cañería en losa | F458: =IFERROR(__xludf.DUMMYFUNCTION("""COMPUTED_VALUE"""),"Canalización de cañería en losa") -> Canalización de cañería en losa | G458: =IFERROR(__xludf.DUMMYFUNCTION("""COMPUTED_VALUE"""),"Canalización de cañería en losa") -> Canalización de cañería en losa | H458: =IFERROR(__xludf.DUMMYFUNCTION("""COMPUTED_VALUE"""),"Canalización de cañería en losa") -> Canalización de cañería en losa | I458: =IFERROR(__xludf.DUMMYFUNCTION("""COMPUTED_VALUE"""),"Canalización de cañería en losa") -> Canalización de cañería en losa | J458: =IFERROR(__xludf.DUMMYFUNCTION("""COMPUTED_VALUE"""),"Canalización de cañería en losa") -> Canalización de cañería en losa | K458: =IFERROR(__xludf.DUMMYFUNCTION("""COMPUTED_VALUE"""),"Canalización de cañería en losa") -> Canalización de cañería en losa | L458: =IFERROR(__xludf.DUMMYFUNCTION("""COMPUTED_VALUE"""),"Canalización de cañería en losa") -> Canalización de cañería en losa | ... U458: =IFERROR(__xludf.DUMMYFUNCTION("""COMPUTED_VALUE"""),"Canalización de cañería en losa") -> Canalización de cañería en losa
E459: =IFERROR(__xludf.DUMMYFUNCTION("""COMPUTED_VALUE"""),"Amurado de cañeria en mampostería (AAIERIC)") -> Amurado de cañeria en mampostería (AAIERIC) | F459: =IFERROR(__xludf.DUMMYFUNCTION("""COMPUTED_VALUE"""),"Amurado de cañeria en mampostería (AAIERIC)") -> Amurado de cañeria en mampostería (AAIERIC) | G459: =IFERROR(__xludf.DUMMYFUNCTION("""COMPUTED_VALUE"""),"Amurado de cañeria en mampostería (AAIERIC)") -> Amurado de cañeria en mampostería (AAIERIC) | H459: =IFERROR(__xludf.DUMMYFUNCTION("""COMPUTED_VALUE"""),"Amurado de cañeria en mampostería (AAIERIC)") -> Amurado de cañeria en mampostería (AAIERIC) | I459: =IFERROR(__xludf.DUMMYFUNCTION("""COMPUTED_VALUE"""),"Amurado de cañeria en mampostería (AAIERIC)") -> Amurado de cañeria en mampostería (AAIERIC) | J459: =IFERROR(__xludf.DUMMYFUNCTION("""COMPUTED_VALUE"""),"Amurado de cañeria en mampostería (AAIERIC)") -> Amurado de cañeria en mampostería (AAIERIC) | K459: =IFERROR(__xludf.DUMMYFUNCTION("""COMPUTED_VALUE"""),"Amurado de cañeria en mampostería (AAIERIC)") -> Amurado de cañeria en mampostería (AAIERIC) | L459: =IFERROR(__xludf.DUMMYFUNCTION("""COMPUTED_VALUE"""),"Amurado de cañeria en mampostería (AAIERIC)") -> Amurado de cañeria en mampostería (AAIERIC) | ... U459: =IFERROR(__xludf.DUMMYFUNCTION("""COMPUTED_VALUE"""),"Amurado de cañeria en mampostería (AAIERIC)") -> Amurado de cañeria en mampostería (AAIERIC)
E460: =IFERROR(__xludf.DUMMYFUNCTION("""COMPUTED_VALUE"""),"Amurado de cañeria a la vista") -> Amurado de cañeria a la vista | F460: =IFERROR(__xludf.DUMMYFUNCTION("""COMPUTED_VALUE"""),"Amurado de cañeria a la vista") -> Amurado de cañeria a la vista | G460: =IFERROR(__xludf.DUMMYFUNCTION("""COMPUTED_VALUE"""),"Amurado de cañeria a la vista") -> Amurado de cañeria a la vista | H460: =IFERROR(__xludf.DUMMYFUNCTION("""COMPUTED_VALUE"""),"Amurado de cañeria a la vista") -> Amurado de cañeria a la vista | I460: =IFERROR(__xludf.DUMMYFUNCTION("""COMPUTED_VALUE"""),"Amurado de cañeria a la vista") -> Amurado de cañeria a la vista | J460: =IFERROR(__xludf.DUMMYFUNCTION("""COMPUTED_VALUE"""),"Amurado de cañeria a la vista") -> Amurado de cañeria a la vista | K460: =IFERROR(__xludf.DUMMYFUNCTION("""COMPUTED_VALUE"""),"Amurado de cañeria a la vista") -> Amurado de cañeria a la vista | L460: =IFERROR(__xludf.DUMMYFUNCTION("""COMPUTED_VALUE"""),"Amurado de cañeria a la vista") -> Amurado de cañeria a la vista | ... U460: =IFERROR(__xludf.DUMMYFUNCTION("""COMPUTED_VALUE"""),"Amurado de cañeria a la vista") -> Amurado de cañeria a la vista
E463: =IFERROR(__xludf.DUMMYFUNCTION("""COMPUTED_VALUE"""),"Pase de viga y/o columna (AAIERIC)") -> Pase de viga y/o columna (AAIERIC) | F463: =IFERROR(__xludf.DUMMYFUNCTION("""COMPUTED_VALUE"""),"Pase de viga y/o columna (AAIERIC)") -> Pase de viga y/o columna (AAIERIC) | G463: =IFERROR(__xludf.DUMMYFUNCTION("""COMPUTED_VALUE"""),"Pase de viga y/o columna (AAIERIC)") -> Pase de viga y/o columna (AAIERIC) | H463: =IFERROR(__xludf.DUMMYFUNCTION("""COMPUTED_VALUE"""),"Pase de viga y/o columna (AAIERIC)") -> Pase de viga y/o columna (AAIERIC) | I463: =IFERROR(__xludf.DUMMYFUNCTION("""COMPUTED_VALUE"""),"Pase de viga y/o columna (AAIERIC)") -> Pase de viga y/o columna (AAIERIC) | J463: =IFERROR(__xludf.DUMMYFUNCTION("""COMPUTED_VALUE"""),"Pase de viga y/o columna (AAIERIC)") -> Pase de viga y/o columna (AAIERIC) | K463: =IFERROR(__xludf.DUMMYFUNCTION("""COMPUTED_VALUE"""),"Pase de viga y/o columna (AAIERIC)") -> Pase de viga y/o columna (AAIERIC) | L463: =IFERROR(__xludf.DUMMYFUNCTION("""COMPUTED_VALUE"""),"Pase de viga y/o columna (AAIERIC)") -> Pase de viga y/o columna (AAIERIC) | ... U463: =IFERROR(__xludf.DUMMYFUNCTION("""COMPUTED_VALUE"""),"Pase de viga y/o columna (AAIERIC)") -> Pase de viga y/o columna (AAIERIC)
E465: =IFERROR(__xludf.DUMMYFUNCTION("""COMPUTED_VALUE"""),"Cable subterráneo (AAIERIC)") -> Cable subterráneo (AAIERIC) | F465: =IFERROR(__xludf.DUMMYFUNCTION("""COMPUTED_VALUE"""),"Cable subterráneo (AAIERIC)") -> Cable subterráneo (AAIERIC) | G465: =IFERROR(__xludf.DUMMYFUNCTION("""COMPUTED_VALUE"""),"Cable subterráneo (AAIERIC)") -> Cable subterráneo (AAIERIC) | H465: =IFERROR(__xludf.DUMMYFUNCTION("""COMPUTED_VALUE"""),"Cable subterráneo (AAIERIC)") -> Cable subterráneo (AAIERIC) | I465: =IFERROR(__xludf.DUMMYFUNCTION("""COMPUTED_VALUE"""),"Cable subterráneo (AAIERIC)") -> Cable subterráneo (AAIERIC) | J465: =IFERROR(__xludf.DUMMYFUNCTION("""COMPUTED_VALUE"""),"Cable subterráneo (AAIERIC)") -> Cable subterráneo (AAIERIC) | K465: =IFERROR(__xludf.DUMMYFUNCTION("""COMPUTED_VALUE"""),"Cable subterráneo (AAIERIC)") -> Cable subterráneo (AAIERIC) | L465: =IFERROR(__xludf.DUMMYFUNCTION("""COMPUTED_VALUE"""),"Cable subterráneo (AAIERIC)") -> Cable subterráneo (AAIERIC) | ... U465: =IFERROR(__xludf.DUMMYFUNCTION("""COMPUTED_VALUE"""),"Cable subterráneo (AAIERIC)") -> Cable subterráneo (AAIERIC)
E466: =IFERROR(__xludf.DUMMYFUNCTION("""COMPUTED_VALUE"""),"Cableado (AAIERIC)") -> Cableado (AAIERIC) | F466: =IFERROR(__xludf.DUMMYFUNCTION("""COMPUTED_VALUE"""),"Cableado (AAIERIC)") -> Cableado (AAIERIC) | G466: =IFERROR(__xludf.DUMMYFUNCTION("""COMPUTED_VALUE"""),"Cableado (AAIERIC)") -> Cableado (AAIERIC) | H466: =IFERROR(__xludf.DUMMYFUNCTION("""COMPUTED_VALUE"""),"Cableado (AAIERIC)") -> Cableado (AAIERIC) | I466: =IFERROR(__xludf.DUMMYFUNCTION("""COMPUTED_VALUE"""),"Cableado (AAIERIC)") -> Cableado (AAIERIC) | J466: =IFERROR(__xludf.DUMMYFUNCTION("""COMPUTED_VALUE"""),"Cableado (AAIERIC)") -> Cableado (AAIERIC) | K466: =IFERROR(__xludf.DUMMYFUNCTION("""COMPUTED_VALUE"""),"Cableado (AAIERIC)") -> Cableado (AAIERIC) | L466: =IFERROR(__xludf.DUMMYFUNCTION("""COMPUTED_VALUE"""),"Cableado (AAIERIC)") -> Cableado (AAIERIC) | ... U466: =IFERROR(__xludf.DUMMYFUNCTION("""COMPUTED_VALUE"""),"Cableado (AAIERIC)") -> Cableado (AAIERIC)
E467: =IFERROR(__xludf.DUMMYFUNCTION("""COMPUTED_VALUE"""),"Conexión de Puntos y Tomas (AAIERIC)") -> Conexión de Puntos y Tomas (AAIERIC) | F467: =IFERROR(__xludf.DUMMYFUNCTION("""COMPUTED_VALUE"""),"Conexión de Puntos y Tomas (AAIERIC)") -> Conexión de Puntos y Tomas (AAIERIC) | G467: =IFERROR(__xludf.DUMMYFUNCTION("""COMPUTED_VALUE"""),"Conexión de Puntos y Tomas (AAIERIC)") -> Conexión de Puntos y Tomas (AAIERIC) | H467: =IFERROR(__xludf.DUMMYFUNCTION("""COMPUTED_VALUE"""),"Conexión de Puntos y Tomas (AAIERIC)") -> Conexión de Puntos y Tomas (AAIERIC) | I467: =IFERROR(__xludf.DUMMYFUNCTION("""COMPUTED_VALUE"""),"Conexión de Puntos y Tomas (AAIERIC)") -> Conexión de Puntos y Tomas (AAIERIC) | J467: =IFERROR(__xludf.DUMMYFUNCTION("""COMPUTED_VALUE"""),"Conexión de Puntos y Tomas (AAIERIC)") -> Conexión de Puntos y Tomas (AAIERIC) | K467: =IFERROR(__xludf.DUMMYFUNCTION("""COMPUTED_VALUE"""),"Conexión de Puntos y Tomas (AAIERIC)") -> Conexión de Puntos y Tomas (AAIERIC) | L467: =IFERROR(__xludf.DUMMYFUNCTION("""COMPUTED_VALUE"""),"Conexión de Puntos y Tomas (AAIERIC)") -> Conexión de Puntos y Tomas (AAIERIC) | ... U467: =IFERROR(__xludf.DUMMYFUNCTION("""COMPUTED_VALUE"""),"Conexión de Puntos y Tomas (AAIERIC)") -> Conexión de Puntos y Tomas (AAIERIC)
E468: =IFERROR(__xludf.DUMMYFUNCTION("""COMPUTED_VALUE"""),"Tableros (AAIERIC)") -> Tableros (AAIERIC) | F468: =IFERROR(__xludf.DUMMYFUNCTION("""COMPUTED_VALUE"""),"Tableros (AAIERIC)") -> Tableros (AAIERIC) | G468: =IFERROR(__xludf.DUMMYFUNCTION("""COMPUTED_VALUE"""),"Tableros (AAIERIC)") -> Tableros (AAIERIC) | H468: =IFERROR(__xludf.DUMMYFUNCTION("""COMPUTED_VALUE"""),"Tableros (AAIERIC)") -> Tableros (AAIERIC) | I468: =IFERROR(__xludf.DUMMYFUNCTION("""COMPUTED_VALUE"""),"Tableros (AAIERIC)") -> Tableros (AAIERIC) | J468: =IFERROR(__xludf.DUMMYFUNCTION("""COMPUTED_VALUE"""),"Tableros (AAIERIC)") -> Tableros (AAIERIC) | K468: =IFERROR(__xludf.DUMMYFUNCTION("""COMPUTED_VALUE"""),"Tableros (AAIERIC)") -> Tableros (AAIERIC) | L468: =IFERROR(__xludf.DUMMYFUNCTION("""COMPUTED_VALUE"""),"Tableros (AAIERIC)") -> Tableros (AAIERIC) | ... U468: =IFERROR(__xludf.DUMMYFUNCTION("""COMPUTED_VALUE"""),"Tableros (AAIERIC)") -> Tableros (AAIERIC)
E469: =IFERROR(__xludf.DUMMYFUNCTION("""COMPUTED_VALUE"""),"Colocación de Artefactos de iluminación y otros (AAIERIC)") -> Colocación de Artefactos de iluminación y otros (AAIERIC) | F469: =IFERROR(__xludf.DUMMYFUNCTION("""COMPUTED_VALUE"""),"Colocación de Artefactos de iluminación y otros (AAIERIC)") -> Colocación de Artefactos de iluminación y otros (AAIERIC) | G469: =IFERROR(__xludf.DUMMYFUNCTION("""COMPUTED_VALUE"""),"Colocación de Artefactos de iluminación y otros (AAIERIC)") -> Colocación de Artefactos de iluminación y otros (AAIERIC) | H469: =IFERROR(__xludf.DUMMYFUNCTION("""COMPUTED_VALUE"""),"Colocación de Artefactos de iluminación y otros (AAIERIC)") -> Colocación de Artefactos de iluminación y otros (AAIERIC) | I469: =IFERROR(__xludf.DUMMYFUNCTION("""COMPUTED_VALUE"""),"Colocación de Artefactos de iluminación y otros (AAIERIC)") -> Colocación de Artefactos de iluminación y otros (AAIERIC) | J469: =IFERROR(__xludf.DUMMYFUNCTION("""COMPUTED_VALUE"""),"Colocación de Artefactos de iluminación y otros (AAIERIC)") -> Colocación de Artefactos de iluminación y otros (AAIERIC) | K469: =IFERROR(__xludf.DUMMYFUNCTION("""COMPUTED_VALUE"""),"Colocación de Artefactos de iluminación y otros (AAIERIC)") -> Colocación de Artefactos de iluminación y otros (AAIERIC) | L469: =IFERROR(__xludf.DUMMYFUNCTION("""COMPUTED_VALUE"""),"Colocación de Artefactos de iluminación y otros (AAIERIC)") -> Colocación de Artefactos de iluminación y otros (AAIERIC) | ... U469: =IFERROR(__xludf.DUMMYFUNCTION("""COMPUTED_VALUE"""),"Colocación de Artefactos de iluminación y otros (AAIERIC)") -> Colocación de Artefactos de iluminación y otros (AAIERIC)
E470: =IFERROR(__xludf.DUMMYFUNCTION("""COMPUTED_VALUE"""),"Acometida (amurado + conexión)") -> Acometida (amurado + conexión) | F470: =IFERROR(__xludf.DUMMYFUNCTION("""COMPUTED_VALUE"""),"Acometida (amurado + conexión)") -> Acometida (amurado + conexión) | G470: =IFERROR(__xludf.DUMMYFUNCTION("""COMPUTED_VALUE"""),"Acometida (amurado + conexión)") -> Acometida (amurado + conexión) | H470: =IFERROR(__xludf.DUMMYFUNCTION("""COMPUTED_VALUE"""),"Acometida (amurado + conexión)") -> Acometida (amurado + conexión) | I470: =IFERROR(__xludf.DUMMYFUNCTION("""COMPUTED_VALUE"""),"Acometida (amurado + conexión)") -> Acometida (amurado + conexión) | J470: =IFERROR(__xludf.DUMMYFUNCTION("""COMPUTED_VALUE"""),"Acometida (amurado + conexión)") -> Acometida (amurado + conexión) | K470: =IFERROR(__xludf.DUMMYFUNCTION("""COMPUTED_VALUE"""),"Acometida (amurado + conexión)") -> Acometida (amurado + conexión) | L470: =IFERROR(__xludf.DUMMYFUNCTION("""COMPUTED_VALUE"""),"Acometida (amurado + conexión)") -> Acometida (amurado + conexión) | ... U470: =IFERROR(__xludf.DUMMYFUNCTION("""COMPUTED_VALUE"""),"Acometida (amurado + conexión)") -> Acometida (amurado + conexión)
E471: =IFERROR(__xludf.DUMMYFUNCTION("""COMPUTED_VALUE"""),"Bandejas Portacables x metro (AAIERIC)") -> Bandejas Portacables x metro (AAIERIC) | F471: =IFERROR(__xludf.DUMMYFUNCTION("""COMPUTED_VALUE"""),"Bandejas Portacables x metro (AAIERIC)") -> Bandejas Portacables x metro (AAIERIC) | G471: =IFERROR(__xludf.DUMMYFUNCTION("""COMPUTED_VALUE"""),"Bandejas Portacables x metro (AAIERIC)") -> Bandejas Portacables x metro (AAIERIC) | H471: =IFERROR(__xludf.DUMMYFUNCTION("""COMPUTED_VALUE"""),"Bandejas Portacables x metro (AAIERIC)") -> Bandejas Portacables x metro (AAIERIC) | I471: =IFERROR(__xludf.DUMMYFUNCTION("""COMPUTED_VALUE"""),"Bandejas Portacables x metro (AAIERIC)") -> Bandejas Portacables x metro (AAIERIC) | J471: =IFERROR(__xludf.DUMMYFUNCTION("""COMPUTED_VALUE"""),"Bandejas Portacables x metro (AAIERIC)") -> Bandejas Portacables x metro (AAIERIC) | K471: =IFERROR(__xludf.DUMMYFUNCTION("""COMPUTED_VALUE"""),"Bandejas Portacables x metro (AAIERIC)") -> Bandejas Portacables x metro (AAIERIC) | L471: =IFERROR(__xludf.DUMMYFUNCTION("""COMPUTED_VALUE"""),"Bandejas Portacables x metro (AAIERIC)") -> Bandejas Portacables x metro (AAIERIC) | ... U471: =IFERROR(__xludf.DUMMYFUNCTION("""COMPUTED_VALUE"""),"Bandejas Portacables x metro (AAIERIC)") -> Bandejas Portacables x metro (AAIERIC)

Sheet Precios
A1: Codigo | B1: Fuente | C1: Tema | D1: Concepto | E1: Importe neto | F1: Notas Aclaratorias | G1: Mostrar
A2: 00-00 | B2: EPAC | D2: DOCUMENTACIÓN, CERTIFICACIÓN Y SERVICIO DE MEDICIÓN | E2: Importe Neto | F2: Notas Aclaratorias | G2: ---
A3: 00-01 | B3: EPAC | C3: Documentación Certificación y Servicio de Medición | D3: Cuota societaria | E3: 7000 | F3: Valor mensual, si pagas año adelantado se cobra el equivalente a 10 cuotas. Debemos recordarles que las cuotas se deben abonnar del 1 al 10 de cada mes. Las cuotas atrasadas se cobraran al valor del mes en curso. | G3: NO
A4: 00-02 | B4: EPAC | C4: Documentación Certificación y Servicio de Medición | D4: Visita de Inspeccion Técnica | E4: 33000 | F4: Gastos para inspección visual, tomar mediciones, realizar diagnóstico y poder emitir presupuesto. | G4: SI
A5: 00-03 | B5: EPAC | C5: Documentación Certificación y Servicio de Medición | D5: Cert. pilar de obra - Monofasico - no incluye construccion de pilar | E5: 104000 | F5: Componer documentación para subirla al ERSEP y obtener certificado de instalación eléctrica apta / No incluye construcción del pilar. | G5: SI
A6: 00-04 | B6: EPAC | C6: Documentación Certificación y Servicio de Medición | D6: Cert. pilar de obra -Trifasico - no incluye construccion de pilar | E6: 119000 | F6: Componer documentación para subirla al ERSEP y obtener certificado de instalación eléctrica apta / No incluye construcción del pilar. | G6: SI
A7: 00-05 | B7: EPAC | C7: Documentación Certificación y Servicio de Medición | D7: Cert. de vivienda o local comercial (hasta 20bocas) no incluye adecuacion de la instalacion | E7: 215000 | F7: Componer documentación para subirla al ERSEP y obtener certificado de instalación eléctrica apta / No incluye adecuación de la instalación. | G7: SI
A8: 00-06 | B8: EPAC | C8: Documentación Certificación y Servicio de Medición | D8: Costo adicional por boca | E8: 3800 | F8: Componer documentación para subirla al ERSEP y obtener certificado de instalación eléctrica apta | G8: SI
A9: 00-07 | B9: EPAC | C9: Documentación Certificación y Servicio de Medición | D9: Adicional por boca (Certificación) | E9: 3800 | F9: Se consideran una ves superadas las 20 contempladas en la Certificación de vivienda o local comercial. | G9: SI
A10: 00-08 | B10: EPAC | C10: Documentación Certificación y Servicio de Medición | D10: Medicion PAT, lu. a vie. dentro del egido urbano de Córdoba capital | E10: 29000 | F10: Para miembros de EPAC con cuota societaria al dia, consultas al 3516130597 | G10: NO
A11: 00-09 | B11: EPAC | C11: Documentación Certificación y Servicio de Medición | D11: Medicion PAT, lu. a vie. dentro del fuera urbano de Córdoba capital | E11: 77000 | F11: Para no miembros de EPAC o miembros sin cuota societaria al dia, consultas al 3516130597 | G11: NO
A12: 00-10 | B12: EPAC | C12: Documentación Certificación y Servicio de Medición | D12: Medicion PAT, adicional por km fuera del egido urbano de Córdoba capital | E12: 1700 | F12: mas valor de peaje para todo solicitante del servicio, el recorrido se considera ida y vuelta, consultas al 3516130597 | G12: NO
A13: 00-11 | B13: EPAC | C13: Documentación Certificación y Servicio de Medición | G13: NO
A14: 01-00 | B14: EPAC | D14: ACOMETIDAS Y TABLEROS | E14: Importe Neto | F14: Notas Aclaratorias | G14: ---
A15: 01-01 | B15: EPAC | C15: Acometidas y Tableros | D15: Acometida Monofásica aérea, con sistema doble aislación | E15: 146000 | F15: Estos importes corresponden a trabajos de acometidas realizadas de acuerdo a los planos típicos suministrados por la empresa distribuidora de energía ET21 de EPEC S/Materiales, sin certificación, no incluye trabajos de albañilería | G15: SI
A16: 01-02 | B16: EPAC | C16: Acometidas y Tableros | D16: Acometida Trifásica aérea, hasta 10kw con sistema doble aislación | E16: 222000 | F16: Estos importes corresponden a trabajos de acometidas realizadas de acuerdo a los plano típicos suministrados por la empresa distribuidora de energía ET21 de EPEC S/Materiales, sin certificación, no incluye trabajos de albañilería | G16: SI
A17: 01-03 | B17: EPAC | C17: Acometidas y Tableros | D17: Acometida subterránea, hasta 10kw con sistema doble aislación | E17: 200000 | F17: Estos importes corresponden a trabajos de acometidas realizadas de acuerdo a los plano típicos suministrados por la empresa distribuidora de energía ET21 de EPEC S/Materiales, sin certificación, no incluye trabajos de albañilería | G17: SI
A18: 01-04 | B18: EPAC | C18: Acometidas y Tableros | D18: Acometida Trifásica de 11 a 35kw | E18: 289000 | F18: Estos importes corresponden a trabajos de acometidas realizadas de acuerdo a los plano típicos suministrados por la empresa distribuidora de energía ET21 de EPEC S/Materiales, sin certificación, no incluye trabajos de albañilería | G18: SI
A19: 01-05 | B19: EPAC | C19: Acometidas y Tableros | D19: Acometida Trifásica de 36 a 50kw | E19: 376000 | F19: Estos importes corresponden a trabajos de acometidas realizadas de acuerdo a los plano típicos suministrados por la empresa distribuidora de energía ET21 de EPEC S/Materiales, sin certificación, no incluye trabajos de albañilería | G19: SI
A20: 01-06 | B20: EPAC | C20: Acometidas y Tableros | D20: Acometida Trifásica mas de 50kw | E20: 564000 | F20: Estos importes corresponden a trabajos de acometidas realizadas de acuerdo a los plano típicos suministrados por la empresa distribuidora de energía ET21 de EPEC S/Materiales, sin certificación, no incluye trabajos de albañilería | G20: SI
A21: 01-07 | B21: EPAC | C21: Acometidas y Tableros | D21: Fijación tablero de superficie (hasta 54 bocas) | E21: 26900 | F21: Fijación de gabinete a la pared mediante tarugos Fischer u otro elemento | G21: SI
C22: Acometidas y Tableros | D22: Fijación tablero de superficie | E22: 26900 | F22: Fijación de gabinete a la pared mediante tarugos Fischer u otro elemento
A23: 01-08 | B23: EPAC | C23: Acometidas y Tableros | D23: Empotrado de gabinete en mampostería (de 1 a 24 bocas) | E23: 66600 | F23: Picado de pared y fijación de gabinete mediante mortero, incluye fijación de canalizaciones mediante conectores | G23: SI
C24: Acometidas y Tableros | D24: Empotrado / Fijación de gabinete en mampostería | E24: 66600 | F24: Picado/preparado de pared y fijación de gabinete
A25: 01-09 | B25: EPAC | C25: Acometidas y Tableros | D25: Empotrado de gabinete en mampostería (de 25 a 54 bocas) | E25: 96600 | F25: Picado de pared y fijación de gabinete mediante mortero, incluye fijación de canalizaciones mediante conectores | G25: SI
A26: 01-10 | B26: EPAC | C26: Acometidas y Tableros | D26: Armado de tablero de obra | E26: 110800 | F26: Se considera fijación de tablero a superficie, mas un ID y 2 ITM | G26: SI
A27: 01-11 | B27: EPAC | C27: Acometidas y Tableros | D27: Zanjeo x metro ( 25 x 80cm) mas tendido de cable subterraneo hasta 4x10mm y relleno con protecciones mecánicas para longitudes de cable menor a 10 metros | E27: 27500 | F27: Incluye: Zanjeo a 80cm de Prof., colocación de cable, cama de arena, protección mecánica, llenado de zanja y apisonado. No incluyen Materiales. | G27: SI
A28: 01-12 | B28: EPAC | C28: Acometidas y Tableros | D28: Zanjeo x metro ( 25 x 80cm) mas tendido de cable subterraneo hasta 4x10mm y relleno con protecciones mecánicas para longitudes de cable mayor a 10 metros | E28: 19300 | F28: Incluye: Zanjeo a 80cm de Prof., colocación de cable, cama de arena, protección mecánica, y llenado de zanja y apisonado | G28: SI
A29: 01-13 | B29: EPAC | C29: Acometidas y Tableros | D29: Puesta a tierra: jabalina+caja de inspección | E29: 95700 | F29: Incluye: Hincado de jabalina, fijación de caja de inspección , canaleteado de cañería desde tablero a la c. de inspección (2mts lineal) y conexión del conductos a jabalina, en caso de suelos duros incrementar costo en 30% | G29: SI
A30: 02-00 | B30: EPAC | D30: CANALIZACIÓN EMBUTIDA | E30: Importe Neto | F30: Notas Aclaratorias | G30: SI
A31: 02-01 | B31: EPAC | C31: Canalización Embutido | D31: Cañería PVC rígido y caja de boca (centro, aplique y toma) hasta 50 bocas, Solo MO | E31: 39100 | F31: Para las cajas en losa, estos ítem incluyen los tramos de cañería que llegan o salen de la caja y la caja propiamente dicha. Para cajas en paredes, comprende el canaleteado de un promedio de 3mts de cañería y la caja rectangular, octogonal o cuadrada. Por lo general los tamaños de los tableros son proporcionales a los circuitos de la instalación , y en consecuencia a la cantidad de caños que acometan al gabinete; por ello el canaleteado y amurado será más complejo y más oneroso cuanto más caños acometan. Las cajas de paso y/o derivación tienen tanto trabajo como una boca (boca definida por la reglamentación AEA: punto de un circuito terminal, donde se conecta el aparato utilizador por medio de tomacorrientes o por medio de conexiones fijas -uniones o borneras- Considerar que una boca puede ser a la vez: a) una caja de paso o una caja de derivación con un único circuito, o b)una caja de paso con más de un circuito, o una caja de derivación con más de un circuito o una caja de paso y derivación, si están ubicadas a una altura no inferior a 1,8mts. Los criterios generales para la consideración de la instalación de cajas en inmuebles, están especificadas la reglamentación AEA 90364 parte 7 -771 paginas 42 a 44). | G31: SI
A32: 02-02 | B32: EPAC | C32: Canalización Embutido | D32: Cañería PVC rígido y caja de paso y/o distribución, hasta 50 bocas, Solo MO | E32: 39100 | F32: Para las cajas en losa, estos ítem incluyen los tramos de cañería que llegan o salen de la caja y la caja propiamente dicha. Para cajas en paredes, comprende el canaleteado de un promedio de 3mts de cañería y la caja rectangular, octogonal o cuadrada. Por lo general los tamaños de los tableros son proporcionales a los circuitos de la instalación , y en consecuencia a la cantidad de caños que acometan al gabinete; por ello el canaleteado y amurado será más complejo y más oneroso cuanto más caños acometan. Las cajas de paso y/o derivación tienen tanto trabajo como una boca (boca definida por la reglamentación AEA: punto de un circuito terminal, donde se conecta el aparato utilizador por medio de tomacorrientes o por medio de conexiones fijas -uniones o borneras- Considerar que una boca puede ser a la vez: a) una caja de paso o una caja de derivación con un único circuito, o b)una caja de paso con más de un circuito, o una caja de derivación con más de un circuito o una caja de paso y derivación, si están ubicadas a una altura no inferior a 1,8mts. Los criterios generales para la consideración de la instalación de cajas en inmuebles, están especificadas la reglamentación AEA 90364 parte 7 -771 paginas 42 a 44). | G32: SI
A33: 02-03 | B33: EPAC | C33: Canalización Embutido | D33: Cañería PVC rígido y Caja para interruptores (punto o combinación) hasta 50 bocas, Solo MO | E33: 39100 | F33: Para las cajas en losa, estos ítem incluyen los tramos de cañería que llegan o salen de la caja y la caja propiamente dicha. Para cajas en paredes, comprende el canaleteado de un promedio de 3mts de cañería y la caja rectangular, octogonal o cuadrada. Por lo general los tamaños de los tableros son proporcionales a los circuitos de la instalación , y en consecuencia a la cantidad de caños que acometan al gabinete; por ello el canaleteado y amurado será más complejo y más oneroso cuanto más caños acometan. Las cajas de paso y/o derivación tienen tanto trabajo como una boca (boca definida por la reglamentación AEA: punto de un circuito terminal, donde se conecta el aparato utilizador por medio de tomacorrientes o por medio de conexiones fijas -uniones o borneras- Considerar que una boca puede ser a la vez: a) una caja de paso o una caja de derivación con un único circuito, o b)una caja de paso con más de un circuito, o una caja de derivación con más de un circuito o una caja de paso y derivación, si están ubicadas a una altura no inferior a 1,8mts. Los criterios generales para la consideración de la instalación de cajas en inmuebles, están especificadas la reglamentación AEA 90364 parte 7 -771 paginas 42 a 44). | G33: SI
A34: 02-04 | B34: EPAC | C34: Canalización Embutido | D34: Cañería PVC rígido y caja de Boca(centro, aplique y toma) de 51 a 100 bocas, Solo MO | E34: 34700 | F34: Para las cajas en losa, estos ítem incluyen los tramos de cañería que llegan o salen de la caja y la caja propiamente dicha. Para cajas en paredes, comprende el canaleteado de un promedio de 3mts de cañería y la caja rectangular, octogonal o cuadrada. Por lo general los tamaños de los tableros son proporcionales a los circuitos de la instalación , y en consecuencia a la cantidad de caños que acometan al gabinete; por ello el canaleteado y amurado será más complejo y más oneroso cuanto más caños acometan. Las cajas de paso y/o derivación tienen tanto trabajo como una boca (boca definida por la reglamentación AEA: punto de un circuito terminal, donde se conecta el aparato utilizador por medio de tomacorrientes o por medio de conexiones fijas -uniones o borneras- Considerar que una boca puede ser a la vez: a) una caja de paso o una caja de derivación con un único circuito, o b)una caja de paso con más de un circuito, o una caja de derivación con más de un circuito o una caja de paso y derivación, si están ubicadas a una altura no inferior a 1,8mts. Los criterios generales para la consideración de la instalación de cajas en inmuebles, están especificadas la reglamentación AEA 90364 parte 7 -771 paginas 42 a 44). | G34: SI
A35: 02-05 | B35: EPAC | C35: Canalización Embutido | D35: Cañería PVC rígido y caja de paso y/o distribución, de 51 a 100 bocas, Solo MO | E35: 34700 | F35: Para las cajas en losa, estos ítem incluyen los tramos de cañería que llegan o salen de la caja y la caja propiamente dicha. Para cajas en paredes, comprende el canaleteado de un promedio de 3mts de cañería y la caja rectangular, octogonal o cuadrada. Por lo general los tamaños de los tableros son proporcionales a los circuitos de la instalación , y en consecuencia a la cantidad de caños que acometan al gabinete; por ello el canaleteado y amurado será más complejo y más oneroso cuanto más caños acometan. Las cajas de paso y/o derivación tienen tanto trabajo como una boca (boca definida por la reglamentación AEA: punto de un circuito terminal, donde se conecta el aparato utilizador por medio de tomacorrientes o por medio de conexiones fijas -uniones o borneras- Considerar que una boca puede ser a la vez: a) una caja de paso o una caja de derivación con un único circuito, o b)una caja de paso con más de un circuito, o una caja de derivación con más de un circuito o una caja de paso y derivación, si están ubicadas a una altura no inferior a 1,8mts. Los criterios generales para la consideración de la instalación de cajas en inmuebles, están especificadas la reglamentación AEA 90364 parte 7 -771 paginas 42 a 44). | G35: SI
A36: 02-06 | B36: EPAC | C36: Canalización Embutido | D36: Cañería PVC rígido y Caja para interruptores (punto o combinación) de 51 a 100 bocas, Solo MO | E36: 34700 | F36: Para las cajas en losa, estos ítem incluyen los tramos de cañería que llegan o salen de la caja y la caja propiamente dicha. Para cajas en paredes, comprende el canaleteado de un promedio de 3mts de cañería y la caja rectangular, octogonal o cuadrada. Por lo general los tamaños de los tableros son proporcionales a los circuitos de la instalación , y en consecuencia a la cantidad de caños que acometan al gabinete; por ello el canaleteado y amurado será más complejo y más oneroso cuanto más caños acometan. Las cajas de paso y/o derivación tienen tanto trabajo como una boca (boca definida por la reglamentación AEA: punto de un circuito terminal, donde se conecta el aparato utilizador por medio de tomacorrientes o por medio de conexiones fijas -uniones o borneras- Considerar que una boca puede ser a la vez: a) una caja de paso o una caja de derivación con un único circuito, o b)una caja de paso con más de un circuito, o una caja de derivación con más de un circuito o una caja de paso y derivación, si están ubicadas a una altura no inferior a 1,8mts. Los criterios generales para la consideración de la instalación de cajas en inmuebles, están especificadas la reglamentación AEA 90364 parte 7 -771 paginas 42 a 44). | G36: SI
A37: 02-07 | B37: EPAC | C37: Canalización Embutido | D37: Cañería PVC rígido y Colocación de TABLERO: multiplicar por 5 (bocas) | E37: 34700 | F37: Para las cajas en losa, estos ítem incluyen los tramos de cañería que llegan o salen de la caja y la caja propiamente dicha. Para cajas en paredes, comprende el canaleteado de un promedio de 3mts de cañería y la caja rectangular, octogonal o cuadrada. Por lo general los tamaños de los tableros son proporcionales a los circuitos de la instalación , y en consecuencia a la cantidad de caños que acometan al gabinete; por ello el canaleteado y amurado será más complejo y más oneroso cuanto más caños acometan. Las cajas de paso y/o derivación tienen tanto trabajo como una boca (boca definida por la reglamentación AEA: punto de un circuito terminal, donde se conecta el aparato utilizador por medio de tomacorrientes o por medio de conexiones fijas -uniones o borneras- Considerar que una boca puede ser a la vez: a) una caja de paso o una caja de derivación con un único circuito, o b)una caja de paso con más de un circuito, o una caja de derivación con más de un circuito o una caja de paso y derivación, si están ubicadas a una altura no inferior a 1,8mts. Los criterios generales para la consideración de la instalación de cajas en inmuebles, están especificadas la reglamentación AEA 90364 parte 7 -771 paginas 42 a 44). | G37: SI
A38: 02-08 | B38: EPAC | C38: Canalización Embutido | D38: Cañería PVC flexible y caja de Boca (centro, aplique y toma) hasta 50 bocas, Solo MO | E38: 29000 | F38: Para las cajas en losa, estos ítem incluyen los tramos de cañería que llegan o salen de la caja y la caja propiamente dicha. Para cajas en paredes, comprende el canaleteado de un promedio de 3mts de cañería y la caja rectangular, octogonal o cuadrada. Por lo general los tamaños de los tableros son proporcionales a los circuitos de la instalación , y en consecuencia a la cantidad de caños que acometan al gabinete; por ello el canaleteado y amurado será más complejo y más oneroso cuanto más caños acometan. Las cajas de paso y/o derivación tienen tanto trabajo como una boca (boca definida por la reglamentación AEA: punto de un circuito terminal, donde se conecta el aparato utilizador por medio de tomacorrientes o por medio de conexiones fijas -uniones o borneras- Considerar que una boca puede ser a la vez: a) una caja de paso o una caja de derivación con un único circuito, o b)una caja de paso con más de un circuito, o una caja de derivación con más de un circuito o una caja de paso y derivación, si están ubicadas a una altura no inferior a 1,8mts. Los criterios generales para la consideración de la instalación de cajas en inmuebles, están especificadas la reglamentación AEA 90364 parte 7 -771 paginas 42 a 44). | G38: SI
A39: 02-09 | B39: EPAC | C39: Canalización Embutido | D39: Cañería PVC flexible y caja de paso y/o distribución, hasta 50 bocas, Solo MO | E39: 29000 | F39: Para las cajas en losa, estos ítem incluyen los tramos de cañería que llegan o salen de la caja y la caja propiamente dicha. Para cajas en paredes, comprende el canaleteado de un promedio de 3mts de cañería y la caja rectangular, octogonal o cuadrada. Por lo general los tamaños de los tableros son proporcionales a los circuitos de la instalación , y en consecuencia a la cantidad de caños que acometan al gabinete; por ello el canaleteado y amurado será más complejo y más oneroso cuanto más caños acometan. Las cajas de paso y/o derivación tienen tanto trabajo como una boca (boca definida por la reglamentación AEA: punto de un circuito terminal, donde se conecta el aparato utilizador por medio de tomacorrientes o por medio de conexiones fijas -uniones o borneras- Considerar que una boca puede ser a la vez: a) una caja de paso o una caja de derivación con un único circuito, o b)una caja de paso con más de un circuito, o una caja de derivación con más de un circuito o una caja de paso y derivación, si están ubicadas a una altura no inferior a 1,8mts. Los criterios generales para la consideración de la instalación de cajas en inmuebles, están especificadas la reglamentación AEA 90364 parte 7 -771 paginas 42 a 44). | G39: SI
A40: 02-10 | B40: EPAC | C40: Canalización Embutido | D40: Cañería PVC flexible y Caja para interruptores (punto o combinación) hasta 50 bocas, Solo MO | E40: 29000 | F40: Para las cajas en losa, estos ítem incluyen los tramos de cañería que llegan o salen de la caja y la caja propiamente dicha. Para cajas en paredes, comprende el canaleteado de un promedio de 3mts de cañería y la caja rectangular, octogonal o cuadrada. Por lo general los tamaños de los tableros son proporcionales a los circuitos de la instalación , y en consecuencia a la cantidad de caños que acometan al gabinete; por ello el canaleteado y amurado será más complejo y más oneroso cuanto más caños acometan. Las cajas de paso y/o derivación tienen tanto trabajo como una boca (boca definida por la reglamentación AEA: punto de un circuito terminal, donde se conecta el aparato utilizador por medio de tomacorrientes o por medio de conexiones fijas -uniones o borneras- Considerar que una boca puede ser a la vez: a) una caja de paso o una caja de derivación con un único circuito, o b)una caja de paso con más de un circuito, o una caja de derivación con más de un circuito o una caja de paso y derivación, si están ubicadas a una altura no inferior a 1,8mts. Los criterios generales para la consideración de la instalación de cajas en inmuebles, están especificadas la reglamentación AEA 90364 parte 7 -771 paginas 42 a 44). | G40: SI
A41: 02-11 | B41: EPAC | C41: Canalización Embutido | D41: Cañería PVC flexible y caja de Boca(centro, aplique y toma) de 51 a 100 bocas, Solo MO | E41: 23700 | F41: Para las cajas en losa, estos ítem incluyen los tramos de cañería que llegan o salen de la caja y la caja propiamente dicha. Para cajas en paredes, comprende el canaleteado de un promedio de 3mts de cañería y la caja rectangular, octogonal o cuadrada. Por lo general los tamaños de los tableros son proporcionales a los circuitos de la instalación , y en consecuencia a la cantidad de caños que acometan al gabinete; por ello el canaleteado y amurado será más complejo y más oneroso cuanto más caños acometan. Las cajas de paso y/o derivación tienen tanto trabajo como una boca (boca definida por la reglamentación AEA: punto de un circuito terminal, donde se conecta el aparato utilizador por medio de tomacorrientes o por medio de conexiones fijas -uniones o borneras- Considerar que una boca puede ser a la vez: a) una caja de paso o una caja de derivación con un único circuito, o b)una caja de paso con más de un circuito, o una caja de derivación con más de un circuito o una caja de paso y derivación, si están ubicadas a una altura no inferior a 1,8mts. Los criterios generales para la consideración de la instalación de cajas en inmuebles, están especificadas la reglamentación AEA 90364 parte 7 -771 paginas 42 a 44). | G41: SI
A42: 02-12 | B42: EPAC | C42: Canalización Embutido | D42: Cañería PVC flexible y caja de paso y/o distribución, de 51 a 100 bocas, Solo MO | E42: 23700 | F42: Para las cajas en losa, estos ítem incluyen los tramos de cañería que llegan o salen de la caja y la caja propiamente dicha. Para cajas en paredes, comprende el canaleteado de un promedio de 3mts de cañería y la caja rectangular, octogonal o cuadrada. Por lo general los tamaños de los tableros son proporcionales a los circuitos de la instalación , y en consecuencia a la cantidad de caños que acometan al gabinete; por ello el canaleteado y amurado será más complejo y más oneroso cuanto más caños acometan. Las cajas de paso y/o derivación tienen tanto trabajo como una boca (boca definida por la reglamentación AEA: punto de un circuito terminal, donde se conecta el aparato utilizador por medio de tomacorrientes o por medio de conexiones fijas -uniones o borneras- Considerar que una boca puede ser a la vez: a) una caja de paso o una caja de derivación con un único circuito, o b)una caja de paso con más de un circuito, o una caja de derivación con más de un circuito o una caja de paso y derivación, si están ubicadas a una altura no inferior a 1,8mts. Los criterios generales para la consideración de la instalación de cajas en inmuebles, están especificadas la reglamentación AEA 90364 parte 7 -771 paginas 42 a 44). | G42: SI
... A51: 02-21 | B51: EPAC | C51: Canalización Embutido | D51: Cañería Metálica + Colocación de TABLERO: multiplicar por 5(Bocas) | E51: 43400 | F51: Para las cajas en losa, estos ítem incluyen los tramos de cañería que llegan o salen de la caja y la caja propiamente dicha. Para cajas en paredes, comprende el canaleteado de un promedio de 3mts de cañería y la caja rectangular, octogonal o cuadrada. Por lo general los tamaños de los tableros son proporcionales a los circuitos de la instalación , y en consecuencia a la cantidad de caños que acometan al gabinete; por ello el canaleteado y amurado será más complejo y más oneroso cuanto más caños acometan. Las cajas de paso y/o derivación tienen tanto trabajo como una boca (boca definida por la reglamentación AEA: punto de un circuito terminal, donde se conecta el aparato utilizador por medio de tomacorrientes o por medio de conexiones fijas -uniones o borneras- Considerar que una boca puede ser a la vez: a) una caja de paso o una caja de derivación con un único circuito, o b)una caja de paso con más de un circuito, o una caja de derivación con más de un circuito o una caja de paso y derivación, si están ubicadas a una altura no inferior a 1,8mts. Los criterios generales para la consideración de la instalación de cajas en inmuebles, están especificadas la reglamentación AEA 90364 parte 7 -771 paginas 42 a 44). | G51: SI
A52: 03-00 | B52: EPAC | D52: CANALIZACIÓN EMBUTIDA EN DURLOCK | E52: Importe Neto | F52: Notas Aclaratorias | G52: SI
A53: 03-01 | B53: EPAC | C53: Canalización Embutido en Durlock | D53: Cañería PVC rígido de Boca(centro, aplique , toma ,caja de interruptores y de distribución) hasta 50 cajas | E53: 36200 | F53: Las cañerías en Durlock deben rigidizarse correctamente para evitar fallas al momento del cableado. | G53: SI
A54: 03-02 | B54: EPAC | C54: Canalización Embutido en Durlock | D54: Cañería Metálica de Boca(centro, aplique , toma, caja de interruptores y de distribución) hasta 50 bocas | E54: 36200 | F54: Las cañerías en Durlock deben rigidizarse correctamente para evitar fallas al momento del cableado. | G54: SI
A55: 04-00 | B55: EPAC | D55: CANALIZACIÓN EXTERIOR | E55: Importe Neto | F55: Notas Aclaratorias | G55: SI
A56: 04-01 | B56: EPAC | C56: Canalización Exterior | D56: Cañería PVC x Boca (centro, aplique, toma, caja de interruptores y de distribución) hasta 50 bocas | E56: 34500 | F56: Se considera hasta 5m de cañería entre bocas. Al momento de presupuestar considerar las curvas entre bocas para agregar cajas de paso/derivación, o en caso de columnas/vigas prever perforación de la misma. No es recomendable utilizar grampas tipo omega en ambientes húmedos o con polvos en suspensión, para evitar acumulación de agua o polvo entre el caño y el muro. Cuando se exija el empleo de empalmes con cuplas y conectores roscados incrementar el costo en un 25% | G56: SI
A57: 04-02 | B57: EPAC | C57: Canalización Exterior | D57: Cañería PVC x Boca (centro, aplique, toma, caja de interruptores y de distribución) desde 51 hasta 100 bocas | E57: 31700 | F57: Se considera hasta 5m de cañería entre bocas. Al momento de presupuestar considerar las curvas entre bocas para agregar cajas de paso/derivación, o en caso de columnas/vigas prever perforación de la misma. No es recomendable utilizar grampas tipo omega en ambientes húmedos o con polvos en suspensión, para evitar acumulación de agua o polvo entre el caño y el muro. Cuando se exija el empleo de empalmes con cuplas y conectores roscados incrementar el costo en un 25% | G57: SI
A58: 04-03 | B58: EPAC | C58: Canalización Exterior | D58: Cañería Metálica x Boca (centro, aplique, toma, caja de interruptores y de distribución) hasta 50 bocas | E58: 37900 | F58: Se considera hasta 5m de cañería entre bocas. Al momento de presupuestar considerar las curvas entre bocas para agregar cajas de paso/derivación, o en caso de columnas/vigas prever perforación de la misma. No es recomendable utilizar grampas tipo omega en ambientes húmedos o con polvos en suspensión, para evitar acumulación de agua o polvo entre el caño y el muro. Cuando se exija el empleo de empalmes con cuplas y conectores roscados incrementar el costo en un 25% | G58: SI
A59: 04-04 | B59: EPAC | C59: Canalización Exterior | D59: Cañería Metálica x Boca (centro, aplique, toma, caja de interruptores y de distribución) de 51 a 100 bocas | E59: 34900 | F59: Se considera hasta 5m de cañería entre bocas. Al momento de presupuestar considerar las curvas entre bocas para agregar cajas de paso/derivación, o en caso de columnas/vigas prever perforación de la misma. No es recomendable utilizar grampas tipo omega en ambientes húmedos o con polvos en suspensión, para evitar acumulación de agua o polvo entre el caño y el muro. Cuando se exija el empleo de empalmes con cuplas y conectores roscados incrementar el costo en un 25% | G59: SI
A60: 04-05 | B60: EPAC | C60: Canalización Exterior | D60: Metro adicional (canalización exterior) | E60: 6900 | F60: Se considera hasta 5m de cañería entre bocas. Al momento de presupuestar considerar las curvas entre bocas para agregar cajas de paso/derivación, o en caso de columnas/vigas prever perforación de la misma. No es recomendable utilizar grampas tipo omega en ambientes húmedos o con polvos en suspensión, para evitar acumulación de agua o polvo entre el caño y el muro. Cuando se exija el empleo de empalmes con cuplas y conectores roscados incrementar el costo en un 25% | G60: SI
A61: 05-00 | B61: EPAC | D61: CANALIZACIÓN DE CABLE CANAL | E61: Importe Neto | F61: Notas Aclaratorias | G61: SI
A62: 05-01 | B62: EPAC | C62: Canalización Cable - Canal | D62: Canal. Cable Canal x boca | E62: 30600 | F62: Se considera hasta 4m de cable canal de 14x7 hasta 75x17, incluye instalación de caja y accesorios de instalación. Al momento de presupuestar tener en cuenta costos de fijación del cable canal (tarugos o pegamentos especiales) Corresponde a cable canal para servicios de alimentación de 220v, comunicación y red; compartidos en el mismo canal separados por tabique
A63: 05-02 | B63: EPAC | C63: Canalización Cable - Canal | D63: Canal. Cable Canal hasta 50 bocas | E63: 30600 | F63: Se considera hasta 4m de cable canal de 14x7 hasta 75x17, incluye instalación de caja y accesorios de instalación. Al momento de presupuestar tener en cuenta costos de fijación del cable canal (tarugos o pegamentos especiales) Corresponde a cable canal para servicios de alimentación de 220v, comunicación y red; compartidos en el mismo canal separados por tabique | G63: SI
A64: 05-03 | B64: EPAC | C64: Canalización Cable - Canal | D64: Canal. Cable Canal de 51 a 100 bocas | E64: 28900 | F64: Se considera hasta 4m de cable canal de 14x7 hasta 75x17, incluye instalación de caja y accesorios de instalación. al momento de presupuestar tener en cuenta costos de fijación del cable canal (tarugos o pegamentos especiales) Corresponde a cable canal para servicios de alimentación de 220v, comunicación y red; compartidos en el mismo canal separados por tabique | G64: SI
A65: 05-04 | B65: EPAC | C65: Canalización Cable - Canal | D65: Metro adicional / canal. Cable Canal | E65: 5700 | F65: Se considera hasta 4m de cable canal de 14x7 hasta 75x17, incluye instalación de caja y accesorios de instalación. al momento de presupuestar tener en cuenta costos de fijación del cable canal (tarugos o pegamentos especiales) Corresponde a cable canal para servicios de alimentación de 220v, comunicación y red; compartidos en el mismo canal separados por tabique | G65: SI
A66: 06-00 | B66: EPAC | D66: CANALIZACIÓN Y CABLEADO CON PISO DUCTOS / POLIDUCTOS | E66: Importe Neto | F66: Notas Aclaratorias | G66: SI
A67: 06-01 | B67: EPAC | C67: Canalización y Cableado con Piso Ductos / Poliductos | D67: Instalación de piso ductos x metros | E67: 34600 | F67: Comprende el armado de canalización con conductos de sección rectangular, con cuplas niveladoras entre tramos, sin relleno de hormigón. | G67: SI
A68: 06-02 | B68: EPAC | C68: Canalización y Cableado con Piso Ductos / Poliductos | D68: Colocación de cajas de piso de tomas y o derivación o curvas verticales o curvas horizontales | E68: 89800 | F68: Comprende el armado de canalización con conductos de sección rectangular, con cuplas niveladoras entre tramos, sin relleno de hormigón. | G68: SI
A69: 06-03 | B69: EPAC | C69: Canalización y Cableado con Piso Ductos / Poliductos | D69: Colocación de periscopios | E69: 47500 | F69: Comprende el armado de canalización con conductos de sección rectangular, con cuplas niveladoras entre tramos, sin relleno de hormigón. | G69: SI
A70: 06-04 | B70: EPAC | C70: Canalización y Cableado con Piso Ductos / Poliductos | D70: Cableado por cada vía del piso ducto con cables de alimentación y/o de comunicación | E70: 39500 | F70: Comprende el armado de canalización con conductos de sección rectangular, con cuplas niveladoras entre tramos, sin relleno de hormigón. | G70: SI
A71: 06-05 | B71: EPAC | C71: Canalización y Cableado con Piso Ductos / Poliductos | D71: Instalación de tomas en periscopios | E71: 20500 | F71: Comprende el armado de canalización con conductos de sección rectangular, con cuplas niveladoras entre tramos, sin relleno de hormigón. | G71: SI
A72: 06-06 | B72: EPAC | C72: Canalización y Cableado con Piso Ductos / Poliductos | D72: Colocación de Tomas de TV,. Te con cableado | E72: 20500 | F72: Comprende el armado de canalización con conductos de sección rectangular, con cuplas niveladoras entre tramos, sin relleno de hormigón. | G72: SI
A73: 06-07 | B73: EPAC | C73: Canalización y Cableado con Piso Ductos / Poliductos | D73: Colocación de Tomas de Red con cableado | E73: 47600 | F73: Comprende el armado de canalización con conductos de sección rectangular, con cuplas niveladoras entre tramos, sin relleno de hormigón. | G73: SI
A74: 07-00 | B74: EPAC | D74: CANALIZACIÓN CON BANDEJAS PORTA CABLES Y PERFIL C | E74: Importe Neto | F74: Notas Aclaratorias | G74: SI
A75: 07-01 | B75: EPAC | C75: Canalización con Bandejas Porta Cables y Perfil C | D75: Instalación a altura h<4mts, anchos de bandeja hasta 300mm (escalera o perforada) C/ménsula | E75: 37200 | F75: Costos por tramos de 3m No incluye el alquiler de andamios, escaleras, elevadores etc. | G75: SI
A76: 07-02 | B76: EPAC | C76: Canalización con Bandejas Porta Cables y Perfil C | D76: Instalación a altura h<4mts, anchos de bandeja de 450 y 600mm (escalera o perforada) C/ménsula | E76: 47600 | F76: Costos por tramos de 3m No incluye el alquiler de andamios, escaleras, elevadores etc. | G76: SI
A77: 07-03 | B77: EPAC | C77: Canalización con Bandejas Porta Cables y Perfil C | D77: Instalación a altura h>4mts, anchos de bandeja hasta 300mm (escalera o perforada) C/ménsula | E77: 37200 | F77: Costos por tramos de 3m No incluye el alquiler de andamios, escaleras, elevadores etc. | G77: SI
A78: 07-04 | B78: EPAC | C78: Canalización con Bandejas Porta Cables y Perfil C | D78: Instalación a altura h>4mts, anchos de bandeja de 450 y 600mm (escalera o perforada) C/ménsula | E78: 47600 | F78: Costos por tramos de 3m No incluye el alquiler de andamios, escaleras, elevadores etc. | G78: SI
A79: 07-05 | B79: EPAC | C79: Canalización con Bandejas Porta Cables y Perfil C | D79: Instalación a altura h<4mts con perfil C P/ BPC 100 a 300 | E79: 51700 | F79: Costos por tramos de 3m No incluye el alquiler de andamios, escaleras, elevadores etc. | G79: SI
A80: 07-06 | B80: EPAC | C80: Canalización con Bandejas Porta Cables y Perfil C | D80: Instalación a altura h<4mts con perfil C P/ BPC 450 a 600 | E80: 53800 | F80: Costos por tramos de 3m No incluye el alquiler de andamios, escaleras, elevadores etc. | G80: SI
A81: 08-00 | B81: EPAC | D81: CABLEADOS EN CAÑERÍAS | E81: Importe Neto | F81: Notas Aclaratorias | G81: SI
A82: 08-01 | B82: EPAC | C82: Cableados en Cañerías | D82: Cableado de Boca (centro, aplique y toma) hasta 50 bocas | E82: 16500 | F82: Este Valor es orientativo si se debe realizar cableado solo, El cableado en cañería es independiente de la cantidad de conductores, pues todos deben pasarse a la misma ves en un solo acto; por lo tanto no diferenciamos entre cableado de bocas de un efecto , de dos o tres, o combinación. La diferencia el costo está en el importe del elemento interruptor a instalarse en las cajas rectangulares. | G82: SI
A83: 08-02 | B83: EPAC | C83: Cableados en Cañerías | D83: Cableado de Boca (centro, aplique y toma) de 51 a 100 bocas | E83: 14400 | F83: Este Valor es orientativo si se debe realizar cableado solo, El cableado en cañería es independiente de la cantidad de conductores, pues todos deben pasarse a la misma ves en un solo acto; por lo tanto no diferenciamos entre cableado de bocas de un efecto , de dos o tres, o combinación. La diferencia el costo está en el importe del elemento interruptor a instalarse en las cajas rectangulares. | G83: SI
A84: 08-03 | B84: EPAC | C84: Cableados en Cañerías | D84: Recableado (incluye sacar artef, llaves y colocar nueva instalación) por Boca | E84: 56500 | F84: Este Valor es orientativo si se debe realizar cableado solo, El cableado en cañería es independiente de la cantidad de conductores, pues todos deben pasarse a la misma ves en un solo acto; por lo tanto no diferenciamos entre cableado de bocas de un efecto , de dos o tres, o combinación. La diferencia el costo está en el importe del elemento interruptor a instalarse en las cajas rectangulares. | G84: SI
A85: 09-00 | B85: EPAC | D85: CABLEADO EN BANDEJAS PORTA CABLES | E85: Importe Neto | F85: Notas Aclaratorias | G85: SI
A86: 09-01 | B86: EPAC | C86: Cableado en Bande. Porta - Cables | D86: Cableado de cables subterráneos hasta 4 x 10mm² o 1 x 35mm² a h < 4mts (x metros) | E86: 6200 | G86: SI
A87: 09-02 | B87: EPAC | C87: Cableado en Bande. Porta - Cables | D87: Cableado de cables subterráneos mayores a 4 x 10mm² o mayores 1 x 35mm² a h < 4mts (x metros) | E87: 8900 | G87: SI
A88: 09-03 | B88: EPAC | C88: Cableado en Bande. Porta - Cables | D88: Cableado de cables subterráneos hasta 4 x 10mm² o 1 x 35mm² a h > 4mts (xmetros) | E88: 11700 | G88: SI
A89: 09-04 | B89: EPAC | C89: Cableado en Bande. Porta - Cables | D89: Cableado de cables subterráneos mayores a 4 x 10mm² o mayores 1 x 35mm² a h > 4mts (x metros) | E89: 19300 | G89: SI
A90: 10-00 | B90: EPAC | D90: COLOCACIÓN DE INTERRUPTORES, TOMAS, ETC. | E90: Importe Neto | F90: Notas Aclaratorias | G90: SI
A91: 10-01 | B91: EPAC | C91: Colocación de Interruptores, tomas, etc | D91: Instalación de interruptores un efecto y/o pulsadores entre 1 y 10 bocas | E91: 11700 | F91: Importante: solo se admite la instalación de "punto más toma" en una caja rectangular en los baños de inmuebles. El toma ira conectado al circuito de iluminación. Las reglas del buen arte recomienda colocar el tomacorriente en una caja rectangular, en la zona 3 y conectado a un circuito de tomacorrientes. | G91: SI
A92: 10-02 | B92: EPAC | C92: Colocación de Interruptores, tomas, etc | D92: Instalación de interruptores un efecto y/o pulsadores mas de 11 bocas | E92: 10300 | F92: Importante: solo se admite la instalación de "punto más toma" en una caja rectangular en los baños de inmuebles. El toma ira conectado al circuito de iluminación. Las reglas del buen arte recomienda colocar el tomacorriente en una caja rectangular, en la zona 3 y conectado a un circuito de tomacorrientes. | G92: SI
A93: 10-03 | B93: EPAC | C93: Colocación de Interruptores, tomas, etc | D93: Instalación de interruptores un efecto combinación | E93: 17600 | F93: Importante: solo se admite la instalación de "punto más toma" en una caja rectangular en los baños de inmuebles. El toma ira conectado al circuito de iluminación. Las reglas del buen arte recomienda colocar el tomacorriente en una caja rectangular, en la zona 3 y conectado a un circuito de tomacorrientes. | G93: SI
A94: 10-04 | B94: EPAC | C94: Colocación de Interruptores, tomas, etc | D94: Instalación de tomacorrientes simple entre 1 y 10 bocas | E94: 11700 | F94: Importante: solo se admite la instalación de "punto más toma" en una caja rectangular en los baños de inmuebles. El toma ira conectado al circuito de iluminación. Las reglas del buen arte recomienda colocar el tomacorriente en una caja rectangular, en la zona 3 y conectado a un circuito de tomacorrientes. | G94: SI
A95: 10-05 | B95: EPAC | C95: Colocación de Interruptores, tomas, etc | D95: Instalación de tomacorrientes simple mas de 11 bocas | E95: 10300 | F95: Importante: solo se admite la instalación de "punto más toma" en una caja rectangular en los baños de inmuebles. El toma ira conectado al circuito de iluminación. Las reglas del buen arte recomienda colocar el tomacorriente en una caja rectangular, en la zona 3 y conectado a un circuito de tomacorrientes. | G95: SI
A96: 10-06 | B96: EPAC | C96: Colocación de Interruptores, tomas, etc | D96: Instalación de tomacorrientes dobles entre 1 y 10 bocas | E96: 17600 | F96: Importante: solo se admite la instalación de "punto más toma" en una caja rectangular en los baños de inmuebles. El toma ira conectado al circuito de iluminación. Las reglas del buen arte recomienda colocar el tomacorriente en una caja rectangular, en la zona 3 y conectado a un circuito de tomacorrientes. | G96: SI
A97: 10-07 | B97: EPAC | C97: Colocación de Interruptores, tomas, etc | D97: Instalación de tomacorrientes dobles mas de 11 bocas | E97: 15300 | F97: Importante: solo se admite la instalación de "punto más toma" en una caja rectangular en los baños de inmuebles. El toma ira conectado al circuito de iluminación. Las reglas del buen arte recomienda colocar el tomacorriente en una caja rectangular, en la zona 3 y conectado a un circuito de tomacorrientes. | G97: SI
A98: 10-08 | B98: EPAC | C98: Colocación de Interruptores, tomas, etc | D98: Instalación de tomacorrientes cuádruples en cajas 100x100 | E98: 31100 | F98: Importante: solo se admite la instalación de "punto más toma" en una caja rectangular en los baños de inmuebles. El toma ira conectado al circuito de iluminación. Las reglas del buen arte recomienda colocar el tomacorriente en una caja rectangular, en la zona 3 y conectado a un circuito de tomacorrientes. | G98: SI
A99: 10-09 | B99: EPAC | C99: Colocación de Interruptores, tomas, etc | D99: Instalación de interruptores un efecto combinación doble | E99: 20500 | F99: Importante: solo se admite la instalación de "punto más toma" en una caja rectangular en los baños de inmuebles. El toma ira conectado al circuito de iluminación. Las reglas del buen arte recomienda colocar el tomacorriente en una caja rectangular, en la zona 3 y conectado a un circuito de tomacorrientes. | G99: SI
A100: 10-10 | B100: EPAC | C100: Colocación de Interruptores, tomas, etc | D100: Instalación de interruptores un efecto doble | E100: 14600 | F100: Importante: solo se admite la instalación de "punto más toma" en una caja rectangular en los baños de inmuebles. El toma ira conectado al circuito de iluminación. Las reglas del buen arte recomienda colocar el tomacorriente en una caja rectangular, en la zona 3 y conectado a un circuito de tomacorrientes. | G100: SI
A101: 10-11 | B101: EPAC | C101: Colocación de Interruptores, tomas, etc | D101: Instalación de interruptores un efecto triple | E101: 17600 | F101: Importante: solo se admite la instalación de "punto más toma" en una caja rectangular en los baños de inmuebles. El toma ira conectado al circuito de iluminación. Las reglas del buen arte recomienda colocar el tomacorriente en una caja rectangular, en la zona 3 y conectado a un circuito de tomacorrientes. | G101: SI
A102: 10-12 | B102: EPAC | C102: Colocación de Interruptores, tomas, etc | D102: Instalación de Regulador de velocidad ventilador o dimmer de Intensidad | E102: 20600 | F102: Importante: solo se admite la instalación de "punto más toma" en una caja rectangular en los baños de inmuebles. El toma ira conectado al circuito de iluminación. Las reglas del buen arte recomienda colocar el tomacorriente en una caja rectangular, en la zona 3 y conectado a un circuito de tomacorrientes. | G102: SI
... A104: 10-14 | B104: EPAC | C104: Colocación de Interruptores, tomas, etc | D104: Instalación de sensores de humo, gases, inundación, etc. en caja rect. | E104: 41300 | F104: Importante: solo se admite la instalación de "punto más toma" en una caja rectangular en los baños de inmuebles. El toma ira conectado al circuito de iluminación. Las reglas del buen arte recomienda colocar el tomacorriente en una caja rectangular, en la zona 3 y conectado a un circuito de tomacorrientes. | G104: SI
A105: 11-00 | B105: EPAC | D105: COLOCACIÓN DE ARTEFACTOS | E105: Importe Neto | F105: Notas Aclaratorias | G105: SI
A106: 11-01 | B106: EPAC | C106: Colocación de Artefactos | D106: Colocación de Artefacto tipo(aplique, extractores de baño, campanillas, etc.) | E106: 27900 | F106: Verificar la protección individual de cada artefacto (con fusibles ), pues la sección de los conductores del cableado interno del artefacto no están protegidos por los dispositivos instalados en los tableros . Estos interruptores están dimensionados según los conductores instalados en las canalizaciones. Por ejemplo una luminaria de tubos fluorescentes tienen conductores en su cableado interno de 0,5 mm2, y está conectado a un circuito con protecciones termomagnéticos de 2x10A, Es necesario entonces colocar un fusible de por lo menos 1A para evitar recalentamiento del cableado interno , posible foco de incendio. no contempla medios de elevación. Para elcaso de tiras led en perfil de aluminio incluye instalacion de la fuente correspondiente | G106: SI
A107: 11-02 | B107: EPAC | C107: Colocación de Artefactos | D107: Luminarias exterior montada en columna hasta 3 mts | E107: 86500 | F107: Verificar la protección individual de cada artefacto (con fusibles ), pues la sección de los conductores del cableado interno del artefacto no están protegidos por los dispositivos instalados en los tableros . Estos interruptores están dimensionados según los conductores instalados en las canalizaciones. Por ejemplo una luminaria de tubos fluorescentes tienen conductores en su cableado interno de 0,5 mm2, y está conectado a un circuito con protecciones termomagnéticos de 2x10A, Es necesario entonces colocar un fusible de por lo menos 1A para evitar recalentamiento del cableado interno , posible foco de incendio. no contempla medios de elevación. Para elcaso de tiras led en perfil de aluminio incluye instalacion de la fuente correspondiente | G107: SI
A108: 11-03 | B108: EPAC | C108: Colocación de Artefactos | D108: Luminarias exterior montada en Brazos hasta 4mts de altura amurado a pared o columna | E108: 86500 | F108: Verificar la protección individual de cada artefacto (con fusibles ), pues la sección de los conductores del cableado interno del artefacto no están protegidos por los dispositivos instalados en los tableros . Estos interruptores están dimensionados según los conductores instalados en las canalizaciones. Por ejemplo una luminaria de tubos fluorescentes tienen conductores en su cableado interno de 0,5 mm2, y está conectado a un circuito con protecciones termomagnéticos de 2x10A, Es necesario entonces colocar un fusible de por lo menos 1A para evitar recalentamiento del cableado interno , posible foco de incendio. no contempla medios de elevación. Para elcaso de tiras led en perfil de aluminio incluye instalacion de la fuente correspondiente | G108: SI
A109: 11-04 | B109: EPAC | C109: Colocación de Artefactos | D109: Luminarias exterior de aplicar en muro en intemperie (Ipx5 o Ipx6) | E109: 31000 | F109: Verificar la protección individual de cada artefacto (con fusibles ), pues la sección de los conductores del cableado interno del artefacto no están protegidos por los dispositivos instalados en los tableros . Estos interruptores están dimensionados según los conductores instalados en las canalizaciones. Por ejemplo una luminaria de tubos fluorescentes tienen conductores en su cableado interno de 0,5 mm2, y está conectado a un circuito con protecciones termomagnéticos de 2x10A, Es necesario entonces colocar un fusible de por lo menos 1A para evitar recalentamiento del cableado interno , posible foco de incendio. no contempla medios de elevación. Para elcaso de tiras led en perfil de aluminio incluye instalacion de la fuente correspondiente | G109: SI
...

Sheet Desplegables
A1: =Presupuesto!B15 -> Visita de inspeccion | B1: =Presupuesto!B16 -> Visita de Inspección - Bonificación | C1: =Presupuesto!B17 -> Recableado (incluye sacar artef, llaves y colocar nueva instalación) por Boca | D1: =Presupuesto!B18 -> Otros Descuentos 45 % | E1: =Presupuesto!B19 | F1: =Presupuesto!B20 | G1: =Presupuesto!B21 | H1: =Presupuesto!B22 | I1: =Presupuesto!B23 | J1: =Presupuesto!B24 | K1: =Presupuesto!B25 | L1: =Presupuesto!B26 | M1: =Presupuesto!B27 | N1: =Presupuesto!B28 | O1: =Presupuesto!B29 | P1: =Presupuesto!B30 | Q1: =Presupuesto!B31 | R1: =Presupuesto!B32 | S1: =Presupuesto!B33 | T1: =Presupuesto!B34 | U1: =Presupuesto!B35 | V1: =Presupuesto!B36 -> Acometida Trifásica aérea, hasta 10kw con sistema doble aislación | W1: =Presupuesto!B37 -> Acometida Trifásica de 11 a 35kw | X1: =Presupuesto!B38
A2: =IFERROR(__xludf.DUMMYFUNCTION("FILTER(Precios!$D$2:$D$574,A1=Precios!$C$2:$C$574,""SI""=Precios!$G2:$G574)"),"#N/A") -> #N/A | B2: =IFERROR(__xludf.DUMMYFUNCTION("FILTER(Precios!$D$2:$D$574,B1=Precios!$C$2:$C$574,""SI""=Precios!$G2:$G574)"),"#N/A") -> #N/A | C2: =IFERROR(__xludf.DUMMYFUNCTION("FILTER(Precios!$D$2:$D$574,C1=Precios!$C$2:$C$574,""SI""=Precios!$G2:$G574)"),"#N/A") -> #N/A | D2: =IFERROR(__xludf.DUMMYFUNCTION("FILTER(Precios!$D$2:$D$574,D1=Precios!$C$2:$C$574,""SI""=Precios!$G2:$G574)"),"#N/A") -> #N/A | E2: =IFERROR(__xludf.DUMMYFUNCTION("FILTER(Precios!$D$2:$D$574,E1=Precios!$C$2:$C$574,""SI""=Precios!$G2:$G574)"),"#N/A") -> #N/A | F2: =IFERROR(__xludf.DUMMYFUNCTION("FILTER(Precios!$D$2:$D$574,F1=Precios!$C$2:$C$574,""SI""=Precios!$G2:$G574)"),"#N/A") -> #N/A | G2: =IFERROR(__xludf.DUMMYFUNCTION("FILTER(Precios!$D$2:$D$574,G1=Precios!$C$2:$C$574,""SI""=Precios!$G2:$G574)"),"#N/A") -> #N/A | H2: =IFERROR(__xludf.DUMMYFUNCTION("FILTER(Precios!$D$2:$D$574,H1=Precios!$C$2:$C$574,""SI""=Precios!$G2:$G574)"),"#N/A") -> #N/A | I2: =IFERROR(__xludf.DUMMYFUNCTION("FILTER(Precios!$D$2:$D$574,I1=Precios!$C$2:$C$574,""SI""=Precios!$G2:$G574)"),"#N/A") -> #N/A | J2: =IFERROR(__xludf.DUMMYFUNCTION("FILTER(Precios!$D$2:$D$574,J1=Precios!$C$2:$C$574,""SI""=Precios!$G2:$G574)"),"#N/A") -> #N/A | K2: =IFERROR(__xludf.DUMMYFUNCTION("FILTER(Precios!$D$2:$D$574,K1=Precios!$C$2:$C$574,""SI""=Precios!$G2:$G574)"),"#N/A") -> #N/A | L2: =IFERROR(__xludf.DUMMYFUNCTION("FILTER(Precios!$D$2:$D$574,L1=Precios!$C$2:$C$574,""SI""=Precios!$G2:$G574)"),"#N/A") -> #N/A | M2: =IFERROR(__xludf.DUMMYFUNCTION("FILTER(Precios!$D$2:$D$574,M1=Precios!$C$2:$C$574,""SI""=Precios!$G2:$G574)"),"#N/A") -> #N/A | N2: =IFERROR(__xludf.DUMMYFUNCTION("FILTER(Precios!$D$2:$D$574,N1=Precios!$C$2:$C$574,""SI""=Precios!$G2:$G574)"),"#N/A") -> #N/A | O2: =IFERROR(__xludf.DUMMYFUNCTION("FILTER(Precios!$D$2:$D$574,O1=Precios!$C$2:$C$574,""SI""=Precios!$G2:$G574)"),"#N/A") -> #N/A | P2: =IFERROR(__xludf.DUMMYFUNCTION("FILTER(Precios!$D$2:$D$574,P1=Precios!$C$2:$C$574,""SI""=Precios!$G2:$G574)"),"#N/A") -> #N/A | Q2: =IFERROR(__xludf.DUMMYFUNCTION("FILTER(Precios!$D$2:$D$574,Q1=Precios!$C$2:$C$574,""SI""=Precios!$G2:$G574)"),"#N/A") -> #N/A | R2: =IFERROR(__xludf.DUMMYFUNCTION("FILTER(Precios!$D$2:$D$574,R1=Precios!$C$2:$C$574,""SI""=Precios!$G2:$G574)"),"#N/A") -> #N/A | S2: =IFERROR(__xludf.DUMMYFUNCTION("FILTER(Precios!$D$2:$D$574,S1=Precios!$C$2:$C$574,""SI""=Precios!$G2:$G574)"),"#N/A") -> #N/A | T2: =IFERROR(__xludf.DUMMYFUNCTION("FILTER(Precios!$D$2:$D$574,T1=Precios!$C$2:$C$574,""SI""=Precios!$G2:$G574)"),"#N/A") -> #N/A | U2: =IFERROR(__xludf.DUMMYFUNCTION("FILTER(Precios!$D$2:$D$574,U1=Precios!$C$2:$C$574,""SI""=Precios!$G2:$G574)"),"#N/A") -> #N/A | V2: =IFERROR(__xludf.DUMMYFUNCTION("FILTER(Precios!$D$2:$D$574,V1=Precios!$C$2:$C$574,""SI""=Precios!$G2:$G574)"),"#N/A") -> #N/A | W2: =IFERROR(__xludf.DUMMYFUNCTION("FILTER(Precios!$D$2:$D$574,W1=Precios!$C$2:$C$574,""SI""=Precios!$G2:$G574)"),"#N/A") -> #N/A | X2: =IFERROR(__xludf.DUMMYFUNCTION("FILTER(Precios!$D$2:$D$574,X1=Precios!$C$2:$C$574,""SI""=Precios!$G2:$G574)"),"CANALIZACIÓN EMBUTIDA") -> CANALIZACIÓN EMBUTIDA
X3: =IFERROR(__xludf.DUMMYFUNCTION("""COMPUTED_VALUE"""),"CANALIZACIÓN EMBUTIDA EN DURLOCK") -> CANALIZACIÓN EMBUTIDA EN DURLOCK
X4: =IFERROR(__xludf.DUMMYFUNCTION("""COMPUTED_VALUE"""),"CANALIZACIÓN EXTERIOR ") -> CANALIZACIÓN EXTERIOR
X5: =IFERROR(__xludf.DUMMYFUNCTION("""COMPUTED_VALUE"""),"CANALIZACIÓN DE CABLE CANAL") -> CANALIZACIÓN DE CABLE CANAL
X6: =IFERROR(__xludf.DUMMYFUNCTION("""COMPUTED_VALUE"""),"CANALIZACIÓN Y CABLEADO CON PISO DUCTOS / POLIDUCTOS ") -> CANALIZACIÓN Y CABLEADO CON PISO DUCTOS / POLIDUCTOS
X7: =IFERROR(__xludf.DUMMYFUNCTION("""COMPUTED_VALUE"""),"CANALIZACIÓN CON BANDEJAS PORTA CABLES Y PERFIL C") -> CANALIZACIÓN CON BANDEJAS PORTA CABLES Y PERFIL C
X8: =IFERROR(__xludf.DUMMYFUNCTION("""COMPUTED_VALUE"""),"CABLEADOS EN CAÑERÍAS ") -> CABLEADOS EN CAÑERÍAS
X9: =IFERROR(__xludf.DUMMYFUNCTION("""COMPUTED_VALUE"""),"CABLEADO EN BANDEJAS PORTA CABLES ") -> CABLEADO EN BANDEJAS PORTA CABLES
X10: =IFERROR(__xludf.DUMMYFUNCTION("""COMPUTED_VALUE"""),"COLOCACIÓN DE INTERRUPTORES, TOMAS, ETC.") -> COLOCACIÓN DE INTERRUPTORES, TOMAS, ETC.
X11: =IFERROR(__xludf.DUMMYFUNCTION("""COMPUTED_VALUE"""),"COLOCACIÓN DE ARTEFACTOS") -> COLOCACIÓN DE ARTEFACTOS
X12: =IFERROR(__xludf.DUMMYFUNCTION("""COMPUTED_VALUE"""),"COLOCACIÓN DE ELEMENTOS DE PROTECCIÓN Y COMANDO") -> COLOCACIÓN DE ELEMENTOS DE PROTECCIÓN Y COMANDO
X13: =IFERROR(__xludf.DUMMYFUNCTION("""COMPUTED_VALUE"""),"TABLERO DE COMANDO DE MOTORES") -> TABLERO DE COMANDO DE MOTORES
X14: =IFERROR(__xludf.DUMMYFUNCTION("""COMPUTED_VALUE"""),"EMERGENCIAS ") -> EMERGENCIAS
X15: =IFERROR(__xludf.DUMMYFUNCTION("""COMPUTED_VALUE"""),"MANTENIMIENTO DE TABLEROS ELÉCTRICOS E INSTALACIONES ELECTRICAS") -> MANTENIMIENTO DE TABLEROS ELÉCTRICOS E INSTALACIONES ELECTRICAS
X16: =IFERROR(__xludf.DUMMYFUNCTION("""COMPUTED_VALUE"""),"VARIOS BAJA TENSIÓN ") -> VARIOS BAJA TENSIÓN
X17: =IFERROR(__xludf.DUMMYFUNCTION("""COMPUTED_VALUE"""),"COLOCACIÓN DE PORTERO ELÉCTRICO UNIFAMILIAR") -> COLOCACIÓN DE PORTERO ELÉCTRICO UNIFAMILIAR
X18: =IFERROR(__xludf.DUMMYFUNCTION("""COMPUTED_VALUE"""),"COLOCACIÓN DE PORTERO ELÉCTRICO EN EDIFICIO (AUDIO SOLO) MULTIFAMILIAR") -> COLOCACIÓN DE PORTERO ELÉCTRICO EN EDIFICIO (AUDIO SOLO) MULTIFAMILIAR
X19: =IFERROR(__xludf.DUMMYFUNCTION("""COMPUTED_VALUE"""),"SISTEMAS DE SEGURIDAD") -> SISTEMAS DE SEGURIDAD
X20: =IFERROR(__xludf.DUMMYFUNCTION("""COMPUTED_VALUE"""),"VARIOS CORRIENTES DÉBILES ") -> VARIOS CORRIENTES DÉBILES
X21: =IFERROR(__xludf.DUMMYFUNCTION("""COMPUTED_VALUE"""),"COMPUESTO DE INSTALACONES EMBUTIDAS") -> COMPUESTO DE INSTALACONES EMBUTIDAS
X22: =IFERROR(__xludf.DUMMYFUNCTION("""COMPUTED_VALUE"""),"COMPUESTO DE CANALIZACIÓN EXTERIOR ") -> COMPUESTO DE CANALIZACIÓN EXTERIOR
X23: =IFERROR(__xludf.DUMMYFUNCTION("""COMPUTED_VALUE"""),"COMPUESTO DE INSTALACIONES CON CABLE CANAL") -> COMPUESTO DE INSTALACIONES CON CABLE CANAL
X24: =IFERROR(__xludf.DUMMYFUNCTION("""COMPUTED_VALUE"""),"COMPUESTO ACOMETIDA") -> COMPUESTO ACOMETIDA
X25: =IFERROR(__xludf.DUMMYFUNCTION("""COMPUTED_VALUE"""),"PERSONAL CONTRATADO") -> PERSONAL CONTRATADO
X26: =IFERROR(__xludf.DUMMYFUNCTION("""COMPUTED_VALUE"""),"Nueva Categoría ") -> Nueva Categoría
X27: =IFERROR(__xludf.DUMMYFUNCTION("""COMPUTED_VALUE"""),"PURIFICACION (EI)") -> PURIFICACION (EI)
X28: =IFERROR(__xludf.DUMMYFUNCTION("""COMPUTED_VALUE"""),"ELECTROINSTALADOR (Otros)") -> ELECTROINSTALADOR (Otros)

Sheet Presupuesto
A1: Presupuesto
A2: Nro Presupuesto | F2: =IFERROR(UPPER(CONCATENATE(LEFT(F6,2),MID(F6,SEARCH(" ",F6)+1,1),"-",TEXT(F4,"DD"),TEXT(F4,"MM"))), "") -> PEM-1402
A4: Fecha | F4: =Carga!B2 -> 46067
A6: Cliente | F6: =Carga!B3 -> Pepito monje
A8: Dirección obra | F8: =Carga!B4 -> Guntanamera 1020
A12: Codigo | C12: Concepto | H12: Cantidad | K12: Valor | L12: Subtotal
A15: =IFERROR(VLOOKUP(Carga!B8,Precios!D:F,5,0), "") | B15: =CONCATENATE(Carga!B8," ",Carga!C8," ",Carga!D8," ",Carga!E8) -> Visita de inspeccion | H15: =Carga!F8 -> 1 | I15: =IFERROR(VLOOKUP(Carga!B8,Precios!D:F,4,0), "") | K15: =IFERROR(VLOOKUP(Carga!B8,Precios!D:E,2,0), "") | L15: =Carga!M8
A16: =IFERROR(VLOOKUP(Carga!B9,Precios!D:F,5,0), "") | B16: =CONCATENATE(Carga!B9," ",Carga!C9," ",Carga!D9," ",Carga!E9) -> Visita de Inspección - Bonificación | H16: =Carga!F9 -> 1 | I16: =IFERROR(VLOOKUP(Carga!B9,Precios!D:F,4,0), "") | K16: =IFERROR(VLOOKUP(Carga!B9,Precios!D:E,2,0), "") | L16: =Carga!M9
A17: =IFERROR(VLOOKUP(Carga!B10,Precios!D:F,5,0), "") | B17: =CONCATENATE(Carga!B10," ",Carga!C10," ",Carga!D10," ",Carga!E10) -> Recableado (incluye sacar artef, llaves y colocar nueva instalación) por Boca | H17: =Carga!F10 -> 1 | I17: =IFERROR(VLOOKUP(Carga!B10,Precios!D:F,4,0), "") | K17: =IFERROR(VLOOKUP(Carga!B10,Precios!D:E,2,0), "") -> 56500 | L17: =Carga!M10 -> 56500
A18: =IFERROR(VLOOKUP(Carga!B11,Precios!D:F,5,0), "") | B18: =CONCATENATE(Carga!B11," ",Carga!C11," ",Carga!D11," ",Carga!E11) -> Otros Descuentos 45 % | H18: =Carga!F11 | I18: =IFERROR(VLOOKUP(Carga!B11,Precios!D:F,4,0), "") | K18: =IFERROR(VLOOKUP(Carga!B11,Precios!D:E,2,0), "") | L18: =Carga!M11 -> -155475
A19: =IFERROR(VLOOKUP(Carga!B12,Precios!D:F,5,0), "") | B19: =CONCATENATE(Carga!B12," ",Carga!C12," ",Carga!D12," ",Carga!E12) | H19: =Carga!F12 | I19: =IFERROR(VLOOKUP(Carga!B12,Precios!D:F,4,0), "") | K19: =IFERROR(VLOOKUP(Carga!B12,Precios!D:E,2,0), "") | L19: =Carga!M12
A20: =IFERROR(VLOOKUP(Carga!B13,Precios!D:F,5,0), "") | B20: =CONCATENATE(Carga!B13," ",Carga!C13," ",Carga!D13," ",Carga!E13) | H20: =Carga!F13 | I20: =IFERROR(VLOOKUP(Carga!B13,Precios!D:F,4,0), "") | K20: =IFERROR(VLOOKUP(Carga!B13,Precios!D:E,2,0), "") | L20: =Carga!M13
A21: =IFERROR(VLOOKUP(Carga!B14,Precios!D:F,5,0), "") | B21: =CONCATENATE(Carga!B14," ",Carga!C14," ",Carga!D14," ",Carga!E14) | H21: =Carga!F14 | I21: =IFERROR(VLOOKUP(Carga!B14,Precios!D:F,4,0), "") | K21: =IFERROR(VLOOKUP(Carga!B14,Precios!D:E,2,0), "") | L21: =Carga!M14
A22: =IFERROR(VLOOKUP(Carga!B15,Precios!D:F,5,0), "") | B22: =CONCATENATE(Carga!B15," ",Carga!C15," ",Carga!D15," ",Carga!E15) | H22: =Carga!F15 | I22: =IFERROR(VLOOKUP(Carga!B15,Precios!D:F,4,0), "") | K22: =IFERROR(VLOOKUP(Carga!B15,Precios!D:E,2,0), "") | L22: =Carga!M15
A23: =IFERROR(VLOOKUP(Carga!B16,Precios!D:F,5,0), "") | B23: =CONCATENATE(Carga!B16," ",Carga!C16," ",Carga!D16," ",Carga!E16) | H23: =Carga!F16 | I23: =IFERROR(VLOOKUP(Carga!B16,Precios!D:F,4,0), "") | K23: =IFERROR(VLOOKUP(Carga!B16,Precios!D:E,2,0), "") | L23: =Carga!M16
A24: =IFERROR(VLOOKUP(Carga!B17,Precios!D:F,5,0), "") | B24: =CONCATENATE(Carga!B17," ",Carga!C17," ",Carga!D17," ",Carga!E17) | H24: =Carga!F17 | I24: =IFERROR(VLOOKUP(Carga!B17,Precios!D:F,4,0), "") | K24: =IFERROR(VLOOKUP(Carga!B17,Precios!D:E,2,0), "") | L24: =Carga!M17
A25: =IFERROR(VLOOKUP(Carga!B18,Precios!D:F,5,0), "") | B25: =CONCATENATE(Carga!B18," ",Carga!C18," ",Carga!D18," ",Carga!E18) | H25: =Carga!F18 | I25: =IFERROR(VLOOKUP(Carga!B18,Precios!D:F,4,0), "") | K25: =IFERROR(VLOOKUP(Carga!B18,Precios!D:E,2,0), "") | L25: =Carga!M18
A26: =IFERROR(VLOOKUP(Carga!B19,Precios!D:F,5,0), "") | B26: =CONCATENATE(Carga!B19," ",Carga!C19," ",Carga!D19," ",Carga!E19) | H26: =Carga!F19 | I26: =IFERROR(VLOOKUP(Carga!B19,Precios!D:F,4,0), "") | K26: =IFERROR(VLOOKUP(Carga!B19,Precios!D:E,2,0), "") | L26: =Carga!M19
... A37: =IFERROR(VLOOKUP(Carga!B30,Precios!D:F,5,0), "") | B37: =CONCATENATE(Carga!B30," ",Carga!C30," ",Carga!D30," ",Carga!E30) -> Acometida Trifásica de 11 a 35kw | H37: =Carga!F30 -> 1 | I37: =IFERROR(VLOOKUP(Carga!B30,Precios!D:F,4,0), "") | K37: =IFERROR(VLOOKUP(Carga!B30,Precios!D:E,2,0), "") -> 289000 | L37: =Carga!M30 -> 289000
A38: Notas Aclaratorias por codigos
K40: =SUM(L15:L37) -> 190025
A41: =IF(Nota!E24=0, "",Nota!E24) -> / / / / / / / / / / / / / / / / / / / / / / / | K41: Subtotal | L41: =Carga!M34 -> 345500
K42: Descuentos | L42: =Carga!M35 -> -155475
K44: Total
K45: =Carga!M37 -> 190025
A47: Formas De Pago
A49: Efectivo / Transferencia / QR | G49: Descuentos
A51: Cuotas, hasta 3 y 6 sin interés | G51: Con Mercado Pago
A53: ¡Electricidad Segura, Hogar Tranquilo!

Sheet Blok Presupuesto
A1: Presupuesto
A2: Nro Presupuesto | F2: =IFERROR(UPPER(CONCATENATE(LEFT(F6,2),MID(F6,SEARCH(" ",F6)+1,1),"-",TEXT(F4,"DD"),TEXT(F4,"MM"))), "") -> PEM-1402
A4: Fecha | F4: =Carga!B2 -> 46067
A6: Cliente | F6: =Carga!B3 -> Pepito monje
A8: Dirección obra | F8: =Carga!B4 -> Guntanamera 1020
A12: Codigo | C12: Concepto | H12: Cantidad | K12: Valor | L12: Subtotal
A15: =IFERROR(VLOOKUP(B15,Precios!D:F,5,0), "") | B15: =Copia_de_Carga!B8 -> 46072 | H15: =Copia_de_Carga!F8 -> Villagrono Alfredus | I15: =IFERROR(VLOOKUP(Carga!B8,Precios!D:F,4,0), "") | K15: =IFERROR(VLOOKUP(Copia_de_Carga!B8,Precios!D:E,2,0), "") | L15: =Copia_de_Carga!M8 -> #VALUE!
A16: =IFERROR(VLOOKUP(B16,Precios!D:F,5,0), "") | B16: =Copia_de_Carga!B9 -> Instalación a altura h<4mts con perfil C P/ BPC 100 a 300 | H16: =Copia_de_Carga!F9 -> 1 | I16: =IFERROR(VLOOKUP(Carga!B9,Precios!D:F,4,0), "") | K16: =IFERROR(VLOOKUP(Copia_de_Carga!B9,Precios!D:E,2,0), "") -> 51700 | L16: =Copia_de_Carga!M9 -> #VALUE!
A17: =IFERROR(VLOOKUP(B17,Precios!D:F,5,0), "") | B17: =Copia_de_Carga!B10 -> Instalación a altura h<4mts con perfil C P/ BPC 100 a 300 | H17: =Copia_de_Carga!F10 -> 1 | I17: =IFERROR(VLOOKUP(Carga!B10,Precios!D:F,4,0), "") | K17: =IFERROR(VLOOKUP(Copia_de_Carga!B10,Precios!D:E,2,0), "") -> 51700 | L17: =Copia_de_Carga!M10 -> #VALUE!
A18: =IFERROR(VLOOKUP(B18,Precios!D:F,5,0), "") | B18: =Copia_de_Carga!B11 -> Instalación a altura h<4mts con perfil C P/ BPC 100 a 300 | H18: =Copia_de_Carga!F11 -> 1 | I18: =IFERROR(VLOOKUP(Carga!B11,Precios!D:F,4,0), "") | K18: =IFERROR(VLOOKUP(Copia_de_Carga!B11,Precios!D:E,2,0), "") -> 51700 | L18: =Copia_de_Carga!M11 -> #VALUE!
A19: =IFERROR(VLOOKUP(B19,Precios!D:F,5,0), "") | B19: =Copia_de_Carga!B12 -> Instalación a altura h<4mts con perfil C P/ BPC 100 a 300 | H19: =Copia_de_Carga!F12 -> 1 | I19: =IFERROR(VLOOKUP(Carga!B12,Precios!D:F,4,0), "") | K19: =IFERROR(VLOOKUP(Copia_de_Carga!B12,Precios!D:E,2,0), "") -> 51700 | L19: =Copia_de_Carga!M12 -> #VALUE!
A20: =IFERROR(VLOOKUP(B20,Precios!D:F,5,0), "") | B20: =Copia_de_Carga!B13 -> Instalación a altura h<4mts con perfil C P/ BPC 100 a 300 | H20: =Copia_de_Carga!F13 -> 1 | I20: =IFERROR(VLOOKUP(Carga!B13,Precios!D:F,4,0), "") | K20: =IFERROR(VLOOKUP(Copia_de_Carga!B13,Precios!D:E,2,0), "") -> 51700 | L20: =Copia_de_Carga!M13 -> #VALUE!
A21: =IFERROR(VLOOKUP(B21,Precios!D:F,5,0), "") | B21: =Copia_de_Carga!B14 -> Instalación a altura h<4mts con perfil C P/ BPC 100 a 300 | H21: =Copia_de_Carga!F14 -> 1 | I21: =IFERROR(VLOOKUP(Carga!B14,Precios!D:F,4,0), "") | K21: =IFERROR(VLOOKUP(Copia_de_Carga!B14,Precios!D:E,2,0), "") -> 51700 | L21: =Copia_de_Carga!M14 -> #VALUE!
A22: =IFERROR(VLOOKUP(B22,Precios!D:F,5,0), "") | B22: =Copia_de_Carga!B15 -> Certificacion de vivienda o local comercial (hasta 20bocas) no incluye adecuacion de la instalacion | H22: =Copia_de_Carga!F15 -> -2 | I22: =IFERROR(VLOOKUP(Carga!B15,Precios!D:F,4,0), "") | K22: =IFERROR(VLOOKUP(Copia_de_Carga!B15,Precios!D:E,2,0), "") | L22: =Copia_de_Carga!M15 -> #VALUE!
A23: =IFERROR(VLOOKUP(B23,Precios!D:F,5,0), "") | B23: =Copia_de_Carga!B16 -> Certificacion de vivienda o local comercial (hasta 20bocas) no incluye adecuacion de la instalacion | H23: =Copia_de_Carga!F16 -> -2 | I23: =IFERROR(VLOOKUP(Carga!B16,Precios!D:F,4,0), "") | K23: =IFERROR(VLOOKUP(Copia_de_Carga!B16,Precios!D:E,2,0), "") | L23: =Copia_de_Carga!M16 -> #VALUE!
A24: =IFERROR(VLOOKUP(B24,Precios!D:F,5,0), "") | B24: =Copia_de_Carga!B17 -> Certificacion de vivienda o local comercial (hasta 20bocas) no incluye adecuacion de la instalacion | H24: =Copia_de_Carga!F17 -> -2 | I24: =IFERROR(VLOOKUP(Carga!B17,Precios!D:F,4,0), "") | K24: =IFERROR(VLOOKUP(Copia_de_Carga!B17,Precios!D:E,2,0), "") | L24: =Copia_de_Carga!M17 -> #VALUE!
A25: =IFERROR(VLOOKUP(B25,Precios!D:F,5,0), "") | B25: =Copia_de_Carga!B18 -> Certificacion de vivienda o local comercial (hasta 20bocas) no incluye adecuacion de la instalacion | H25: =Copia_de_Carga!F18 -> -2 | I25: =IFERROR(VLOOKUP(Carga!B18,Precios!D:F,4,0), "") | K25: =IFERROR(VLOOKUP(Copia_de_Carga!B18,Precios!D:E,2,0), "") | L25: =Copia_de_Carga!M18 -> #VALUE!
A26: =IFERROR(VLOOKUP(B26,Precios!D:F,5,0), "") | B26: =Copia_de_Carga!B19 -> Certificacion de vivienda o local comercial (hasta 20bocas) no incluye adecuacion de la instalacion | H26: =Copia_de_Carga!F19 -> -2 | I26: =IFERROR(VLOOKUP(Carga!B19,Precios!D:F,4,0), "") | K26: =IFERROR(VLOOKUP(Copia_de_Carga!B19,Precios!D:E,2,0), "") | L26: =Copia_de_Carga!M19 -> #VALUE!
... A37: =IFERROR(VLOOKUP(B37,Precios!D:F,5,0), "") | B37: =Copia_de_Carga!B30 -> Certificacion de vivienda o local comercial (hasta 20bocas) no incluye adecuacion de la instalacion | H37: =Copia_de_Carga!F30 -> -2 | I37: =IFERROR(VLOOKUP(Carga!B30,Precios!D:F,4,0), "") | K37: =IFERROR(VLOOKUP(Copia_de_Carga!B30,Precios!D:E,2,0), "") | L37: =Copia_de_Carga!M30 -> #VALUE!
A38: Notas Aclaratorias por codigos
K40: =SUM(L15:L37) -> #VALUE!
A41: =IF(Nota!E24=0, "",Nota!E24) -> / / / / / / / / / / / / / / / / / / / / / / / | K41: Subtotal | L41: =Carga!M34 -> 345500
K42: Descuentos | L42: =Carga!M35 -> -155475
K44: Total
K45: =Carga!M37 -> 190025
A47: Formas De Pago
A49: Efectivo / Transferencia / QR | G49: Descuentos
A51: Cuotas, hasta 3 y 6 sin interés | G51: Con Mercado Pago
A53: ¡Electricidad Segura, Hogar Tranquilo!
